Workbook
Name budget: 'Budget Dashboard'!$L1
Name current_date: TODAY()
Name expenses_header_row: ROW(expenses[[#Headers],[Expenses]])
Name expenses_max_row: MAX(ROW(expenses[]))
Name expenses_min_row: MIN(ROW(expenses[]))
Name expenses_total_row: ROW('Budget Planning'!$C$48)
Name income_header_row: ROW(income[[#Headers],[Income]])
Name income_max_row: MAX(ROW(income[]))
Name income_min_row: MIN(ROW(income[]))
Name income_total_row: ROW('Budget Planning'!$C$22)
Name item: 'Budget Dashboard'!$J1
Name savings_header_row: ROW(savings[[#Headers],[Savings]])
Name savings_max_row: MAX(ROW(savings[]))
Name savings_min_row: MIN(ROW(savings[]))
Name savings_rate_calculation_type: Settings!$E$22
Name savings_total_row: ROW('Budget Planning'!$C$60)
Name selected_period: Calculation!$E$20
Name selected_period_display: Calculation!$E$21
Name selected_year: Calculation!$E$19
Name shift_late_income_starting_day: Settings!$E$18
Name shift_late_income_status: Settings!$E$16
Name starting_year: Settings!$E$8
Name tracked: 'Budget Dashboard'!$K1
Name type: 'Budget Dashboard'!$I1
Name budget_range: 'Budget Dashboard'!$Q1
Name budget_rank: 'Budget Dashboard'!$R1
Name comb_rank: 'Budget Dashboard'!$S1
Name comb_rank_norm: 'Budget Dashboard'!$U1
Name comb_rank_norm_run_range: 'Budget Dashboard'!$V1
Name comb_rank_range: 'Budget Dashboard'!$T1
Name comb_rank_unique: 'Budget Dashboard'!$W1
Name header_row_id: 'Budget Dashboard'!$D1
Name is_cat: 'Budget Dashboard'!$F1
Name is_empty: 'Budget Dashboard'!$H1
Name is_header: 'Budget Dashboard'!$E1
Name is_total: 'Budget Dashboard'!$G1
Name out_budget: 'Budget Dashboard'!$AA1
Name out_percentage_completed: 'Budget Dashboard'!$AB1
Name out_tracked: 'Budget Dashboard'!$Z1
Name row_id: 'Budget Dashboard'!$C1
Name sort_max_row: 'Budget Dashboard'!$N1
Name sort_min_row: 'Budget Dashboard'!$M1
Name tracked_range: 'Budget Dashboard'!$O1
Name tracked_rank: 'Budget Dashboard'!$P1
Name cc_budget: Calculation!$K1
Name cc_delta: Calculation!$L1
Name cc_in_focus: Calculation!$G1
Name cc_month_number: Calculation!$F1
Name cc_show_rem_budget: Calculation!$I1
Name cc_show_type: Calculation!$H1
Name cc_tracked: Calculation!$J1
Name cc_type: Calculation!$E1

Sheet Settings
B1: Settings
C6: General
D8: Starting Year: | E8: 2025 | G8: Set the starting year (yyyy) once at the beginning and do not change it again.
C12: Budget Tracking & Dashboard
D14: Late Monthly Income
D16: Shift Late Income: | E16: Inactive | G16: Activate this option to treat late income received on or after a certain day of the month as income for the next month. This is especially recommended in case you receive your monthly paycheck towards the end of the month and prefer to consider this income as the disposable income for the next month.
D18: Starting on day x in month: | E18: 20
D20: KPI Calculation in Dashboard
D22: Savings Rate as % of Income: | E22: % allocated to Savings | G22: Choose how you want the savings rate (SR) to be calculated in the dashboard KPI tiles: 1) Active Option (% allocated to Savings): SR = Savings/Income 2) Passive Option (% not allocated to Expenses): SR = (Income - Expenses) / Income

Sheet Budget Planning
B1: Budget Planning
C5: Define starting year in Settings --> | E5: =starting_year | S5: =E5+1 | AG5: =S5+1 | AU5: =AG5+1 | BI5: =AU5+1 | BW5: =BI5+1 | CK5: =BW5+1 | CY5: =CK5+1 | DM5: =CY5+1 | EA5: =DM5+1
E6: =IF(E7=0, "Jan✓", "Jan") | F6: =IF(F7=0, "Feb✓", "Feb") | G6: =IF(G7=0, "Mar✓", "Mar") | H6: =IF(H7=0, "Apr✓", "Apr") | I6: =IF(I7=0, "May✓", "May") | J6: =IF(J7=0, "Jun✓", "Jun") | K6: =IF(K7=0, "Jul✓", "Jul") | L6: =IF(L7=0, "Aug✓", "Aug") | M6: =IF(M7=0, "Sep✓", "Sep") | N6: =IF(N7=0, "Oct✓", "Oct") | O6: =IF(O7=0, "Nov✓", "Nov") | P6: =IF(P7=0, "Dec✓", "Dec") | Q6: =IF(Q7=0, "Total✓", "Total") | S6: =IF(S7=0, "Jan✓", "Jan") | T6: =IF(T7=0, "Feb✓", "Feb") | U6: =IF(U7=0, "Mar✓", "Mar") | V6: =IF(V7=0, "Apr✓", "Apr") | W6: =IF(W7=0, "May✓", "May") | X6: =IF(X7=0, "Jun✓", "Jun") | Y6: =IF(Y7=0, "Jul✓", "Jul") | Z6: =IF(Z7=0, "Aug✓", "Aug") | AA6: =IF(AA7=0, "Sep✓", "Sep") | AB6: =IF(AB7=0, "Oct✓", "Oct") | AC6: =IF(AC7=0, "Nov✓", "Nov") | AD6: =IF(AD7=0, "Dec✓", "Dec") | AE6: =IF(AE7=0, "Total✓", "Total") | AG6: =IF(AG7=0, "Jan✓", "Jan") | AH6: =IF(AH7=0, "Feb✓", "Feb") | AI6: =IF(AI7=0, "Mar✓", "Mar") | AJ6: =IF(AJ7=0, "Apr✓", "Apr") | AK6: =IF(AK7=0, "May✓", "May") | AL6: =IF(AL7=0, "Jun✓", "Jun") | AM6: =IF(AM7=0, "Jul✓", "Jul") | AN6: =IF(AN7=0, "Aug✓", "Aug") | AO6: =IF(AO7=0, "Sep✓", "Sep") | AP6: =IF(AP7=0, "Oct✓", "Oct") | AQ6: =IF(AQ7=0, "Nov✓", "Nov") | AR6: =IF(AR7=0, "Dec✓", "Dec") | AS6: =IF(AS7=0, "Total✓", "Total") | AU6: =IF(AU7=0, "Jan✓", "Jan") | AV6: =IF(AV7=0, "Feb✓", "Feb") | AW6: =IF(AW7=0, "Mar✓", "Mar") | AX6: =IF(AX7=0, "Apr✓", "Apr") | AY6: =IF(AY7=0, "May✓", "May") | AZ6: =IF(AZ7=0, "Jun✓", "Jun") | BA6: =IF(BA7=0, "Jul✓", "Jul") | BB6: =IF(BB7=0, "Aug✓", "Aug") | BC6: =IF(BC7=0, "Sep✓", "Sep") | BD6: =IF(BD7=0, "Oct✓", "Oct") | BE6: =IF(BE7=0, "Nov✓", "Nov") | BF6: =IF(BF7=0, "Dec✓", "Dec") | BG6: =IF(BG7=0, "Total✓", "Total") | BI6: =IF(BI7=0, "Jan✓", "Jan") | BJ6: =IF(BJ7=0, "Feb✓", "Feb") | BK6: =IF(BK7=0, "Mar✓", "Mar") | BL6: =IF(BL7=0, "Apr✓", "Apr") | BM6: =IF(BM7=0, "May✓", "May") | BN6: =IF(BN7=0, "Jun✓", "Jun") | BO6: =IF(BO7=0, "Jul✓", "Jul") | BP6: =IF(BP7=0, "Aug✓", "Aug") | BQ6: =IF(BQ7=0, "Sep✓", "Sep") | BR6: =IF(BR7=0, "Oct✓", "Oct") | BS6: =IF(BS7=0, "Nov✓", "Nov") | BT6: =IF(BT7=0, "Dec✓", "Dec") | BU6: =IF(BU7=0, "Total✓", "Total") | BW6: =IF(BW7=0, "Jan✓", "Jan") | BX6: =IF(BX7=0, "Feb✓", "Feb") | BY6: =IF(BY7=0, "Mar✓", "Mar") | BZ6: =IF(BZ7=0, "Apr✓", "Apr") | CA6: =IF(CA7=0, "May✓", "May") | CB6: =IF(CB7=0, "Jun✓", "Jun") | CC6: =IF(CC7=0, "Jul✓", "Jul") | CD6: =IF(CD7=0, "Aug✓", "Aug") | CE6: =IF(CE7=0, "Sep✓", "Sep") | CF6: =IF(CF7=0, "Oct✓", "Oct") | CG6: =IF(CG7=0, "Nov✓", "Nov") | CH6: =IF(CH7=0, "Dec✓", "Dec") | CI6: =IF(CI7=0, "Total✓", "Total") | CK6: =IF(CK7=0, "Jan✓", "Jan") | CL6: =IF(CL7=0, "Feb✓", "Feb") | CM6: =IF(CM7=0, "Mar✓", "Mar") | CN6: =IF(CN7=0, "Apr✓", "Apr") | CO6: =IF(CO7=0, "May✓", "May") | CP6: =IF(CP7=0, "Jun✓", "Jun") | CQ6: =IF(CQ7=0, "Jul✓", "Jul") | CR6: =IF(CR7=0, "Aug✓", "Aug") | CS6: =IF(CS7=0, "Sep✓", "Sep") | CT6: =IF(CT7=0, "Oct✓", "Oct") | CU6: =IF(CU7=0, "Nov✓", "Nov") | CV6: =IF(CV7=0, "Dec✓", "Dec") | CW6: =IF(CW7=0, "Total✓", "Total") | CY6: =IF(CY7=0, "Jan✓", "Jan") | CZ6: =IF(CZ7=0, "Feb✓", "Feb") | DA6: =IF(DA7=0, "Mar✓", "Mar") | DB6: =IF(DB7=0, "Apr✓", "Apr") | DC6: =IF(DC7=0, "May✓", "May") | DD6: =IF(DD7=0, "Jun✓", "Jun") | DE6: =IF(DE7=0, "Jul✓", "Jul") | DF6: =IF(DF7=0, "Aug✓", "Aug") | DG6: =IF(DG7=0, "Sep✓", "Sep") | DH6: =IF(DH7=0, "Oct✓", "Oct") | DI6: =IF(DI7=0, "Nov✓", "Nov") | DJ6: =IF(DJ7=0, "Dec✓", "Dec") | DK6: =IF(DK7=0, "Total✓", "Total") | DM6: =IF(DM7=0, "Jan✓", "Jan") | DN6: =IF(DN7=0, "Feb✓", "Feb") | DO6: =IF(DO7=0, "Mar✓", "Mar") | DP6: =IF(DP7=0, "Apr✓", "Apr") | DQ6: =IF(DQ7=0, "May✓", "May") | DR6: =IF(DR7=0, "Jun✓", "Jun") | DS6: =IF(DS7=0, "Jul✓", "Jul") | DT6: =IF(DT7=0, "Aug✓", "Aug") | DU6: =IF(DU7=0, "Sep✓", "Sep") | DV6: =IF(DV7=0, "Oct✓", "Oct") | DW6: =IF(DW7=0, "Nov✓", "Nov") | DX6: =IF(DX7=0, "Dec✓", "Dec") | DY6: =IF(DY7=0, "Total✓", "Total") | EA6: =IF(EA7=0, "Jan✓", "Jan") | EB6: =IF(EB7=0, "Feb✓", "Feb") | EC6: =IF(EC7=0, "Mar✓", "Mar") | ED6: =IF(ED7=0, "Apr✓", "Apr") | EE6: =IF(EE7=0, "May✓", "May") | EF6: =IF(EF7=0, "Jun✓", "Jun") | EG6: =IF(EG7=0, "Jul✓", "Jul") | EH6: =IF(EH7=0, "Aug✓", "Aug") | EI6: =IF(EI7=0, "Sep✓", "Sep") | EJ6: =IF(EJ7=0, "Oct✓", "Oct") | EK6: =IF(EK7=0, "Nov✓", "Nov") | EL6: =IF(EL7=0, "Dec✓", "Dec") | EM6: =IF(EM7=0, "Total✓", "Total")
C7: To be allocated: | E7: =E22-(E48+E60) | F7: =F22-(F48+F60) | G7: =G22-(G48+G60) | H7: =H22-(H48+H60) | I7: =I22-(I48+I60) | J7: =J22-(J48+J60) | K7: =K22-(K48+K60) | L7: =L22-(L48+L60) | ... Q7: =Q22-(Q48+Q60) | S7: =S22-(S48+S60) | T7: =T22-(T48+T60) | U7: =U22-(U48+U60) | V7: =V22-(V48+V60) | W7: =W22-(W48+W60) | X7: =X22-(X48+X60) | Y7: =Y22-(Y48+Y60) | Z7: =Z22-(Z48+Z60) | ... AE7: =AE22-(AE48+AE60) | AG7: =AG22-(AG48+AG60) | AH7: =AH22-(AH48+AH60) | AI7: =AI22-(AI48+AI60) | AJ7: =AJ22-(AJ48+AJ60) | AK7: =AK22-(AK48+AK60) | AL7: =AL22-(AL48+AL60) | AM7: =AM22-(AM48+AM60) | AN7: =AN22-(AN48+AN60) | ... AS7: =AS22-(AS48+AS60) | AU7: =AU22-(AU48+AU60) | AV7: =AV22-(AV48+AV60) | AW7: =AW22-(AW48+AW60) | AX7: =AX22-(AX48+AX60) | AY7: =AY22-(AY48+AY60) | AZ7: =AZ22-(AZ48+AZ60) | BA7: =BA22-(BA48+BA60) | BB7: =BB22-(BB48+BB60) | ... BG7: =BG22-(BG48+BG60) | BI7: =BI22-(BI48+BI60) | BJ7: =BJ22-(BJ48+BJ60) | BK7: =BK22-(BK48+BK60) | BL7: =BL22-(BL48+BL60) | BM7: =BM22-(BM48+BM60) | BN7: =BN22-(BN48+BN60) | BO7: =BO22-(BO48+BO60) | BP7: =BP22-(BP48+BP60) | ... BU7: =BU22-(BU48+BU60) | BW7: =BW22-(BW48+BW60) | BX7: =BX22-(BX48+BX60) | BY7: =BY22-(BY48+BY60) | BZ7: =BZ22-(BZ48+BZ60) | CA7: =CA22-(CA48+CA60) | CB7: =CB22-(CB48+CB60) | CC7: =CC22-(CC48+CC60) | CD7: =CD22-(CD48+CD60) | ... CI7: =CI22-(CI48+CI60) | CK7: =CK22-(CK48+CK60) | CL7: =CL22-(CL48+CL60) | CM7: =CM22-(CM48+CM60) | CN7: =CN22-(CN48+CN60) | CO7: =CO22-(CO48+CO60) | CP7: =CP22-(CP48+CP60) | CQ7: =CQ22-(CQ48+CQ60) | CR7: =CR22-(CR48+CR60) | ... CW7: =CW22-(CW48+CW60) | CY7: =CY22-(CY48+CY60) | CZ7: =CZ22-(CZ48+CZ60) | DA7: =DA22-(DA48+DA60) | DB7: =DB22-(DB48+DB60) | DC7: =DC22-(DC48+DC60) | DD7: =DD22-(DD48+DD60) | DE7: =DE22-(DE48+DE60) | DF7: =DF22-(DF48+DF60) | ... DK7: =DK22-(DK48+DK60) | DM7: =DM22-(DM48+DM60) | DN7: =DN22-(DN48+DN60) | DO7: =DO22-(DO48+DO60) | DP7: =DP22-(DP48+DP60) | DQ7: =DQ22-(DQ48+DQ60) | DR7: =DR22-(DR48+DR60) | DS7: =DS22-(DS48+DS60) | DT7: =DT22-(DT48+DT60) | ... DY7: =DY22-(DY48+DY60) | EA7: =EA22-(EA48+EA60) | EB7: =EB22-(EB48+EB60) | EC7: =EC22-(EC48+EC60) | ED7: =ED22-(ED48+ED60) | EE7: =EE22-(EE48+EE60) | EF7: =EF22-(EF48+EF60) | EG7: =EG22-(EG48+EG60) | EH7: =EH22-(EH48+EH60) | ... EM7: =EM22-(EM48+EM60)
C9: Income | E9: =DATE(E$5,1,1) | F9: =DATE(E$5,2,1) | G9: =DATE(E$5,3,1) | H9: =DATE(E$5,4,1) | I9: =DATE(E$5,5,1) | J9: =DATE(E$5,6,1) | K9: =DATE(E$5,7,1) | L9: =DATE(E$5,8,1) | M9: =DATE(E$5,9,1) | N9: =DATE(E$5,10,1) | O9: =DATE(E$5,11,1) | P9: =DATE(E$5,12,1) | Q9: =E$5 | S9: =DATE(S$5,1,1) | T9: =DATE(S$5,2,1) | U9: =DATE(S$5,3,1) | V9: =DATE(S$5,4,1) | W9: =DATE(S$5,5,1) | X9: =DATE(S$5,6,1) | Y9: =DATE(S$5,7,1) | Z9: =DATE(S$5,8,1) | AA9: =DATE(S$5,9,1) | AB9: =DATE(S$5,10,1) | AC9: =DATE(S$5,11,1) | AD9: =DATE(S$5,12,1) | AE9: =S$5 | AG9: =DATE(AG$5,1,1) | AH9: =DATE(AG$5,2,1) | AI9: =DATE(AG$5,3,1) | AJ9: =DATE(AG$5,4,1) | AK9: =DATE(AG$5,5,1) | AL9: =DATE(AG$5,6,1) | AM9: =DATE(AG$5,7,1) | AN9: =DATE(AG$5,8,1) | AO9: =DATE(AG$5,9,1) | AP9: =DATE(AG$5,10,1) | AQ9: =DATE(AG$5,11,1) | AR9: =DATE(AG$5,12,1) | AS9: =AG$5 | AU9: =DATE(AU$5,1,1) | AV9: =DATE(AU$5,2,1) | AW9: =DATE(AU$5,3,1) | AX9: =DATE(AU$5,4,1) | AY9: =DATE(AU$5,5,1) | AZ9: =DATE(AU$5,6,1) | BA9: =DATE(AU$5,7,1) | BB9: =DATE(AU$5,8,1) | BC9: =DATE(AU$5,9,1) | BD9: =DATE(AU$5,10,1) | BE9: =DATE(AU$5,11,1) | BF9: =DATE(AU$5,12,1) | BG9: =AU$5 | BI9: =DATE(BI$5,1,1) | BJ9: =DATE(BI$5,2,1) | BK9: =DATE(BI$5,3,1) | BL9: =DATE(BI$5,4,1) | BM9: =DATE(BI$5,5,1) | BN9: =DATE(BI$5,6,1) | BO9: =DATE(BI$5,7,1) | BP9: =DATE(BI$5,8,1) | BQ9: =DATE(BI$5,9,1) | BR9: =DATE(BI$5,10,1) | BS9: =DATE(BI$5,11,1) | BT9: =DATE(BI$5,12,1) | BU9: =BI$5 | BW9: =DATE(BW$5,1,1) | BX9: =DATE(BW$5,2,1) | BY9: =DATE(BW$5,3,1) | BZ9: =DATE(BW$5,4,1) | CA9: =DATE(BW$5,5,1) | CB9: =DATE(BW$5,6,1) | CC9: =DATE(BW$5,7,1) | CD9: =DATE(BW$5,8,1) | CE9: =DATE(BW$5,9,1) | CF9: =DATE(BW$5,10,1) | CG9: =DATE(BW$5,11,1) | CH9: =DATE(BW$5,12,1) | CI9: =BW$5 | CK9: =DATE(CK$5,1,1) | CL9: =DATE(CK$5,2,1) | CM9: =DATE(CK$5,3,1) | CN9: =DATE(CK$5,4,1) | CO9: =DATE(CK$5,5,1) | CP9: =DATE(CK$5,6,1) | CQ9: =DATE(CK$5,7,1) | CR9: =DATE(CK$5,8,1) | CS9: =DATE(CK$5,9,1) | CT9: =DATE(CK$5,10,1) | CU9: =DATE(CK$5,11,1) | CV9: =DATE(CK$5,12,1) | CW9: =CK$5 | CY9: =DATE(CY$5,1,1) | CZ9: =DATE(CY$5,2,1) | DA9: =DATE(CY$5,3,1) | DB9: =DATE(CY$5,4,1) | DC9: =DATE(CY$5,5,1) | DD9: =DATE(CY$5,6,1) | DE9: =DATE(CY$5,7,1) | DF9: =DATE(CY$5,8,1) | DG9: =DATE(CY$5,9,1) | DH9: =DATE(CY$5,10,1) | DI9: =DATE(CY$5,11,1) | DJ9: =DATE(CY$5,12,1) | DK9: =CY$5 | DM9: =DATE(DM$5,1,1) | DN9: =DATE(DM$5,2,1) | DO9: =DATE(DM$5,3,1) | DP9: =DATE(DM$5,4,1) | DQ9: =DATE(DM$5,5,1) | DR9: =DATE(DM$5,6,1) | DS9: =DATE(DM$5,7,1) | DT9: =DATE(DM$5,8,1) | DU9: =DATE(DM$5,9,1) | DV9: =DATE(DM$5,10,1) | DW9: =DATE(DM$5,11,1) | DX9: =DATE(DM$5,12,1) | DY9: =DM$5 | EA9: =DATE(EA$5,1,1) | EB9: =DATE(EA$5,2,1) | EC9: =DATE(EA$5,3,1) | ED9: =DATE(EA$5,4,1) | EE9: =DATE(EA$5,5,1) | EF9: =DATE(EA$5,6,1) | EG9: =DATE(EA$5,7,1) | EH9: =DATE(EA$5,8,1) | EI9: =DATE(EA$5,9,1) | EJ9: =DATE(EA$5,10,1) | EK9: =DATE(EA$5,11,1) | EL9: =DATE(EA$5,12,1) | EM9: =EA$5
C10: Employment (Net) | Q10: =SUM(E10:P10) | S10: 5000 | AE10: =SUM(S10:AD10) | AS10: =SUM(AG10:AR10) | BG10: =SUM(AU10:BF10) | BU10: =SUM(BI10:BT10) | CI10: =SUM(BW10:CH10) | CW10: =SUM(CK10:CV10) | DK10: =SUM(CY10:DJ10) | DY10: =SUM(DM10:DX10) | EM10: =SUM(EA10:EL10)
C11: Reimbursements | Q11: =SUM(E11:P11) | AE11: =SUM(S11:AD11)
C12: Bonus | Q12: =SUM(E12:P12) | AE12: =SUM(S12:AD12)
C13: Refunds | Q13: =SUM(E13:P13) | AE13: =SUM(S13:AD13)
C14: Side Hustle (Net) | Q14: =SUM(E14:P14) | AE14: =SUM(S14:AD14) | AS14: =SUM(AG14:AR14) | BG14: =SUM(AU14:BF14) | BU14: =SUM(BI14:BT14) | CI14: =SUM(BW14:CH14) | CW14: =SUM(CK14:CV14) | DK14: =SUM(CY14:DJ14) | DY14: =SUM(DM14:DX14) | EM14: =SUM(EA14:EL14)
C15: Other Income | Q15: =SUM(E15:P15) | AE15: =SUM(S15:AD15) | AS15: =SUM(AG15:AR15) | BG15: =SUM(AU15:BF15) | BU15: =SUM(BI15:BT15) | CI15: =SUM(BW15:CH15) | CW15: =SUM(CK15:CV15) | DK15: =SUM(CY15:DJ15) | DY15: =SUM(DM15:DX15) | EM15: =SUM(EA15:EL15)
C16: Enter Income Categoroy | Q16: =SUM(E16:P16) | AE16: =SUM(S16:AD16) | AS16: =SUM(AG16:AR16) | BG16: =SUM(AU16:BF16) | BU16: =SUM(BI16:BT16) | CI16: =SUM(BW16:CH16) | CW16: =SUM(CK16:CV16) | DK16: =SUM(CY16:DJ16) | DY16: =SUM(DM16:DX16) | EM16: =SUM(EA16:EL16)
C17: Enter Income Categoroy | Q17: =SUM(E17:P17) | AE17: =SUM(S17:AD17) | AS17: =SUM(AG17:AR17) | BG17: =SUM(AU17:BF17) | BU17: =SUM(BI17:BT17) | CI17: =SUM(BW17:CH17) | CW17: =SUM(CK17:CV17) | DK17: =SUM(CY17:DJ17) | DY17: =SUM(DM17:DX17) | EM17: =SUM(EA17:EL17)
C18: Enter Income Categoroy | Q18: =SUM(E18:P18) | AE18: =SUM(S18:AD18) | AS18: =SUM(AG18:AR18) | BG18: =SUM(AU18:BF18) | BU18: =SUM(BI18:BT18) | CI18: =SUM(BW18:CH18) | CW18: =SUM(CK18:CV18) | DK18: =SUM(CY18:DJ18) | DY18: =SUM(DM18:DX18) | EM18: =SUM(EA18:EL18)
C19: Enter Income Categoroy | Q19: =SUM(E19:P19) | AE19: =SUM(S19:AD19) | AS19: =SUM(AG19:AR19) | BG19: =SUM(AU19:BF19) | BU19: =SUM(BI19:BT19) | CI19: =SUM(BW19:CH19) | CW19: =SUM(CK19:CV19) | DK19: =SUM(CY19:DJ19) | DY19: =SUM(DM19:DX19) | EM19: =SUM(EA19:EL19)
C20: Enter Income Categoroy | Q20: =SUM(E20:P20) | AE20: =SUM(S20:AD20) | AS20: =SUM(AG20:AR20) | BG20: =SUM(AU20:BF20) | BU20: =SUM(BI20:BT20) | CI20: =SUM(BW20:CH20) | CW20: =SUM(CK20:CV20) | DK20: =SUM(CY20:DJ20) | DY20: =SUM(DM20:DX20) | EM20: =SUM(EA20:EL20)
C21: Enter Income Categoroy | Q21: =SUM(E21:P21) | AE21: =SUM(S21:AD21) | AS21: =SUM(AG21:AR21) | BG21: =SUM(AU21:BF21) | BU21: =SUM(BI21:BT21) | CI21: =SUM(BW21:CH21) | CW21: =SUM(CK21:CV21) | DK21: =SUM(CY21:DJ21) | DY21: =SUM(DM21:DX21) | EM21: =SUM(EA21:EL21)
C22: Total | E22: {=SUM(INDIRECT(ADDRESS(income_min_row,COLUMN())&":"&ADDRESS(income_max_row,COLUMN())))} | F22: {=SUM(INDIRECT(ADDRESS(income_min_row,COLUMN())&":"&ADDRESS(income_max_row,COLUMN())))} | G22: {=SUM(INDIRECT(ADDRESS(income_min_row,COLUMN())&":"&ADDRESS(income_max_row,COLUMN())))} | H22: {=SUM(INDIRECT(ADDRESS(income_min_row,COLUMN())&":"&ADDRESS(income_max_row,COLUMN())))} | I22: {=SUM(INDIRECT(ADDRESS(income_min_row,COLUMN())&":"&ADDRESS(income_max_row,COLUMN())))} | J22: {=SUM(INDIRECT(ADDRESS(income_min_row,COLUMN())&":"&ADDRESS(income_max_row,COLUMN())))} | K22: {=SUM(INDIRECT(ADDRESS(income_min_row,COLUMN())&":"&ADDRESS(income_max_row,COLUMN())))} | L22: {=SUM(INDIRECT(ADDRESS(income_min_row,COLUMN())&":"&ADDRESS(income_max_row,COLUMN())))} | ... Q22: {=SUM(INDIRECT(ADDRESS(income_min_row,COLUMN())&":"&ADDRESS(income_max_row,COLUMN())))} | S22: {=SUM(INDIRECT(ADDRESS(income_min_row,COLUMN())&":"&ADDRESS(income_max_row,COLUMN())))} | T22: {=SUM(INDIRECT(ADDRESS(income_min_row,COLUMN())&":"&ADDRESS(income_max_row,COLUMN())))} | U22: {=SUM(INDIRECT(ADDRESS(income_min_row,COLUMN())&":"&ADDRESS(income_max_row,COLUMN())))} | V22: {=SUM(INDIRECT(ADDRESS(income_min_row,COLUMN())&":"&ADDRESS(income_max_row,COLUMN())))} | W22: {=SUM(INDIRECT(ADDRESS(income_min_row,COLUMN())&":"&ADDRESS(income_max_row,COLUMN())))} | X22: {=SUM(INDIRECT(ADDRESS(income_min_row,COLUMN())&":"&ADDRESS(income_max_row,COLUMN())))} | Y22: {=SUM(INDIRECT(ADDRESS(income_min_row,COLUMN())&":"&ADDRESS(income_max_row,COLUMN())))} | Z22: {=SUM(INDIRECT(ADDRESS(income_min_row,COLUMN())&":"&ADDRESS(income_max_row,COLUMN())))} | ... AE22: {=SUM(INDIRECT(ADDRESS(income_min_row,COLUMN())&":"&ADDRESS(income_max_row,COLUMN())))} | AG22: {=SUM(INDIRECT(ADDRESS(income_min_row,COLUMN())&":"&ADDRESS(income_max_row,COLUMN())))} | AH22: {=SUM(INDIRECT(ADDRESS(income_min_row,COLUMN())&":"&ADDRESS(income_max_row,COLUMN())))} | AI22: {=SUM(INDIRECT(ADDRESS(income_min_row,COLUMN())&":"&ADDRESS(income_max_row,COLUMN())))} | AJ22: {=SUM(INDIRECT(ADDRESS(income_min_row,COLUMN())&":"&ADDRESS(income_max_row,COLUMN())))} | AK22: {=SUM(INDIRECT(ADDRESS(income_min_row,COLUMN())&":"&ADDRESS(income_max_row,COLUMN())))} | AL22: {=SUM(INDIRECT(ADDRESS(income_min_row,COLUMN())&":"&ADDRESS(income_max_row,COLUMN())))} | AM22: {=SUM(INDIRECT(ADDRESS(income_min_row,COLUMN())&":"&ADDRESS(income_max_row,COLUMN())))} | AN22: {=SUM(INDIRECT(ADDRESS(income_min_row,COLUMN())&":"&ADDRESS(income_max_row,COLUMN())))} | ... AS22: {=SUM(INDIRECT(ADDRESS(income_min_row,COLUMN())&":"&ADDRESS(income_max_row,COLUMN())))} | AU22: {=SUM(INDIRECT(ADDRESS(income_min_row,COLUMN())&":"&ADDRESS(income_max_row,COLUMN())))} | AV22: {=SUM(INDIRECT(ADDRESS(income_min_row,COLUMN())&":"&ADDRESS(income_max_row,COLUMN())))} | AW22: {=SUM(INDIRECT(ADDRESS(income_min_row,COLUMN())&":"&ADDRESS(income_max_row,COLUMN())))} | AX22: {=SUM(INDIRECT(ADDRESS(income_min_row,COLUMN())&":"&ADDRESS(income_max_row,COLUMN())))} | AY22: {=SUM(INDIRECT(ADDRESS(income_min_row,COLUMN())&":"&ADDRESS(income_max_row,COLUMN())))} | AZ22: {=SUM(INDIRECT(ADDRESS(income_min_row,COLUMN())&":"&ADDRESS(income_max_row,COLUMN())))} | BA22: {=SUM(INDIRECT(ADDRESS(income_min_row,COLUMN())&":"&ADDRESS(income_max_row,COLUMN())))} | BB22: {=SUM(INDIRECT(ADDRESS(income_min_row,COLUMN())&":"&ADDRESS(income_max_row,COLUMN())))} | ... BG22: {=SUM(INDIRECT(ADDRESS(income_min_row,COLUMN())&":"&ADDRESS(income_max_row,COLUMN())))} | BI22: {=SUM(INDIRECT(ADDRESS(income_min_row,COLUMN())&":"&ADDRESS(income_max_row,COLUMN())))} | BJ22: {=SUM(INDIRECT(ADDRESS(income_min_row,COLUMN())&":"&ADDRESS(income_max_row,COLUMN())))} | BK22: {=SUM(INDIRECT(ADDRESS(income_min_row,COLUMN())&":"&ADDRESS(income_max_row,COLUMN())))} | BL22: {=SUM(INDIRECT(ADDRESS(income_min_row,COLUMN())&":"&ADDRESS(income_max_row,COLUMN())))} | BM22: {=SUM(INDIRECT(ADDRESS(income_min_row,COLUMN())&":"&ADDRESS(income_max_row,COLUMN())))} | BN22: {=SUM(INDIRECT(ADDRESS(income_min_row,COLUMN())&":"&ADDRESS(income_max_row,COLUMN())))} | BO22: {=SUM(INDIRECT(ADDRESS(income_min_row,COLUMN())&":"&ADDRESS(income_max_row,COLUMN())))} | BP22: {=SUM(INDIRECT(ADDRESS(income_min_row,COLUMN())&":"&ADDRESS(income_max_row,COLUMN())))} | ... BU22: {=SUM(INDIRECT(ADDRESS(income_min_row,COLUMN())&":"&ADDRESS(income_max_row,COLUMN())))} | BW22: {=SUM(INDIRECT(ADDRESS(income_min_row,COLUMN())&":"&ADDRESS(income_max_row,COLUMN())))} | BX22: {=SUM(INDIRECT(ADDRESS(income_min_row,COLUMN())&":"&ADDRESS(income_max_row,COLUMN())))} | BY22: {=SUM(INDIRECT(ADDRESS(income_min_row,COLUMN())&":"&ADDRESS(income_max_row,COLUMN())))} | BZ22: {=SUM(INDIRECT(ADDRESS(income_min_row,COLUMN())&":"&ADDRESS(income_max_row,COLUMN())))} | CA22: {=SUM(INDIRECT(ADDRESS(income_min_row,COLUMN())&":"&ADDRESS(income_max_row,COLUMN())))} | CB22: {=SUM(INDIRECT(ADDRESS(income_min_row,COLUMN())&":"&ADDRESS(income_max_row,COLUMN())))} | CC22: {=SUM(INDIRECT(ADDRESS(income_min_row,COLUMN())&":"&ADDRESS(income_max_row,COLUMN())))} | CD22: {=SUM(INDIRECT(ADDRESS(income_min_row,COLUMN())&":"&ADDRESS(income_max_row,COLUMN())))} | ... CI22: {=SUM(INDIRECT(ADDRESS(income_min_row,COLUMN())&":"&ADDRESS(income_max_row,COLUMN())))} | CK22: {=SUM(INDIRECT(ADDRESS(income_min_row,COLUMN())&":"&ADDRESS(income_max_row,COLUMN())))} | CL22: {=SUM(INDIRECT(ADDRESS(income_min_row,COLUMN())&":"&ADDRESS(income_max_row,COLUMN())))} | CM22: {=SUM(INDIRECT(ADDRESS(income_min_row,COLUMN())&":"&ADDRESS(income_max_row,COLUMN())))} | CN22: {=SUM(INDIRECT(ADDRESS(income_min_row,COLUMN())&":"&ADDRESS(income_max_row,COLUMN())))} | CO22: {=SUM(INDIRECT(ADDRESS(income_min_row,COLUMN())&":"&ADDRESS(income_max_row,COLUMN())))} | CP22: {=SUM(INDIRECT(ADDRESS(income_min_row,COLUMN())&":"&ADDRESS(income_max_row,COLUMN())))} | CQ22: {=SUM(INDIRECT(ADDRESS(income_min_row,COLUMN())&":"&ADDRESS(income_max_row,COLUMN())))} | CR22: {=SUM(INDIRECT(ADDRESS(income_min_row,COLUMN())&":"&ADDRESS(income_max_row,COLUMN())))} | ... CW22: {=SUM(INDIRECT(ADDRESS(income_min_row,COLUMN())&":"&ADDRESS(income_max_row,COLUMN())))} | CY22: {=SUM(INDIRECT(ADDRESS(income_min_row,COLUMN())&":"&ADDRESS(income_max_row,COLUMN())))} | CZ22: {=SUM(INDIRECT(ADDRESS(income_min_row,COLUMN())&":"&ADDRESS(income_max_row,COLUMN())))} | DA22: {=SUM(INDIRECT(ADDRESS(income_min_row,COLUMN())&":"&ADDRESS(income_max_row,COLUMN())))} | DB22: {=SUM(INDIRECT(ADDRESS(income_min_row,COLUMN())&":"&ADDRESS(income_max_row,COLUMN())))} | DC22: {=SUM(INDIRECT(ADDRESS(income_min_row,COLUMN())&":"&ADDRESS(income_max_row,COLUMN())))} | DD22: {=SUM(INDIRECT(ADDRESS(income_min_row,COLUMN())&":"&ADDRESS(income_max_row,COLUMN())))} | DE22: {=SUM(INDIRECT(ADDRESS(income_min_row,COLUMN())&":"&ADDRESS(income_max_row,COLUMN())))} | DF22: {=SUM(INDIRECT(ADDRESS(income_min_row,COLUMN())&":"&ADDRESS(income_max_row,COLUMN())))} | ... DK22: {=SUM(INDIRECT(ADDRESS(income_min_row,COLUMN())&":"&ADDRESS(income_max_row,COLUMN())))} | DM22: {=SUM(INDIRECT(ADDRESS(income_min_row,COLUMN())&":"&ADDRESS(income_max_row,COLUMN())))} | DN22: {=SUM(INDIRECT(ADDRESS(income_min_row,COLUMN())&":"&ADDRESS(income_max_row,COLUMN())))} | DO22: {=SUM(INDIRECT(ADDRESS(income_min_row,COLUMN())&":"&ADDRESS(income_max_row,COLUMN())))} | DP22: {=SUM(INDIRECT(ADDRESS(income_min_row,COLUMN())&":"&ADDRESS(income_max_row,COLUMN())))} | DQ22: {=SUM(INDIRECT(ADDRESS(income_min_row,COLUMN())&":"&ADDRESS(income_max_row,COLUMN())))} | DR22: {=SUM(INDIRECT(ADDRESS(income_min_row,COLUMN())&":"&ADDRESS(income_max_row,COLUMN())))} | DS22: {=SUM(INDIRECT(ADDRESS(income_min_row,COLUMN())&":"&ADDRESS(income_max_row,COLUMN())))} | DT22: {=SUM(INDIRECT(ADDRESS(income_min_row,COLUMN())&":"&ADDRESS(income_max_row,COLUMN())))} | ... DY22: {=SUM(INDIRECT(ADDRESS(income_min_row,COLUMN())&":"&ADDRESS(income_max_row,COLUMN())))} | EA22: {=SUM(INDIRECT(ADDRESS(income_min_row,COLUMN())&":"&ADDRESS(income_max_row,COLUMN())))} | EB22: {=SUM(INDIRECT(ADDRESS(income_min_row,COLUMN())&":"&ADDRESS(income_max_row,COLUMN())))} | EC22: {=SUM(INDIRECT(ADDRESS(income_min_row,COLUMN())&":"&ADDRESS(income_max_row,COLUMN())))} | ED22: {=SUM(INDIRECT(ADDRESS(income_min_row,COLUMN())&":"&ADDRESS(income_max_row,COLUMN())))} | EE22: {=SUM(INDIRECT(ADDRESS(income_min_row,COLUMN())&":"&ADDRESS(income_max_row,COLUMN())))} | EF22: {=SUM(INDIRECT(ADDRESS(income_min_row,COLUMN())&":"&ADDRESS(income_max_row,COLUMN())))} | EG22: {=SUM(INDIRECT(ADDRESS(income_min_row,COLUMN())&":"&ADDRESS(income_max_row,COLUMN())))} | EH22: {=SUM(INDIRECT(ADDRESS(income_min_row,COLUMN())&":"&ADDRESS(income_max_row,COLUMN())))} | ... EM22: {=SUM(INDIRECT(ADDRESS(income_min_row,COLUMN())&":"&ADDRESS(income_max_row,COLUMN())))}
C24: Expenses | E24: =DATE(E$5,1,1) | F24: =DATE(E$5,2,1) | G24: =DATE(E$5,3,1) | H24: =DATE(E$5,4,1) | I24: =DATE(E$5,5,1) | J24: =DATE(E$5,6,1) | K24: =DATE(E$5,7,1) | L24: =DATE(E$5,8,1) | M24: =DATE(E$5,9,1) | N24: =DATE(E$5,10,1) | O24: =DATE(E$5,11,1) | P24: =DATE(E$5,12,1) | Q24: =E$5 | S24: =DATE(S$5,1,1) | T24: =DATE(S$5,2,1) | U24: =DATE(S$5,3,1) | V24: =DATE(S$5,4,1) | W24: =DATE(S$5,5,1) | X24: =DATE(S$5,6,1) | Y24: =DATE(S$5,7,1) | Z24: =DATE(S$5,8,1) | AA24: =DATE(S$5,9,1) | AB24: =DATE(S$5,10,1) | AC24: =DATE(S$5,11,1) | AD24: =DATE(S$5,12,1) | AE24: =S$5 | AG24: =DATE(AG$5,1,1) | AH24: =DATE(AG$5,2,1) | AI24: =DATE(AG$5,3,1) | AJ24: =DATE(AG$5,4,1) | AK24: =DATE(AG$5,5,1) | AL24: =DATE(AG$5,6,1) | AM24: =DATE(AG$5,7,1) | AN24: =DATE(AG$5,8,1) | AO24: =DATE(AG$5,9,1) | AP24: =DATE(AG$5,10,1) | AQ24: =DATE(AG$5,11,1) | AR24: =DATE(AG$5,12,1) | AS24: =AG$5 | AU24: =DATE(AU$5,1,1) | AV24: =DATE(AU$5,2,1) | AW24: =DATE(AU$5,3,1) | AX24: =DATE(AU$5,4,1) | AY24: =DATE(AU$5,5,1) | AZ24: =DATE(AU$5,6,1) | BA24: =DATE(AU$5,7,1) | BB24: =DATE(AU$5,8,1) | BC24: =DATE(AU$5,9,1) | BD24: =DATE(AU$5,10,1) | BE24: =DATE(AU$5,11,1) | BF24: =DATE(AU$5,12,1) | BG24: =AU$5 | BI24: =DATE(BI$5,1,1) | BJ24: =DATE(BI$5,2,1) | BK24: =DATE(BI$5,3,1) | BL24: =DATE(BI$5,4,1) | BM24: =DATE(BI$5,5,1) | BN24: =DATE(BI$5,6,1) | BO24: =DATE(BI$5,7,1) | BP24: =DATE(BI$5,8,1) | BQ24: =DATE(BI$5,9,1) | BR24: =DATE(BI$5,10,1) | BS24: =DATE(BI$5,11,1) | BT24: =DATE(BI$5,12,1) | BU24: =BI$5 | BW24: =DATE(BW$5,1,1) | BX24: =DATE(BW$5,2,1) | BY24: =DATE(BW$5,3,1) | BZ24: =DATE(BW$5,4,1) | CA24: =DATE(BW$5,5,1) | CB24: =DATE(BW$5,6,1) | CC24: =DATE(BW$5,7,1) | CD24: =DATE(BW$5,8,1) | CE24: =DATE(BW$5,9,1) | CF24: =DATE(BW$5,10,1) | CG24: =DATE(BW$5,11,1) | CH24: =DATE(BW$5,12,1) | CI24: =BW$5 | CK24: =DATE(CK$5,1,1) | CL24: =DATE(CK$5,2,1) | CM24: =DATE(CK$5,3,1) | CN24: =DATE(CK$5,4,1) | CO24: =DATE(CK$5,5,1) | CP24: =DATE(CK$5,6,1) | CQ24: =DATE(CK$5,7,1) | CR24: =DATE(CK$5,8,1) | CS24: =DATE(CK$5,9,1) | CT24: =DATE(CK$5,10,1) | CU24: =DATE(CK$5,11,1) | CV24: =DATE(CK$5,12,1) | CW24: =CK$5 | CY24: =DATE(CY$5,1,1) | CZ24: =DATE(CY$5,2,1) | DA24: =DATE(CY$5,3,1) | DB24: =DATE(CY$5,4,1) | DC24: =DATE(CY$5,5,1) | DD24: =DATE(CY$5,6,1) | DE24: =DATE(CY$5,7,1) | DF24: =DATE(CY$5,8,1) | DG24: =DATE(CY$5,9,1) | DH24: =DATE(CY$5,10,1) | DI24: =DATE(CY$5,11,1) | DJ24: =DATE(CY$5,12,1) | DK24: =CY$5 | DM24: =DATE(DM$5,1,1) | DN24: =DATE(DM$5,2,1) | DO24: =DATE(DM$5,3,1) | DP24: =DATE(DM$5,4,1) | DQ24: =DATE(DM$5,5,1) | DR24: =DATE(DM$5,6,1) | DS24: =DATE(DM$5,7,1) | DT24: =DATE(DM$5,8,1) | DU24: =DATE(DM$5,9,1) | DV24: =DATE(DM$5,10,1) | DW24: =DATE(DM$5,11,1) | DX24: =DATE(DM$5,12,1) | DY24: =DM$5 | EA24: =DATE(EA$5,1,1) | EB24: =DATE(EA$5,2,1) | EC24: =DATE(EA$5,3,1) | ED24: =DATE(EA$5,4,1) | EE24: =DATE(EA$5,5,1) | EF24: =DATE(EA$5,6,1) | EG24: =DATE(EA$5,7,1) | EH24: =DATE(EA$5,8,1) | EI24: =DATE(EA$5,9,1) | EJ24: =DATE(EA$5,10,1) | EK24: =DATE(EA$5,11,1) | EL24: =DATE(EA$5,12,1) | EM24: =EA$5
C25: Rent | Q25: =SUM(E25:P25) | S25: 1500 | AE25: =SUM(S25:AD25) | AS25: =SUM(AG25:AR25) | BG25: =SUM(AU25:BF25) | BU25: =SUM(BI25:BT25) | CI25: =SUM(BW25:CH25) | CW25: =SUM(CK25:CV25) | DK25: =SUM(CY25:DJ25) | DY25: =SUM(DM25:DX25) | EM25: =SUM(EA25:EL25)
C26: Food | Q26: =SUM(E26:P26) | AE26: =SUM(S26:AD26) | AS26: =SUM(AG26:AR26) | BG26: =SUM(AU26:BF26) | BU26: =SUM(BI26:BT26) | CI26: =SUM(BW26:CH26) | CW26: =SUM(CK26:CV26) | DK26: =SUM(CY26:DJ26) | DY26: =SUM(DM26:DX26) | EM26: =SUM(EA26:EL26)
C27: Subscription | Q27: =SUM(E27:P27) | AE27: =SUM(S27:AD27)
C28: ne | Q28: =SUM(E28:P28) | AE28: =SUM(S28:AD28) | AS28: =SUM(AG28:AR28) | BG28: =SUM(AU28:BF28) | BU28: =SUM(BI28:BT28) | CI28: =SUM(BW28:CH28) | CW28: =SUM(CK28:CV28) | DK28: =SUM(CY28:DJ28) | DY28: =SUM(DM28:DX28) | EM28: =SUM(EA28:EL28)
C29: ha | Q29: =SUM(E29:P29) | AE29: =SUM(S29:AD29)
C30: lo | Q30: =SUM(E30:P30) | AE30: =SUM(S30:AD30)
C31: ki | Q31: =SUM(E31:P31) | AE31: =SUM(S31:AD31)
C32: ji | Q32: =SUM(E32:P32) | AE32: =SUM(S32:AD32)
C33: wi | Q33: =SUM(E33:P33) | AE33: =SUM(S33:AD33)
C34: oi | Q34: =SUM(E34:P34) | AE34: =SUM(S34:AD34) | AS34: =SUM(AG34:AR34) | BG34: =SUM(AU34:BF34) | BU34: =SUM(BI34:BT34) | CI34: =SUM(BW34:CH34) | CW34: =SUM(CK34:CV34) | DK34: =SUM(CY34:DJ34) | DY34: =SUM(DM34:DX34) | EM34: =SUM(EA34:EL34)
Q35: =SUM(E35:P35) | AE35: =SUM(S35:AD35) | AS35: =SUM(AG35:AR35) | BG35: =SUM(AU35:BF35) | BU35: =SUM(BI35:BT35) | CI35: =SUM(BW35:CH35) | CW35: =SUM(CK35:CV35) | DK35: =SUM(CY35:DJ35) | DY35: =SUM(DM35:DX35) | EM35: =SUM(EA35:EL35)
Q36: =SUM(E36:P36) | AE36: =SUM(S36:AD36)
Q37: =SUM(E37:P37) | AE37: =SUM(S37:AD37) | AS37: =SUM(AG37:AR37) | BG37: =SUM(AU37:BF37) | BU37: =SUM(BI37:BT37) | CI37: =SUM(BW37:CH37) | CW37: =SUM(CK37:CV37) | DK37: =SUM(CY37:DJ37) | DY37: =SUM(DM37:DX37) | EM37: =SUM(EA37:EL37)
Q38: =SUM(E38:P38) | AE38: =SUM(S38:AD38)
Q39: =SUM(E39:P39) | AE39: =SUM(S39:AD39)
Q40: =SUM(E40:P40) | AE40: =SUM(S40:AD40)
Q41: =SUM(E41:P41) | AE41: =SUM(S41:AD41)
Q42: =SUM(E42:P42) | AE42: =SUM(S42:AD42)
Q43: =SUM(E43:P43) | AE43: =SUM(S43:AD43)
Q44: =SUM(E44:P44) | AE44: =SUM(S44:AD44)
Q45: =SUM(E45:P45) | AE45: =SUM(S45:AD45)
Q46: =SUM(E46:P46) | AE46: =SUM(S46:AD46)
Q47: =SUM(E47:P47) | AE47: =SUM(S47:AD47)
C48: Total | E48: {=SUM(INDIRECT(ADDRESS(expenses_min_row,COLUMN())&":"&ADDRESS(expenses_max_row,COLUMN())))} | F48: {=SUM(INDIRECT(ADDRESS(expenses_min_row,COLUMN())&":"&ADDRESS(expenses_max_row,COLUMN())))} | G48: {=SUM(INDIRECT(ADDRESS(expenses_min_row,COLUMN())&":"&ADDRESS(expenses_max_row,COLUMN())))} | H48: {=SUM(INDIRECT(ADDRESS(expenses_min_row,COLUMN())&":"&ADDRESS(expenses_max_row,COLUMN())))} | I48: {=SUM(INDIRECT(ADDRESS(expenses_min_row,COLUMN())&":"&ADDRESS(expenses_max_row,COLUMN())))} | J48: {=SUM(INDIRECT(ADDRESS(expenses_min_row,COLUMN())&":"&ADDRESS(expenses_max_row,COLUMN())))} | K48: {=SUM(INDIRECT(ADDRESS(expenses_min_row,COLUMN())&":"&ADDRESS(expenses_max_row,COLUMN())))} | L48: {=SUM(INDIRECT(ADDRESS(expenses_min_row,COLUMN())&":"&ADDRESS(expenses_max_row,COLUMN())))} | ... Q48: {=SUM(INDIRECT(ADDRESS(expenses_min_row,COLUMN())&":"&ADDRESS(expenses_max_row,COLUMN())))} | S48: {=SUM(INDIRECT(ADDRESS(expenses_min_row,COLUMN())&":"&ADDRESS(expenses_max_row,COLUMN())))} | T48: {=SUM(INDIRECT(ADDRESS(expenses_min_row,COLUMN())&":"&ADDRESS(expenses_max_row,COLUMN())))} | U48: {=SUM(INDIRECT(ADDRESS(expenses_min_row,COLUMN())&":"&ADDRESS(expenses_max_row,COLUMN())))} | V48: {=SUM(INDIRECT(ADDRESS(expenses_min_row,COLUMN())&":"&ADDRESS(expenses_max_row,COLUMN())))} | W48: {=SUM(INDIRECT(ADDRESS(expenses_min_row,COLUMN())&":"&ADDRESS(expenses_max_row,COLUMN())))} | X48: {=SUM(INDIRECT(ADDRESS(expenses_min_row,COLUMN())&":"&ADDRESS(expenses_max_row,COLUMN())))} | Y48: {=SUM(INDIRECT(ADDRESS(expenses_min_row,COLUMN())&":"&ADDRESS(expenses_max_row,COLUMN())))} | Z48: {=SUM(INDIRECT(ADDRESS(expenses_min_row,COLUMN())&":"&ADDRESS(expenses_max_row,COLUMN())))} | ... AE48: {=SUM(INDIRECT(ADDRESS(expenses_min_row,COLUMN())&":"&ADDRESS(expenses_max_row,COLUMN())))} | AG48: {=SUM(INDIRECT(ADDRESS(expenses_min_row,COLUMN())&":"&ADDRESS(expenses_max_row,COLUMN())))} | AH48: {=SUM(INDIRECT(ADDRESS(expenses_min_row,COLUMN())&":"&ADDRESS(expenses_max_row,COLUMN())))} | AI48: {=SUM(INDIRECT(ADDRESS(expenses_min_row,COLUMN())&":"&ADDRESS(expenses_max_row,COLUMN())))} | AJ48: {=SUM(INDIRECT(ADDRESS(expenses_min_row,COLUMN())&":"&ADDRESS(expenses_max_row,COLUMN())))} | AK48: {=SUM(INDIRECT(ADDRESS(expenses_min_row,COLUMN())&":"&ADDRESS(expenses_max_row,COLUMN())))} | AL48: {=SUM(INDIRECT(ADDRESS(expenses_min_row,COLUMN())&":"&ADDRESS(expenses_max_row,COLUMN())))} | AM48: {=SUM(INDIRECT(ADDRESS(expenses_min_row,COLUMN())&":"&ADDRESS(expenses_max_row,COLUMN())))} | AN48: {=SUM(INDIRECT(ADDRESS(expenses_min_row,COLUMN())&":"&ADDRESS(expenses_max_row,COLUMN())))} | ... AS48: {=SUM(INDIRECT(ADDRESS(expenses_min_row,COLUMN())&":"&ADDRESS(expenses_max_row,COLUMN())))} | AU48: {=SUM(INDIRECT(ADDRESS(expenses_min_row,COLUMN())&":"&ADDRESS(expenses_max_row,COLUMN())))} | AV48: {=SUM(INDIRECT(ADDRESS(expenses_min_row,COLUMN())&":"&ADDRESS(expenses_max_row,COLUMN())))} | AW48: {=SUM(INDIRECT(ADDRESS(expenses_min_row,COLUMN())&":"&ADDRESS(expenses_max_row,COLUMN())))} | AX48: {=SUM(INDIRECT(ADDRESS(expenses_min_row,COLUMN())&":"&ADDRESS(expenses_max_row,COLUMN())))} | AY48: {=SUM(INDIRECT(ADDRESS(expenses_min_row,COLUMN())&":"&ADDRESS(expenses_max_row,COLUMN())))} | AZ48: {=SUM(INDIRECT(ADDRESS(expenses_min_row,COLUMN())&":"&ADDRESS(expenses_max_row,COLUMN())))} | BA48: {=SUM(INDIRECT(ADDRESS(expenses_min_row,COLUMN())&":"&ADDRESS(expenses_max_row,COLUMN())))} | BB48: {=SUM(INDIRECT(ADDRESS(expenses_min_row,COLUMN())&":"&ADDRESS(expenses_max_row,COLUMN())))} | ... BG48: {=SUM(INDIRECT(ADDRESS(expenses_min_row,COLUMN())&":"&ADDRESS(expenses_max_row,COLUMN())))} | BI48: {=SUM(INDIRECT(ADDRESS(expenses_min_row,COLUMN())&":"&ADDRESS(expenses_max_row,COLUMN())))} | BJ48: {=SUM(INDIRECT(ADDRESS(expenses_min_row,COLUMN())&":"&ADDRESS(expenses_max_row,COLUMN())))} | BK48: {=SUM(INDIRECT(ADDRESS(expenses_min_row,COLUMN())&":"&ADDRESS(expenses_max_row,COLUMN())))} | BL48: {=SUM(INDIRECT(ADDRESS(expenses_min_row,COLUMN())&":"&ADDRESS(expenses_max_row,COLUMN())))} | BM48: {=SUM(INDIRECT(ADDRESS(expenses_min_row,COLUMN())&":"&ADDRESS(expenses_max_row,COLUMN())))} | BN48: {=SUM(INDIRECT(ADDRESS(expenses_min_row,COLUMN())&":"&ADDRESS(expenses_max_row,COLUMN())))} | BO48: {=SUM(INDIRECT(ADDRESS(expenses_min_row,COLUMN())&":"&ADDRESS(expenses_max_row,COLUMN())))} | BP48: {=SUM(INDIRECT(ADDRESS(expenses_min_row,COLUMN())&":"&ADDRESS(expenses_max_row,COLUMN())))} | ... BU48: {=SUM(INDIRECT(ADDRESS(expenses_min_row,COLUMN())&":"&ADDRESS(expenses_max_row,COLUMN())))} | BW48: {=SUM(INDIRECT(ADDRESS(expenses_min_row,COLUMN())&":"&ADDRESS(expenses_max_row,COLUMN())))} | BX48: {=SUM(INDIRECT(ADDRESS(expenses_min_row,COLUMN())&":"&ADDRESS(expenses_max_row,COLUMN())))} | BY48: {=SUM(INDIRECT(ADDRESS(expenses_min_row,COLUMN())&":"&ADDRESS(expenses_max_row,COLUMN())))} | BZ48: {=SUM(INDIRECT(ADDRESS(expenses_min_row,COLUMN())&":"&ADDRESS(expenses_max_row,COLUMN())))} | CA48: {=SUM(INDIRECT(ADDRESS(expenses_min_row,COLUMN())&":"&ADDRESS(expenses_max_row,COLUMN())))} | CB48: {=SUM(INDIRECT(ADDRESS(expenses_min_row,COLUMN())&":"&ADDRESS(expenses_max_row,COLUMN())))} | CC48: {=SUM(INDIRECT(ADDRESS(expenses_min_row,COLUMN())&":"&ADDRESS(expenses_max_row,COLUMN())))} | CD48: {=SUM(INDIRECT(ADDRESS(expenses_min_row,COLUMN())&":"&ADDRESS(expenses_max_row,COLUMN())))} | ... CI48: {=SUM(INDIRECT(ADDRESS(expenses_min_row,COLUMN())&":"&ADDRESS(expenses_max_row,COLUMN())))} | CK48: {=SUM(INDIRECT(ADDRESS(expenses_min_row,COLUMN())&":"&ADDRESS(expenses_max_row,COLUMN())))} | CL48: {=SUM(INDIRECT(ADDRESS(expenses_min_row,COLUMN())&":"&ADDRESS(expenses_max_row,COLUMN())))} | CM48: {=SUM(INDIRECT(ADDRESS(expenses_min_row,COLUMN())&":"&ADDRESS(expenses_max_row,COLUMN())))} | CN48: {=SUM(INDIRECT(ADDRESS(expenses_min_row,COLUMN())&":"&ADDRESS(expenses_max_row,COLUMN())))} | CO48: {=SUM(INDIRECT(ADDRESS(expenses_min_row,COLUMN())&":"&ADDRESS(expenses_max_row,COLUMN())))} | CP48: {=SUM(INDIRECT(ADDRESS(expenses_min_row,COLUMN())&":"&ADDRESS(expenses_max_row,COLUMN())))} | CQ48: {=SUM(INDIRECT(ADDRESS(expenses_min_row,COLUMN())&":"&ADDRESS(expenses_max_row,COLUMN())))} | CR48: {=SUM(INDIRECT(ADDRESS(expenses_min_row,COLUMN())&":"&ADDRESS(expenses_max_row,COLUMN())))} | ... CW48: {=SUM(INDIRECT(ADDRESS(expenses_min_row,COLUMN())&":"&ADDRESS(expenses_max_row,COLUMN())))} | CY48: {=SUM(INDIRECT(ADDRESS(expenses_min_row,COLUMN())&":"&ADDRESS(expenses_max_row,COLUMN())))} | CZ48: {=SUM(INDIRECT(ADDRESS(expenses_min_row,COLUMN())&":"&ADDRESS(expenses_max_row,COLUMN())))} | DA48: {=SUM(INDIRECT(ADDRESS(expenses_min_row,COLUMN())&":"&ADDRESS(expenses_max_row,COLUMN())))} | DB48: {=SUM(INDIRECT(ADDRESS(expenses_min_row,COLUMN())&":"&ADDRESS(expenses_max_row,COLUMN())))} | DC48: {=SUM(INDIRECT(ADDRESS(expenses_min_row,COLUMN())&":"&ADDRESS(expenses_max_row,COLUMN())))} | DD48: {=SUM(INDIRECT(ADDRESS(expenses_min_row,COLUMN())&":"&ADDRESS(expenses_max_row,COLUMN())))} | DE48: {=SUM(INDIRECT(ADDRESS(expenses_min_row,COLUMN())&":"&ADDRESS(expenses_max_row,COLUMN())))} | DF48: {=SUM(INDIRECT(ADDRESS(expenses_min_row,COLUMN())&":"&ADDRESS(expenses_max_row,COLUMN())))} | ... DK48: {=SUM(INDIRECT(ADDRESS(expenses_min_row,COLUMN())&":"&ADDRESS(expenses_max_row,COLUMN())))} | DM48: {=SUM(INDIRECT(ADDRESS(expenses_min_row,COLUMN())&":"&ADDRESS(expenses_max_row,COLUMN())))} | DN48: {=SUM(INDIRECT(ADDRESS(expenses_min_row,COLUMN())&":"&ADDRESS(expenses_max_row,COLUMN())))} | DO48: {=SUM(INDIRECT(ADDRESS(expenses_min_row,COLUMN())&":"&ADDRESS(expenses_max_row,COLUMN())))} | DP48: {=SUM(INDIRECT(ADDRESS(expenses_min_row,COLUMN())&":"&ADDRESS(expenses_max_row,COLUMN())))} | DQ48: {=SUM(INDIRECT(ADDRESS(expenses_min_row,COLUMN())&":"&ADDRESS(expenses_max_row,COLUMN())))} | DR48: {=SUM(INDIRECT(ADDRESS(expenses_min_row,COLUMN())&":"&ADDRESS(expenses_max_row,COLUMN())))} | DS48: {=SUM(INDIRECT(ADDRESS(expenses_min_row,COLUMN())&":"&ADDRESS(expenses_max_row,COLUMN())))} | DT48: {=SUM(INDIRECT(ADDRESS(expenses_min_row,COLUMN())&":"&ADDRESS(expenses_max_row,COLUMN())))} | ... DY48: {=SUM(INDIRECT(ADDRESS(expenses_min_row,COLUMN())&":"&ADDRESS(expenses_max_row,COLUMN())))} | EA48: {=SUM(INDIRECT(ADDRESS(expenses_min_row,COLUMN())&":"&ADDRESS(expenses_max_row,COLUMN())))} | EB48: {=SUM(INDIRECT(ADDRESS(expenses_min_row,COLUMN())&":"&ADDRESS(expenses_max_row,COLUMN())))} | EC48: {=SUM(INDIRECT(ADDRESS(expenses_min_row,COLUMN())&":"&ADDRESS(expenses_max_row,COLUMN())))} | ED48: {=SUM(INDIRECT(ADDRESS(expenses_min_row,COLUMN())&":"&ADDRESS(expenses_max_row,COLUMN())))} | EE48: {=SUM(INDIRECT(ADDRESS(expenses_min_row,COLUMN())&":"&ADDRESS(expenses_max_row,COLUMN())))} | EF48: {=SUM(INDIRECT(ADDRESS(expenses_min_row,COLUMN())&":"&ADDRESS(expenses_max_row,COLUMN())))} | EG48: {=SUM(INDIRECT(ADDRESS(expenses_min_row,COLUMN())&":"&ADDRESS(expenses_max_row,COLUMN())))} | EH48: {=SUM(INDIRECT(ADDRESS(expenses_min_row,COLUMN())&":"&ADDRESS(expenses_max_row,COLUMN())))} | ... EM48: {=SUM(INDIRECT(ADDRESS(expenses_min_row,COLUMN())&":"&ADDRESS(expenses_max_row,COLUMN())))}
C50: Savings | E50: =DATE(E$5,1,1) | F50: =DATE(E$5,2,1) | G50: =DATE(E$5,3,1) | H50: =DATE(E$5,4,1) | I50: =DATE(E$5,5,1) | J50: =DATE(E$5,6,1) | K50: =DATE(E$5,7,1) | L50: =DATE(E$5,8,1) | M50: =DATE(E$5,9,1) | N50: =DATE(E$5,10,1) | O50: =DATE(E$5,11,1) | P50: =DATE(E$5,12,1) | Q50: =E$5 | S50: =DATE(S$5,1,1) | T50: =DATE(S$5,2,1) | U50: =DATE(S$5,3,1) | V50: =DATE(S$5,4,1) | W50: =DATE(S$5,5,1) | X50: =DATE(S$5,6,1) | Y50: =DATE(S$5,7,1) | Z50: =DATE(S$5,8,1) | AA50: =DATE(S$5,9,1) | AB50: =DATE(S$5,10,1) | AC50: =DATE(S$5,11,1) | AD50: =DATE(S$5,12,1) | AE50: =S$5 | AG50: =DATE(AG$5,1,1) | AH50: =DATE(AG$5,2,1) | AI50: =DATE(AG$5,3,1) | AJ50: =DATE(AG$5,4,1) | AK50: =DATE(AG$5,5,1) | AL50: =DATE(AG$5,6,1) | AM50: =DATE(AG$5,7,1) | AN50: =DATE(AG$5,8,1) | AO50: =DATE(AG$5,9,1) | AP50: =DATE(AG$5,10,1) | AQ50: =DATE(AG$5,11,1) | AR50: =DATE(AG$5,12,1) | AS50: =AG$5 | AU50: =DATE(AU$5,1,1) | AV50: =DATE(AU$5,2,1) | AW50: =DATE(AU$5,3,1) | AX50: =DATE(AU$5,4,1) | AY50: =DATE(AU$5,5,1) | AZ50: =DATE(AU$5,6,1) | BA50: =DATE(AU$5,7,1) | BB50: =DATE(AU$5,8,1) | BC50: =DATE(AU$5,9,1) | BD50: =DATE(AU$5,10,1) | BE50: =DATE(AU$5,11,1) | BF50: =DATE(AU$5,12,1) | BG50: =AU$5 | BI50: =DATE(BI$5,1,1) | BJ50: =DATE(BI$5,2,1) | BK50: =DATE(BI$5,3,1) | BL50: =DATE(BI$5,4,1) | BM50: =DATE(BI$5,5,1) | BN50: =DATE(BI$5,6,1) | BO50: =DATE(BI$5,7,1) | BP50: =DATE(BI$5,8,1) | BQ50: =DATE(BI$5,9,1) | BR50: =DATE(BI$5,10,1) | BS50: =DATE(BI$5,11,1) | BT50: =DATE(BI$5,12,1) | BU50: =BI$5 | BW50: =DATE(BW$5,1,1) | BX50: =DATE(BW$5,2,1) | BY50: =DATE(BW$5,3,1) | BZ50: =DATE(BW$5,4,1) | CA50: =DATE(BW$5,5,1) | CB50: =DATE(BW$5,6,1) | CC50: =DATE(BW$5,7,1) | CD50: =DATE(BW$5,8,1) | CE50: =DATE(BW$5,9,1) | CF50: =DATE(BW$5,10,1) | CG50: =DATE(BW$5,11,1) | CH50: =DATE(BW$5,12,1) | CI50: =BW$5 | CK50: =DATE(CK$5,1,1) | CL50: =DATE(CK$5,2,1) | CM50: =DATE(CK$5,3,1) | CN50: =DATE(CK$5,4,1) | CO50: =DATE(CK$5,5,1) | CP50: =DATE(CK$5,6,1) | CQ50: =DATE(CK$5,7,1) | CR50: =DATE(CK$5,8,1) | CS50: =DATE(CK$5,9,1) | CT50: =DATE(CK$5,10,1) | CU50: =DATE(CK$5,11,1) | CV50: =DATE(CK$5,12,1) | CW50: =CK$5 | CY50: =DATE(CY$5,1,1) | CZ50: =DATE(CY$5,2,1) | DA50: =DATE(CY$5,3,1) | DB50: =DATE(CY$5,4,1) | DC50: =DATE(CY$5,5,1) | DD50: =DATE(CY$5,6,1) | DE50: =DATE(CY$5,7,1) | DF50: =DATE(CY$5,8,1) | DG50: =DATE(CY$5,9,1) | DH50: =DATE(CY$5,10,1) | DI50: =DATE(CY$5,11,1) | DJ50: =DATE(CY$5,12,1) | DK50: =CY$5 | DM50: =DATE(DM$5,1,1) | DN50: =DATE(DM$5,2,1) | DO50: =DATE(DM$5,3,1) | DP50: =DATE(DM$5,4,1) | DQ50: =DATE(DM$5,5,1) | DR50: =DATE(DM$5,6,1) | DS50: =DATE(DM$5,7,1) | DT50: =DATE(DM$5,8,1) | DU50: =DATE(DM$5,9,1) | DV50: =DATE(DM$5,10,1) | DW50: =DATE(DM$5,11,1) | DX50: =DATE(DM$5,12,1) | DY50: =DM$5 | EA50: =DATE(EA$5,1,1) | EB50: =DATE(EA$5,2,1) | EC50: =DATE(EA$5,3,1) | ED50: =DATE(EA$5,4,1) | EE50: =DATE(EA$5,5,1) | EF50: =DATE(EA$5,6,1) | EG50: =DATE(EA$5,7,1) | EH50: =DATE(EA$5,8,1) | EI50: =DATE(EA$5,9,1) | EJ50: =DATE(EA$5,10,1) | EK50: =DATE(EA$5,11,1) | EL50: =DATE(EA$5,12,1) | EM50: =EA$5
C51: Emergency Fund | Q51: =SUM(E51:P51) | S51: 3500 | AE51: =SUM(S51:AD51) | AS51: =SUM(AG51:AR51) | BG51: =SUM(AU51:BF51) | BU51: =SUM(BI51:BT51) | CI51: =SUM(BW51:CH51) | CW51: =SUM(CK51:CV51) | DK51: =SUM(CY51:DJ51) | DY51: =SUM(DM51:DX51) | EM51: =SUM(EA51:EL51)
C52: Stock Portfolio | Q52: =SUM(E52:P52) | AE52: =SUM(S52:AD52) | AS52: =SUM(AG52:AR52) | BG52: =SUM(AU52:BF52) | BU52: =SUM(BI52:BT52) | CI52: =SUM(BW52:CH52) | CW52: =SUM(CK52:CV52) | DK52: =SUM(CY52:DJ52) | DY52: =SUM(DM52:DX52) | EM52: =SUM(EA52:EL52)
C53: 401(k) | Q53: =SUM(E53:P53) | AE53: =SUM(S53:AD53) | AS53: =SUM(AG53:AR53) | BG53: =SUM(AU53:BF53) | BU53: =SUM(BI53:BT53) | CI53: =SUM(BW53:CH53) | CW53: =SUM(CK53:CV53) | DK53: =SUM(CY53:DJ53) | DY53: =SUM(DM53:DX53) | EM53: =SUM(EA53:EL53)
C54: Roth IRA | Q54: =SUM(E54:P54) | AE54: =SUM(S54:AD54) | AS54: =SUM(AG54:AR54) | BG54: =SUM(AU54:BF54) | BU54: =SUM(BI54:BT54) | CI54: =SUM(BW54:CH54) | CW54: =SUM(CK54:CV54) | DK54: =SUM(CY54:DJ54) | DY54: =SUM(DM54:DX54) | EM54: =SUM(EA54:EL54)
C55: HSA | Q55: =SUM(E55:P55) | AE55: =SUM(S55:AD55) | AS55: =SUM(AG55:AR55) | BG55: =SUM(AU55:BF55) | BU55: =SUM(BI55:BT55) | CI55: =SUM(BW55:CH55) | CW55: =SUM(CK55:CV55) | DK55: =SUM(CY55:DJ55) | DY55: =SUM(DM55:DX55) | EM55: =SUM(EA55:EL55)
C56: Enter Savings Categoroy | Q56: =SUM(E56:P56) | AE56: =SUM(S56:AD56) | AS56: =SUM(AG56:AR56) | BG56: =SUM(AU56:BF56) | BU56: =SUM(BI56:BT56) | CI56: =SUM(BW56:CH56) | CW56: =SUM(CK56:CV56) | DK56: =SUM(CY56:DJ56) | DY56: =SUM(DM56:DX56) | EM56: =SUM(EA56:EL56)
C57: Enter Savings Categoroy | Q57: =SUM(E57:P57) | AE57: =SUM(S57:AD57) | AS57: =SUM(AG57:AR57) | BG57: =SUM(AU57:BF57) | BU57: =SUM(BI57:BT57) | CI57: =SUM(BW57:CH57) | CW57: =SUM(CK57:CV57) | DK57: =SUM(CY57:DJ57) | DY57: =SUM(DM57:DX57) | EM57: =SUM(EA57:EL57)
C58: Enter Savings Categoroy | Q58: =SUM(E58:P58) | AE58: =SUM(S58:AD58) | AS58: =SUM(AG58:AR58) | BG58: =SUM(AU58:BF58) | BU58: =SUM(BI58:BT58) | CI58: =SUM(BW58:CH58) | CW58: =SUM(CK58:CV58) | DK58: =SUM(CY58:DJ58) | DY58: =SUM(DM58:DX58) | EM58: =SUM(EA58:EL58)
C59: Enter Savings Categoroy | Q59: =SUM(E59:P59) | AE59: =SUM(S59:AD59) | AS59: =SUM(AG59:AR59) | BG59: =SUM(AU59:BF59) | BU59: =SUM(BI59:BT59) | CI59: =SUM(BW59:CH59) | CW59: =SUM(CK59:CV59) | DK59: =SUM(CY59:DJ59) | DY59: =SUM(DM59:DX59) | EM59: =SUM(EA59:EL59)
C60: Total | E60: {=SUM(INDIRECT(ADDRESS(savings_min_row,COLUMN())&":"&ADDRESS(savings_max_row,COLUMN())))} | F60: {=SUM(INDIRECT(ADDRESS(savings_min_row,COLUMN())&":"&ADDRESS(savings_max_row,COLUMN())))} | G60: {=SUM(INDIRECT(ADDRESS(savings_min_row,COLUMN())&":"&ADDRESS(savings_max_row,COLUMN())))} | H60: {=SUM(INDIRECT(ADDRESS(savings_min_row,COLUMN())&":"&ADDRESS(savings_max_row,COLUMN())))} | I60: {=SUM(INDIRECT(ADDRESS(savings_min_row,COLUMN())&":"&ADDRESS(savings_max_row,COLUMN())))} | J60: {=SUM(INDIRECT(ADDRESS(savings_min_row,COLUMN())&":"&ADDRESS(savings_max_row,COLUMN())))} | K60: {=SUM(INDIRECT(ADDRESS(savings_min_row,COLUMN())&":"&ADDRESS(savings_max_row,COLUMN())))} | L60: {=SUM(INDIRECT(ADDRESS(savings_min_row,COLUMN())&":"&ADDRESS(savings_max_row,COLUMN())))} | ... Q60: {=SUM(INDIRECT(ADDRESS(savings_min_row,COLUMN())&":"&ADDRESS(savings_max_row,COLUMN())))} | S60: {=SUM(INDIRECT(ADDRESS(savings_min_row,COLUMN())&":"&ADDRESS(savings_max_row,COLUMN())))} | T60: {=SUM(INDIRECT(ADDRESS(savings_min_row,COLUMN())&":"&ADDRESS(savings_max_row,COLUMN())))} | U60: {=SUM(INDIRECT(ADDRESS(savings_min_row,COLUMN())&":"&ADDRESS(savings_max_row,COLUMN())))} | V60: {=SUM(INDIRECT(ADDRESS(savings_min_row,COLUMN())&":"&ADDRESS(savings_max_row,COLUMN())))} | W60: {=SUM(INDIRECT(ADDRESS(savings_min_row,COLUMN())&":"&ADDRESS(savings_max_row,COLUMN())))} | X60: {=SUM(INDIRECT(ADDRESS(savings_min_row,COLUMN())&":"&ADDRESS(savings_max_row,COLUMN())))} | Y60: {=SUM(INDIRECT(ADDRESS(savings_min_row,COLUMN())&":"&ADDRESS(savings_max_row,COLUMN())))} | Z60: {=SUM(INDIRECT(ADDRESS(savings_min_row,COLUMN())&":"&ADDRESS(savings_max_row,COLUMN())))} | ... AE60: {=SUM(INDIRECT(ADDRESS(savings_min_row,COLUMN())&":"&ADDRESS(savings_max_row,COLUMN())))} | AG60: {=SUM(INDIRECT(ADDRESS(savings_min_row,COLUMN())&":"&ADDRESS(savings_max_row,COLUMN())))} | AH60: {=SUM(INDIRECT(ADDRESS(savings_min_row,COLUMN())&":"&ADDRESS(savings_max_row,COLUMN())))} | AI60: {=SUM(INDIRECT(ADDRESS(savings_min_row,COLUMN())&":"&ADDRESS(savings_max_row,COLUMN())))} | AJ60: {=SUM(INDIRECT(ADDRESS(savings_min_row,COLUMN())&":"&ADDRESS(savings_max_row,COLUMN())))} | AK60: {=SUM(INDIRECT(ADDRESS(savings_min_row,COLUMN())&":"&ADDRESS(savings_max_row,COLUMN())))} | AL60: {=SUM(INDIRECT(ADDRESS(savings_min_row,COLUMN())&":"&ADDRESS(savings_max_row,COLUMN())))} | AM60: {=SUM(INDIRECT(ADDRESS(savings_min_row,COLUMN())&":"&ADDRESS(savings_max_row,COLUMN())))} | AN60: {=SUM(INDIRECT(ADDRESS(savings_min_row,COLUMN())&":"&ADDRESS(savings_max_row,COLUMN())))} | ... AS60: {=SUM(INDIRECT(ADDRESS(savings_min_row,COLUMN())&":"&ADDRESS(savings_max_row,COLUMN())))} | AU60: {=SUM(INDIRECT(ADDRESS(savings_min_row,COLUMN())&":"&ADDRESS(savings_max_row,COLUMN())))} | AV60: {=SUM(INDIRECT(ADDRESS(savings_min_row,COLUMN())&":"&ADDRESS(savings_max_row,COLUMN())))} | AW60: {=SUM(INDIRECT(ADDRESS(savings_min_row,COLUMN())&":"&ADDRESS(savings_max_row,COLUMN())))} | AX60: {=SUM(INDIRECT(ADDRESS(savings_min_row,COLUMN())&":"&ADDRESS(savings_max_row,COLUMN())))} | AY60: {=SUM(INDIRECT(ADDRESS(savings_min_row,COLUMN())&":"&ADDRESS(savings_max_row,COLUMN())))} | AZ60: {=SUM(INDIRECT(ADDRESS(savings_min_row,COLUMN())&":"&ADDRESS(savings_max_row,COLUMN())))} | BA60: {=SUM(INDIRECT(ADDRESS(savings_min_row,COLUMN())&":"&ADDRESS(savings_max_row,COLUMN())))} | BB60: {=SUM(INDIRECT(ADDRESS(savings_min_row,COLUMN())&":"&ADDRESS(savings_max_row,COLUMN())))} | ... BG60: {=SUM(INDIRECT(ADDRESS(savings_min_row,COLUMN())&":"&ADDRESS(savings_max_row,COLUMN())))} | BI60: {=SUM(INDIRECT(ADDRESS(savings_min_row,COLUMN())&":"&ADDRESS(savings_max_row,COLUMN())))} | BJ60: {=SUM(INDIRECT(ADDRESS(savings_min_row,COLUMN())&":"&ADDRESS(savings_max_row,COLUMN())))} | BK60: {=SUM(INDIRECT(ADDRESS(savings_min_row,COLUMN())&":"&ADDRESS(savings_max_row,COLUMN())))} | BL60: {=SUM(INDIRECT(ADDRESS(savings_min_row,COLUMN())&":"&ADDRESS(savings_max_row,COLUMN())))} | BM60: {=SUM(INDIRECT(ADDRESS(savings_min_row,COLUMN())&":"&ADDRESS(savings_max_row,COLUMN())))} | BN60: {=SUM(INDIRECT(ADDRESS(savings_min_row,COLUMN())&":"&ADDRESS(savings_max_row,COLUMN())))} | BO60: {=SUM(INDIRECT(ADDRESS(savings_min_row,COLUMN())&":"&ADDRESS(savings_max_row,COLUMN())))} | BP60: {=SUM(INDIRECT(ADDRESS(savings_min_row,COLUMN())&":"&ADDRESS(savings_max_row,COLUMN())))} | ... BU60: {=SUM(INDIRECT(ADDRESS(savings_min_row,COLUMN())&":"&ADDRESS(savings_max_row,COLUMN())))} | BW60: {=SUM(INDIRECT(ADDRESS(savings_min_row,COLUMN())&":"&ADDRESS(savings_max_row,COLUMN())))} | BX60: {=SUM(INDIRECT(ADDRESS(savings_min_row,COLUMN())&":"&ADDRESS(savings_max_row,COLUMN())))} | BY60: {=SUM(INDIRECT(ADDRESS(savings_min_row,COLUMN())&":"&ADDRESS(savings_max_row,COLUMN())))} | BZ60: {=SUM(INDIRECT(ADDRESS(savings_min_row,COLUMN())&":"&ADDRESS(savings_max_row,COLUMN())))} | CA60: {=SUM(INDIRECT(ADDRESS(savings_min_row,COLUMN())&":"&ADDRESS(savings_max_row,COLUMN())))} | CB60: {=SUM(INDIRECT(ADDRESS(savings_min_row,COLUMN())&":"&ADDRESS(savings_max_row,COLUMN())))} | CC60: {=SUM(INDIRECT(ADDRESS(savings_min_row,COLUMN())&":"&ADDRESS(savings_max_row,COLUMN())))} | CD60: {=SUM(INDIRECT(ADDRESS(savings_min_row,COLUMN())&":"&ADDRESS(savings_max_row,COLUMN())))} | ... CI60: {=SUM(INDIRECT(ADDRESS(savings_min_row,COLUMN())&":"&ADDRESS(savings_max_row,COLUMN())))} | CK60: {=SUM(INDIRECT(ADDRESS(savings_min_row,COLUMN())&":"&ADDRESS(savings_max_row,COLUMN())))} | CL60: {=SUM(INDIRECT(ADDRESS(savings_min_row,COLUMN())&":"&ADDRESS(savings_max_row,COLUMN())))} | CM60: {=SUM(INDIRECT(ADDRESS(savings_min_row,COLUMN())&":"&ADDRESS(savings_max_row,COLUMN())))} | CN60: {=SUM(INDIRECT(ADDRESS(savings_min_row,COLUMN())&":"&ADDRESS(savings_max_row,COLUMN())))} | CO60: {=SUM(INDIRECT(ADDRESS(savings_min_row,COLUMN())&":"&ADDRESS(savings_max_row,COLUMN())))} | CP60: {=SUM(INDIRECT(ADDRESS(savings_min_row,COLUMN())&":"&ADDRESS(savings_max_row,COLUMN())))} | CQ60: {=SUM(INDIRECT(ADDRESS(savings_min_row,COLUMN())&":"&ADDRESS(savings_max_row,COLUMN())))} | CR60: {=SUM(INDIRECT(ADDRESS(savings_min_row,COLUMN())&":"&ADDRESS(savings_max_row,COLUMN())))} | ... CW60: {=SUM(INDIRECT(ADDRESS(savings_min_row,COLUMN())&":"&ADDRESS(savings_max_row,COLUMN())))} | CY60: {=SUM(INDIRECT(ADDRESS(savings_min_row,COLUMN())&":"&ADDRESS(savings_max_row,COLUMN())))} | CZ60: {=SUM(INDIRECT(ADDRESS(savings_min_row,COLUMN())&":"&ADDRESS(savings_max_row,COLUMN())))} | DA60: {=SUM(INDIRECT(ADDRESS(savings_min_row,COLUMN())&":"&ADDRESS(savings_max_row,COLUMN())))} | DB60: {=SUM(INDIRECT(ADDRESS(savings_min_row,COLUMN())&":"&ADDRESS(savings_max_row,COLUMN())))} | DC60: {=SUM(INDIRECT(ADDRESS(savings_min_row,COLUMN())&":"&ADDRESS(savings_max_row,COLUMN())))} | DD60: {=SUM(INDIRECT(ADDRESS(savings_min_row,COLUMN())&":"&ADDRESS(savings_max_row,COLUMN())))} | DE60: {=SUM(INDIRECT(ADDRESS(savings_min_row,COLUMN())&":"&ADDRESS(savings_max_row,COLUMN())))} | DF60: {=SUM(INDIRECT(ADDRESS(savings_min_row,COLUMN())&":"&ADDRESS(savings_max_row,COLUMN())))} | ... DK60: {=SUM(INDIRECT(ADDRESS(savings_min_row,COLUMN())&":"&ADDRESS(savings_max_row,COLUMN())))} | DM60: {=SUM(INDIRECT(ADDRESS(savings_min_row,COLUMN())&":"&ADDRESS(savings_max_row,COLUMN())))} | DN60: {=SUM(INDIRECT(ADDRESS(savings_min_row,COLUMN())&":"&ADDRESS(savings_max_row,COLUMN())))} | DO60: {=SUM(INDIRECT(ADDRESS(savings_min_row,COLUMN())&":"&ADDRESS(savings_max_row,COLUMN())))} | DP60: {=SUM(INDIRECT(ADDRESS(savings_min_row,COLUMN())&":"&ADDRESS(savings_max_row,COLUMN())))} | DQ60: {=SUM(INDIRECT(ADDRESS(savings_min_row,COLUMN())&":"&ADDRESS(savings_max_row,COLUMN())))} | DR60: {=SUM(INDIRECT(ADDRESS(savings_min_row,COLUMN())&":"&ADDRESS(savings_max_row,COLUMN())))} | DS60: {=SUM(INDIRECT(ADDRESS(savings_min_row,COLUMN())&":"&ADDRESS(savings_max_row,COLUMN())))} | DT60: {=SUM(INDIRECT(ADDRESS(savings_min_row,COLUMN())&":"&ADDRESS(savings_max_row,COLUMN())))} | ... DY60: {=SUM(INDIRECT(ADDRESS(savings_min_row,COLUMN())&":"&ADDRESS(savings_max_row,COLUMN())))} | EA60: {=SUM(INDIRECT(ADDRESS(savings_min_row,COLUMN())&":"&ADDRESS(savings_max_row,COLUMN())))} | EB60: {=SUM(INDIRECT(ADDRESS(savings_min_row,COLUMN())&":"&ADDRESS(savings_max_row,COLUMN())))} | EC60: {=SUM(INDIRECT(ADDRESS(savings_min_row,COLUMN())&":"&ADDRESS(savings_max_row,COLUMN())))} | ED60: {=SUM(INDIRECT(ADDRESS(savings_min_row,COLUMN())&":"&ADDRESS(savings_max_row,COLUMN())))} | EE60: {=SUM(INDIRECT(ADDRESS(savings_min_row,COLUMN())&":"&ADDRESS(savings_max_row,COLUMN())))} | EF60: {=SUM(INDIRECT(ADDRESS(savings_min_row,COLUMN())&":"&ADDRESS(savings_max_row,COLUMN())))} | EG60: {=SUM(INDIRECT(ADDRESS(savings_min_row,COLUMN())&":"&ADDRESS(savings_max_row,COLUMN())))} | EH60: {=SUM(INDIRECT(ADDRESS(savings_min_row,COLUMN())&":"&ADDRESS(savings_max_row,COLUMN())))} | ... EM60: {=SUM(INDIRECT(ADDRESS(savings_min_row,COLUMN())&":"&ADDRESS(savings_max_row,COLUMN())))}

Sheet Budget Tracking
B1: Budget Tracking
C11: Date | D11: Type | E11: Category | F11: Amount | G11: Details | H11: Balance | I11: Effective Date
C12: 45658 | I12: =IF(AND(tracking[[#This Row],[Type]]="Income", shift_late_income_status="Active", DAY(tracking[[#This Row],[Date]])>=shift_late_income_starting_day), DATE(YEAR(tracking[[#This Row],[Date]]), MONTH(tracking[[#This Row],[Date]])+1, 1), tracking[[#This Row],[Date]])
I13: =IF(AND(tracking[[#This Row],[Type]]="Income", shift_late_income_status="Active", DAY(tracking[[#This Row],[Date]])>=shift_late_income_starting_day), DATE(YEAR(tracking[[#This Row],[Date]]), MONTH(tracking[[#This Row],[Date]])+1, 1), tracking[[#This Row],[Date]])
I14: =IF(AND(tracking[[#This Row],[Type]]="Income", shift_late_income_status="Active", DAY(tracking[[#This Row],[Date]])>=shift_late_income_starting_day), DATE(YEAR(tracking[[#This Row],[Date]]), MONTH(tracking[[#This Row],[Date]])+1, 1), tracking[[#This Row],[Date]])
I15: =IF(AND(tracking[[#This Row],[Type]]="Income", shift_late_income_status="Active", DAY(tracking[[#This Row],[Date]])>=shift_late_income_starting_day), DATE(YEAR(tracking[[#This Row],[Date]]), MONTH(tracking[[#This Row],[Date]])+1, 1), tracking[[#This Row],[Date]])
I16: =IF(AND(tracking[[#This Row],[Type]]="Income", shift_late_income_status="Active", DAY(tracking[[#This Row],[Date]])>=shift_late_income_starting_day), DATE(YEAR(tracking[[#This Row],[Date]]), MONTH(tracking[[#This Row],[Date]])+1, 1), tracking[[#This Row],[Date]])
I17: =IF(AND(tracking[[#This Row],[Type]]="Income", shift_late_income_status="Active", DAY(tracking[[#This Row],[Date]])>=shift_late_income_starting_day), DATE(YEAR(tracking[[#This Row],[Date]]), MONTH(tracking[[#This Row],[Date]])+1, 1), tracking[[#This Row],[Date]])
I18: =IF(AND(tracking[[#This Row],[Type]]="Income", shift_late_income_status="Active", DAY(tracking[[#This Row],[Date]])>=shift_late_income_starting_day), DATE(YEAR(tracking[[#This Row],[Date]]), MONTH(tracking[[#This Row],[Date]])+1, 1), tracking[[#This Row],[Date]])
I19: =IF(AND(tracking[[#This Row],[Type]]="Income", shift_late_income_status="Active", DAY(tracking[[#This Row],[Date]])>=shift_late_income_starting_day), DATE(YEAR(tracking[[#This Row],[Date]]), MONTH(tracking[[#This Row],[Date]])+1, 1), tracking[[#This Row],[Date]])
I20: =IF(AND(tracking[[#This Row],[Type]]="Income", shift_late_income_status="Active", DAY(tracking[[#This Row],[Date]])>=shift_late_income_starting_day), DATE(YEAR(tracking[[#This Row],[Date]]), MONTH(tracking[[#This Row],[Date]])+1, 1), tracking[[#This Row],[Date]])
I21: =IF(AND(tracking[[#This Row],[Type]]="Income", shift_late_income_status="Active", DAY(tracking[[#This Row],[Date]])>=shift_late_income_starting_day), DATE(YEAR(tracking[[#This Row],[Date]]), MONTH(tracking[[#This Row],[Date]])+1, 1), tracking[[#This Row],[Date]])
I22: =IF(AND(tracking[[#This Row],[Type]]="Income", shift_late_income_status="Active", DAY(tracking[[#This Row],[Date]])>=shift_late_income_starting_day), DATE(YEAR(tracking[[#This Row],[Date]]), MONTH(tracking[[#This Row],[Date]])+1, 1), tracking[[#This Row],[Date]])
I23: =IF(AND(tracking[[#This Row],[Type]]="Income", shift_late_income_status="Active", DAY(tracking[[#This Row],[Date]])>=shift_late_income_starting_day), DATE(YEAR(tracking[[#This Row],[Date]]), MONTH(tracking[[#This Row],[Date]])+1, 1), tracking[[#This Row],[Date]])
I24: =IF(AND(tracking[[#This Row],[Type]]="Income", shift_late_income_status="Active", DAY(tracking[[#This Row],[Date]])>=shift_late_income_starting_day), DATE(YEAR(tracking[[#This Row],[Date]]), MONTH(tracking[[#This Row],[Date]])+1, 1), tracking[[#This Row],[Date]])
... I226: =IF(AND(tracking[[#This Row],[Type]]="Income", shift_late_income_status="Active", DAY(tracking[[#This Row],[Date]])>=shift_late_income_starting_day), DATE(YEAR(tracking[[#This Row],[Date]]), MONTH(tracking[[#This Row],[Date]])+1, 1), tracking[[#This Row],[Date]])

Sheet Budget Dashboard
Y3: ‚
AQ5: Year
AN6: Select the year to view → | AQ6: 2025
AQ8: Period
AN9: Select the period to view → | AQ9: Current Month
Y11: ="Breakdown - " & IF(selected_period="Total Year", selected_year & " " & "(Total Year)", selected_period_display & " " & selected_year) | AF11: ="Summary - " & IF(selected_period="Total Year", selected_year & " " & "(Total Year)", selected_period_display & " " & selected_year)
C12: row_id | D12: header_row_id | E12: is_header | F12: is_cat | G12: is_total | H12: is_empty | I12: type | J12: item | K12: tracked | L12: budget | M12: sort_min_row | N12: sort_max_row | O12: tracked_range | P12: tracked_rank | Q12: budget_range | R12: budget_rank | S12: comb_rank | T12: comb_rank_range | U12: comb_rank_norm | V12: comb_rank_norm_run_range | W12: comb_rank_unique | X12: sorted_row_id (Lookup)
C13: {=income_header_row} | D13: =IF(is_header, row_id, IF(NOT(is_empty), D12, -1)) | E13: {=OR(row_id=income_header_row, row_id=expenses_header_row, row_id=savings_header_row) * 1} | F13: =1 * NOT(OR(is_header, is_total, is_empty)) | G13: {=OR(row_id=income_total_row, row_id=expenses_total_row, row_id=savings_total_row) * 1} | H13: =OR(row_id="/1", row_id="/2", row_id=-1)*1 | I13: {=IFERROR(INDEX('Budget Planning'!$C:$C, header_row_id), "")} | J13: {=IFERROR(INDEX('Budget Planning'!$C:$C, row_id), "")} | K13: {=IF(OR(is_header, is_empty), "", IF(is_total, IF(selected_period="Total Year", SUM(tracking[Amount] * (tracking[Type]=type) * (YEAR(tracking[Effective Date])=selected_year)), SUM(tracking[Amount] * (tracking[Type]=type) * (YEAR(tracking[Effective Date])=selected_year) * (MONTH(tracking[Effective Date])=selected_period))), IF(selected_period="Total Year", SUM(tracking[Amount] * (tracking[Type]=type) * (tracking[Category]=item) * (YEAR(tracking[Effective Date])=selected_year)), SUM(tracking[Amount] * (tracking[Type]=type) * (tracking[Category]=item) * (YEAR(tracking[Effective Date])=selected_year) * (MONTH(tracking[Effective Date])=selected_period)))))} | L13: {=IF(OR(is_header, is_empty), "", INDEX('Budget Planning'!$E:$EM, row_id, MATCH(IF(selected_period="Total Year", selected_year, DATE(selected_year, selected_period, 1)), 'Budget Planning'!$E$9:$EM$9, 0)))} | M13: {=IF(is_cat, IF(header_row_id=income_header_row, MATCH(income_min_row, $C:$C, 0), IF(header_row_id=expenses_header_row, MATCH(expenses_min_row, $C:$C, 0), IF(header_row_id=savings_header_row, MATCH(savings_min_row, $C:$C, 0), ""))), "")} | N13: {=IF(is_cat, IF(header_row_id=income_header_row, MATCH(income_max_row, $C:$C, 0), IF(header_row_id=expenses_header_row, MATCH(expenses_max_row, $C:$C, 0), IF(header_row_id=savings_header_row, MATCH(savings_max_row, $C:$C, 0), ""))), "")} | O13: =IF(is_cat, ADDRESS(sort_min_row, COLUMN(tracked)) & ":" & ADDRESS(sort_max_row, COLUMN(tracked)), "") | P13: =IF(is_cat, RANK(tracked, INDIRECT(tracked_range), 0), "") | Q13: =IF(is_cat, ADDRESS(sort_min_row, COLUMN(budget)) & ":" & ADDRESS(sort_max_row, COLUMN(budget)), "") | R13: =IF(is_cat, RANK(budget, INDIRECT(budget_range), 0), "") | S13: =IF(is_cat, _xlfn.NUMBERVALUE(tracked_rank & budget_rank), "") | T13: =IF(is_cat, ADDRESS(sort_min_row, COLUMN(comb_rank)) & ":" & ADDRESS(sort_max_row, COLUMN(comb_rank)), "") | U13: =IF(is_cat, RANK(comb_rank, INDIRECT(comb_rank_range), 1), "") | V13: =IF(is_cat, ADDRESS(sort_min_row, COLUMN(comb_rank_norm)) & ":" & ADDRESS(ROW(), COLUMN(comb_rank_norm)), "") | W13: =IF(is_cat, comb_rank_norm + COUNTIF(INDIRECT(comb_rank_norm_run_range), comb_rank_norm)-1, "") | X13: =IF(is_cat, header_row_id + comb_rank_unique, row_id) | Y13: =IF(is_empty, "", INDEX($J:$J, MATCH(row_id, $X:$X, 0))) | Z13: =IF(is_empty, "", IF(is_header, "Tracked", INDEX($K:$K, MATCH(row_id, $X:$X, 0)))) | AA13: =IF(is_empty, "", IF(is_header, "Budget", INDEX($L:$L, MATCH(row_id, $X:$X, 0)))) | AB13: =IF(is_empty, "", IF(is_header, "% Compl.", IFERROR(out_tracked / out_budget, "-"))) | AC13: =IF(is_empty, "", IF(is_header, "Remaining", IF(out_budget - out_tracked > 0, out_budget - out_tracked, 0))) | AD13: =IF(is_empty, "", IF(is_header, "Excess", IF(out_budget - out_tracked < 0, out_tracked - out_budget, 0)))
C14: {=IF(C13=-1,-1, IF(C13<income_max_row,C13+1, IF(C13=income_max_row,income_total_row, IF(C13=income_total_row,"/1", IF(C13="/1",expenses_header_row, IF(C13<expenses_max_row,C13+1, IF(C13=expenses_max_row,expenses_total_row, IF(C13=expenses_total_row, "/2", IF(C13="/2", savings_header_row, IF(C13<savings_max_row, C13+1, IF(C13=savings_max_row, savings_total_row, -1)))))))))))} | D14: =IF(is_header, row_id, IF(NOT(is_empty), D13, -1)) | E14: {=OR(row_id=income_header_row, row_id=expenses_header_row, row_id=savings_header_row) * 1} | F14: =1 * NOT(OR(is_header, is_total, is_empty)) | G14: {=OR(row_id=income_total_row, row_id=expenses_total_row, row_id=savings_total_row) * 1} | H14: =OR(row_id="/1", row_id="/2", row_id=-1)*1 | I14: {=IFERROR(INDEX('Budget Planning'!$C:$C, header_row_id), "")} | J14: {=IFERROR(INDEX('Budget Planning'!$C:$C, row_id), "")} | K14: {=IF(OR(is_header, is_empty), "", IF(is_total, IF(selected_period="Total Year", SUM(tracking[Amount] * (tracking[Type]=type) * (YEAR(tracking[Effective Date])=selected_year)), SUM(tracking[Amount] * (tracking[Type]=type) * (YEAR(tracking[Effective Date])=selected_year) * (MONTH(tracking[Effective Date])=selected_period))), IF(selected_period="Total Year", SUM(tracking[Amount] * (tracking[Type]=type) * (tracking[Category]=item) * (YEAR(tracking[Effective Date])=selected_year)), SUM(tracking[Amount] * (tracking[Type]=type) * (tracking[Category]=item) * (YEAR(tracking[Effective Date])=selected_year) * (MONTH(tracking[Effective Date])=selected_period)))))} | L14: {=IF(OR(is_header, is_empty), "", INDEX('Budget Planning'!$E:$EM, row_id, MATCH(IF(selected_period="Total Year", selected_year, DATE(selected_year, selected_period, 1)), 'Budget Planning'!$E$9:$EM$9, 0)))} | M14: {=IF(is_cat, IF(header_row_id=income_header_row, MATCH(income_min_row, $C:$C, 0), IF(header_row_id=expenses_header_row, MATCH(expenses_min_row, $C:$C, 0), IF(header_row_id=savings_header_row, MATCH(savings_min_row, $C:$C, 0), ""))), "")} | N14: {=IF(is_cat, IF(header_row_id=income_header_row, MATCH(income_max_row, $C:$C, 0), IF(header_row_id=expenses_header_row, MATCH(expenses_max_row, $C:$C, 0), IF(header_row_id=savings_header_row, MATCH(savings_max_row, $C:$C, 0), ""))), "")} | O14: =IF(is_cat, ADDRESS(sort_min_row, COLUMN(tracked)) & ":" & ADDRESS(sort_max_row, COLUMN(tracked)), "") | P14: =IF(is_cat, RANK(tracked, INDIRECT(tracked_range), 0), "") | Q14: =IF(is_cat, ADDRESS(sort_min_row, COLUMN(budget)) & ":" & ADDRESS(sort_max_row, COLUMN(budget)), "") | R14: =IF(is_cat, RANK(budget, INDIRECT(budget_range), 0), "") | S14: =IF(is_cat, _xlfn.NUMBERVALUE(tracked_rank & budget_rank), "") | T14: =IF(is_cat, ADDRESS(sort_min_row, COLUMN(comb_rank)) & ":" & ADDRESS(sort_max_row, COLUMN(comb_rank)), "") | U14: =IF(is_cat, RANK(comb_rank, INDIRECT(comb_rank_range), 1), "") | V14: =IF(is_cat, ADDRESS(sort_min_row, COLUMN(comb_rank_norm)) & ":" & ADDRESS(ROW(), COLUMN(comb_rank_norm)), "") | W14: =IF(is_cat, comb_rank_norm + COUNTIF(INDIRECT(comb_rank_norm_run_range), comb_rank_norm)-1, "") | X14: =IF(is_cat, header_row_id + comb_rank_unique, row_id) | Y14: =IF(is_empty, "", INDEX($J:$J, MATCH(row_id, $X:$X, 0))) | Z14: =IF(is_empty, "", IF(is_header, "Tracked", INDEX($K:$K, MATCH(row_id, $X:$X, 0)))) | AA14: =IF(is_empty, "", IF(is_header, "Budget", INDEX($L:$L, MATCH(row_id, $X:$X, 0)))) | AB14: =IF(is_empty, "", IF(is_header, "% Compl.", IFERROR(out_tracked / out_budget, "-"))) | AC14: =IF(is_empty, "", IF(is_header, "Remaining", IF(out_budget - out_tracked > 0, out_budget - out_tracked, 0))) | AD14: =IF(is_empty, "", IF(is_header, "Excess", IF(out_budget - out_tracked < 0, out_tracked - out_budget, 0)))
C15: {=IF(C14=-1,-1, IF(C14<income_max_row,C14+1, IF(C14=income_max_row,income_total_row, IF(C14=income_total_row,"/1", IF(C14="/1",expenses_header_row, IF(C14<expenses_max_row,C14+1, IF(C14=expenses_max_row,expenses_total_row, IF(C14=expenses_total_row, "/2", IF(C14="/2", savings_header_row, IF(C14<savings_max_row, C14+1, IF(C14=savings_max_row, savings_total_row, -1)))))))))))} | D15: =IF(is_header, row_id, IF(NOT(is_empty), D14, -1)) | E15: {=OR(row_id=income_header_row, row_id=expenses_header_row, row_id=savings_header_row) * 1} | F15: =1 * NOT(OR(is_header, is_total, is_empty)) | G15: {=OR(row_id=income_total_row, row_id=expenses_total_row, row_id=savings_total_row) * 1} | H15: =OR(row_id="/1", row_id="/2", row_id=-1)*1 | I15: {=IFERROR(INDEX('Budget Planning'!$C:$C, header_row_id), "")} | J15: {=IFERROR(INDEX('Budget Planning'!$C:$C, row_id), "")} | K15: {=IF(OR(is_header, is_empty), "", IF(is_total, IF(selected_period="Total Year", SUM(tracking[Amount] * (tracking[Type]=type) * (YEAR(tracking[Effective Date])=selected_year)), SUM(tracking[Amount] * (tracking[Type]=type) * (YEAR(tracking[Effective Date])=selected_year) * (MONTH(tracking[Effective Date])=selected_period))), IF(selected_period="Total Year", SUM(tracking[Amount] * (tracking[Type]=type) * (tracking[Category]=item) * (YEAR(tracking[Effective Date])=selected_year)), SUM(tracking[Amount] * (tracking[Type]=type) * (tracking[Category]=item) * (YEAR(tracking[Effective Date])=selected_year) * (MONTH(tracking[Effective Date])=selected_period)))))} | L15: {=IF(OR(is_header, is_empty), "", INDEX('Budget Planning'!$E:$EM, row_id, MATCH(IF(selected_period="Total Year", selected_year, DATE(selected_year, selected_period, 1)), 'Budget Planning'!$E$9:$EM$9, 0)))} | M15: {=IF(is_cat, IF(header_row_id=income_header_row, MATCH(income_min_row, $C:$C, 0), IF(header_row_id=expenses_header_row, MATCH(expenses_min_row, $C:$C, 0), IF(header_row_id=savings_header_row, MATCH(savings_min_row, $C:$C, 0), ""))), "")} | N15: {=IF(is_cat, IF(header_row_id=income_header_row, MATCH(income_max_row, $C:$C, 0), IF(header_row_id=expenses_header_row, MATCH(expenses_max_row, $C:$C, 0), IF(header_row_id=savings_header_row, MATCH(savings_max_row, $C:$C, 0), ""))), "")} | O15: =IF(is_cat, ADDRESS(sort_min_row, COLUMN(tracked)) & ":" & ADDRESS(sort_max_row, COLUMN(tracked)), "") | P15: =IF(is_cat, RANK(tracked, INDIRECT(tracked_range), 0), "") | Q15: =IF(is_cat, ADDRESS(sort_min_row, COLUMN(budget)) & ":" & ADDRESS(sort_max_row, COLUMN(budget)), "") | R15: =IF(is_cat, RANK(budget, INDIRECT(budget_range), 0), "") | S15: =IF(is_cat, _xlfn.NUMBERVALUE(tracked_rank & budget_rank), "") | T15: =IF(is_cat, ADDRESS(sort_min_row, COLUMN(comb_rank)) & ":" & ADDRESS(sort_max_row, COLUMN(comb_rank)), "") | U15: =IF(is_cat, RANK(comb_rank, INDIRECT(comb_rank_range), 1), "") | V15: =IF(is_cat, ADDRESS(sort_min_row, COLUMN(comb_rank_norm)) & ":" & ADDRESS(ROW(), COLUMN(comb_rank_norm)), "") | W15: =IF(is_cat, comb_rank_norm + COUNTIF(INDIRECT(comb_rank_norm_run_range), comb_rank_norm)-1, "") | X15: =IF(is_cat, header_row_id + comb_rank_unique, row_id) | Y15: =IF(is_empty, "", INDEX($J:$J, MATCH(row_id, $X:$X, 0))) | Z15: =IF(is_empty, "", IF(is_header, "Tracked", INDEX($K:$K, MATCH(row_id, $X:$X, 0)))) | AA15: =IF(is_empty, "", IF(is_header, "Budget", INDEX($L:$L, MATCH(row_id, $X:$X, 0)))) | AB15: =IF(is_empty, "", IF(is_header, "% Compl.", IFERROR(out_tracked / out_budget, "-"))) | AC15: =IF(is_empty, "", IF(is_header, "Remaining", IF(out_budget - out_tracked > 0, out_budget - out_tracked, 0))) | AD15: =IF(is_empty, "", IF(is_header, "Excess", IF(out_budget - out_tracked < 0, out_tracked - out_budget, 0)))
C16: {=IF(C15=-1,-1, IF(C15<income_max_row,C15+1, IF(C15=income_max_row,income_total_row, IF(C15=income_total_row,"/1", IF(C15="/1",expenses_header_row, IF(C15<expenses_max_row,C15+1, IF(C15=expenses_max_row,expenses_total_row, IF(C15=expenses_total_row, "/2", IF(C15="/2", savings_header_row, IF(C15<savings_max_row, C15+1, IF(C15=savings_max_row, savings_total_row, -1)))))))))))} | D16: =IF(is_header, row_id, IF(NOT(is_empty), D15, -1)) | E16: {=OR(row_id=income_header_row, row_id=expenses_header_row, row_id=savings_header_row) * 1} | F16: =1 * NOT(OR(is_header, is_total, is_empty)) | G16: {=OR(row_id=income_total_row, row_id=expenses_total_row, row_id=savings_total_row) * 1} | H16: =OR(row_id="/1", row_id="/2", row_id=-1)*1 | I16: {=IFERROR(INDEX('Budget Planning'!$C:$C, header_row_id), "")} | J16: {=IFERROR(INDEX('Budget Planning'!$C:$C, row_id), "")} | K16: {=IF(OR(is_header, is_empty), "", IF(is_total, IF(selected_period="Total Year", SUM(tracking[Amount] * (tracking[Type]=type) * (YEAR(tracking[Effective Date])=selected_year)), SUM(tracking[Amount] * (tracking[Type]=type) * (YEAR(tracking[Effective Date])=selected_year) * (MONTH(tracking[Effective Date])=selected_period))), IF(selected_period="Total Year", SUM(tracking[Amount] * (tracking[Type]=type) * (tracking[Category]=item) * (YEAR(tracking[Effective Date])=selected_year)), SUM(tracking[Amount] * (tracking[Type]=type) * (tracking[Category]=item) * (YEAR(tracking[Effective Date])=selected_year) * (MONTH(tracking[Effective Date])=selected_period)))))} | L16: {=IF(OR(is_header, is_empty), "", INDEX('Budget Planning'!$E:$EM, row_id, MATCH(IF(selected_period="Total Year", selected_year, DATE(selected_year, selected_period, 1)), 'Budget Planning'!$E$9:$EM$9, 0)))} | M16: {=IF(is_cat, IF(header_row_id=income_header_row, MATCH(income_min_row, $C:$C, 0), IF(header_row_id=expenses_header_row, MATCH(expenses_min_row, $C:$C, 0), IF(header_row_id=savings_header_row, MATCH(savings_min_row, $C:$C, 0), ""))), "")} | N16: {=IF(is_cat, IF(header_row_id=income_header_row, MATCH(income_max_row, $C:$C, 0), IF(header_row_id=expenses_header_row, MATCH(expenses_max_row, $C:$C, 0), IF(header_row_id=savings_header_row, MATCH(savings_max_row, $C:$C, 0), ""))), "")} | O16: =IF(is_cat, ADDRESS(sort_min_row, COLUMN(tracked)) & ":" & ADDRESS(sort_max_row, COLUMN(tracked)), "") | P16: =IF(is_cat, RANK(tracked, INDIRECT(tracked_range), 0), "") | Q16: =IF(is_cat, ADDRESS(sort_min_row, COLUMN(budget)) & ":" & ADDRESS(sort_max_row, COLUMN(budget)), "") | R16: =IF(is_cat, RANK(budget, INDIRECT(budget_range), 0), "") | S16: =IF(is_cat, _xlfn.NUMBERVALUE(tracked_rank & budget_rank), "") | T16: =IF(is_cat, ADDRESS(sort_min_row, COLUMN(comb_rank)) & ":" & ADDRESS(sort_max_row, COLUMN(comb_rank)), "") | U16: =IF(is_cat, RANK(comb_rank, INDIRECT(comb_rank_range), 1), "") | V16: =IF(is_cat, ADDRESS(sort_min_row, COLUMN(comb_rank_norm)) & ":" & ADDRESS(ROW(), COLUMN(comb_rank_norm)), "") | W16: =IF(is_cat, comb_rank_norm + COUNTIF(INDIRECT(comb_rank_norm_run_range), comb_rank_norm)-1, "") | X16: =IF(is_cat, header_row_id + comb_rank_unique, row_id) | Y16: =IF(is_empty, "", INDEX($J:$J, MATCH(row_id, $X:$X, 0))) | Z16: =IF(is_empty, "", IF(is_header, "Tracked", INDEX($K:$K, MATCH(row_id, $X:$X, 0)))) | AA16: =IF(is_empty, "", IF(is_header, "Budget", INDEX($L:$L, MATCH(row_id, $X:$X, 0)))) | AB16: =IF(is_empty, "", IF(is_header, "% Compl.", IFERROR(out_tracked / out_budget, "-"))) | AC16: =IF(is_empty, "", IF(is_header, "Remaining", IF(out_budget - out_tracked > 0, out_budget - out_tracked, 0))) | AD16: =IF(is_empty, "", IF(is_header, "Excess", IF(out_budget - out_tracked < 0, out_tracked - out_budget, 0))) | AI16: =Calculation!E35 | AJ16: =Calculation!F35
C17: {=IF(C16=-1,-1, IF(C16<income_max_row,C16+1, IF(C16=income_max_row,income_total_row, IF(C16=income_total_row,"/1", IF(C16="/1",expenses_header_row, IF(C16<expenses_max_row,C16+1, IF(C16=expenses_max_row,expenses_total_row, IF(C16=expenses_total_row, "/2", IF(C16="/2", savings_header_row, IF(C16<savings_max_row, C16+1, IF(C16=savings_max_row, savings_total_row, -1)))))))))))} | D17: =IF(is_header, row_id, IF(NOT(is_empty), D16, -1)) | E17: {=OR(row_id=income_header_row, row_id=expenses_header_row, row_id=savings_header_row) * 1} | F17: =1 * NOT(OR(is_header, is_total, is_empty)) | G17: {=OR(row_id=income_total_row, row_id=expenses_total_row, row_id=savings_total_row) * 1} | H17: =OR(row_id="/1", row_id="/2", row_id=-1)*1 | I17: {=IFERROR(INDEX('Budget Planning'!$C:$C, header_row_id), "")} | J17: {=IFERROR(INDEX('Budget Planning'!$C:$C, row_id), "")} | K17: {=IF(OR(is_header, is_empty), "", IF(is_total, IF(selected_period="Total Year", SUM(tracking[Amount] * (tracking[Type]=type) * (YEAR(tracking[Effective Date])=selected_year)), SUM(tracking[Amount] * (tracking[Type]=type) * (YEAR(tracking[Effective Date])=selected_year) * (MONTH(tracking[Effective Date])=selected_period))), IF(selected_period="Total Year", SUM(tracking[Amount] * (tracking[Type]=type) * (tracking[Category]=item) * (YEAR(tracking[Effective Date])=selected_year)), SUM(tracking[Amount] * (tracking[Type]=type) * (tracking[Category]=item) * (YEAR(tracking[Effective Date])=selected_year) * (MONTH(tracking[Effective Date])=selected_period)))))} | L17: {=IF(OR(is_header, is_empty), "", INDEX('Budget Planning'!$E:$EM, row_id, MATCH(IF(selected_period="Total Year", selected_year, DATE(selected_year, selected_period, 1)), 'Budget Planning'!$E$9:$EM$9, 0)))} | M17: {=IF(is_cat, IF(header_row_id=income_header_row, MATCH(income_min_row, $C:$C, 0), IF(header_row_id=expenses_header_row, MATCH(expenses_min_row, $C:$C, 0), IF(header_row_id=savings_header_row, MATCH(savings_min_row, $C:$C, 0), ""))), "")} | N17: {=IF(is_cat, IF(header_row_id=income_header_row, MATCH(income_max_row, $C:$C, 0), IF(header_row_id=expenses_header_row, MATCH(expenses_max_row, $C:$C, 0), IF(header_row_id=savings_header_row, MATCH(savings_max_row, $C:$C, 0), ""))), "")} | O17: =IF(is_cat, ADDRESS(sort_min_row, COLUMN(tracked)) & ":" & ADDRESS(sort_max_row, COLUMN(tracked)), "") | P17: =IF(is_cat, RANK(tracked, INDIRECT(tracked_range), 0), "") | Q17: =IF(is_cat, ADDRESS(sort_min_row, COLUMN(budget)) & ":" & ADDRESS(sort_max_row, COLUMN(budget)), "") | R17: =IF(is_cat, RANK(budget, INDIRECT(budget_range), 0), "") | S17: =IF(is_cat, _xlfn.NUMBERVALUE(tracked_rank & budget_rank), "") | T17: =IF(is_cat, ADDRESS(sort_min_row, COLUMN(comb_rank)) & ":" & ADDRESS(sort_max_row, COLUMN(comb_rank)), "") | U17: =IF(is_cat, RANK(comb_rank, INDIRECT(comb_rank_range), 1), "") | V17: =IF(is_cat, ADDRESS(sort_min_row, COLUMN(comb_rank_norm)) & ":" & ADDRESS(ROW(), COLUMN(comb_rank_norm)), "") | W17: =IF(is_cat, comb_rank_norm + COUNTIF(INDIRECT(comb_rank_norm_run_range), comb_rank_norm)-1, "") | X17: =IF(is_cat, header_row_id + comb_rank_unique, row_id) | Y17: =IF(is_empty, "", INDEX($J:$J, MATCH(row_id, $X:$X, 0))) | Z17: =IF(is_empty, "", IF(is_header, "Tracked", INDEX($K:$K, MATCH(row_id, $X:$X, 0)))) | AA17: =IF(is_empty, "", IF(is_header, "Budget", INDEX($L:$L, MATCH(row_id, $X:$X, 0)))) | AB17: =IF(is_empty, "", IF(is_header, "% Compl.", IFERROR(out_tracked / out_budget, "-"))) | AC17: =IF(is_empty, "", IF(is_header, "Remaining", IF(out_budget - out_tracked > 0, out_budget - out_tracked, 0))) | AD17: =IF(is_empty, "", IF(is_header, "Excess", IF(out_budget - out_tracked < 0, out_tracked - out_budget, 0))) | AI17: =Calculation!E36 | AJ17: =Calculation!F36
C18: {=IF(C17=-1,-1, IF(C17<income_max_row,C17+1, IF(C17=income_max_row,income_total_row, IF(C17=income_total_row,"/1", IF(C17="/1",expenses_header_row, IF(C17<expenses_max_row,C17+1, IF(C17=expenses_max_row,expenses_total_row, IF(C17=expenses_total_row, "/2", IF(C17="/2", savings_header_row, IF(C17<savings_max_row, C17+1, IF(C17=savings_max_row, savings_total_row, -1)))))))))))} | D18: =IF(is_header, row_id, IF(NOT(is_empty), D17, -1)) | E18: {=OR(row_id=income_header_row, row_id=expenses_header_row, row_id=savings_header_row) * 1} | F18: =1 * NOT(OR(is_header, is_total, is_empty)) | G18: {=OR(row_id=income_total_row, row_id=expenses_total_row, row_id=savings_total_row) * 1} | H18: =OR(row_id="/1", row_id="/2", row_id=-1)*1 | I18: {=IFERROR(INDEX('Budget Planning'!$C:$C, header_row_id), "")} | J18: {=IFERROR(INDEX('Budget Planning'!$C:$C, row_id), "")} | K18: {=IF(OR(is_header, is_empty), "", IF(is_total, IF(selected_period="Total Year", SUM(tracking[Amount] * (tracking[Type]=type) * (YEAR(tracking[Effective Date])=selected_year)), SUM(tracking[Amount] * (tracking[Type]=type) * (YEAR(tracking[Effective Date])=selected_year) * (MONTH(tracking[Effective Date])=selected_period))), IF(selected_period="Total Year", SUM(tracking[Amount] * (tracking[Type]=type) * (tracking[Category]=item) * (YEAR(tracking[Effective Date])=selected_year)), SUM(tracking[Amount] * (tracking[Type]=type) * (tracking[Category]=item) * (YEAR(tracking[Effective Date])=selected_year) * (MONTH(tracking[Effective Date])=selected_period)))))} | L18: {=IF(OR(is_header, is_empty), "", INDEX('Budget Planning'!$E:$EM, row_id, MATCH(IF(selected_period="Total Year", selected_year, DATE(selected_year, selected_period, 1)), 'Budget Planning'!$E$9:$EM$9, 0)))} | M18: {=IF(is_cat, IF(header_row_id=income_header_row, MATCH(income_min_row, $C:$C, 0), IF(header_row_id=expenses_header_row, MATCH(expenses_min_row, $C:$C, 0), IF(header_row_id=savings_header_row, MATCH(savings_min_row, $C:$C, 0), ""))), "")} | N18: {=IF(is_cat, IF(header_row_id=income_header_row, MATCH(income_max_row, $C:$C, 0), IF(header_row_id=expenses_header_row, MATCH(expenses_max_row, $C:$C, 0), IF(header_row_id=savings_header_row, MATCH(savings_max_row, $C:$C, 0), ""))), "")} | O18: =IF(is_cat, ADDRESS(sort_min_row, COLUMN(tracked)) & ":" & ADDRESS(sort_max_row, COLUMN(tracked)), "") | P18: =IF(is_cat, RANK(tracked, INDIRECT(tracked_range), 0), "") | Q18: =IF(is_cat, ADDRESS(sort_min_row, COLUMN(budget)) & ":" & ADDRESS(sort_max_row, COLUMN(budget)), "") | R18: =IF(is_cat, RANK(budget, INDIRECT(budget_range), 0), "") | S18: =IF(is_cat, _xlfn.NUMBERVALUE(tracked_rank & budget_rank), "") | T18: =IF(is_cat, ADDRESS(sort_min_row, COLUMN(comb_rank)) & ":" & ADDRESS(sort_max_row, COLUMN(comb_rank)), "") | U18: =IF(is_cat, RANK(comb_rank, INDIRECT(comb_rank_range), 1), "") | V18: =IF(is_cat, ADDRESS(sort_min_row, COLUMN(comb_rank_norm)) & ":" & ADDRESS(ROW(), COLUMN(comb_rank_norm)), "") | W18: =IF(is_cat, comb_rank_norm + COUNTIF(INDIRECT(comb_rank_norm_run_range), comb_rank_norm)-1, "") | X18: =IF(is_cat, header_row_id + comb_rank_unique, row_id) | Y18: =IF(is_empty, "", INDEX($J:$J, MATCH(row_id, $X:$X, 0))) | Z18: =IF(is_empty, "", IF(is_header, "Tracked", INDEX($K:$K, MATCH(row_id, $X:$X, 0)))) | AA18: =IF(is_empty, "", IF(is_header, "Budget", INDEX($L:$L, MATCH(row_id, $X:$X, 0)))) | AB18: =IF(is_empty, "", IF(is_header, "% Compl.", IFERROR(out_tracked / out_budget, "-"))) | AC18: =IF(is_empty, "", IF(is_header, "Remaining", IF(out_budget - out_tracked > 0, out_budget - out_tracked, 0))) | AD18: =IF(is_empty, "", IF(is_header, "Excess", IF(out_budget - out_tracked < 0, out_tracked - out_budget, 0))) | AI18: =Calculation!E37 | AJ18: =Calculation!F37
C19: {=IF(C18=-1,-1, IF(C18<income_max_row,C18+1, IF(C18=income_max_row,income_total_row, IF(C18=income_total_row,"/1", IF(C18="/1",expenses_header_row, IF(C18<expenses_max_row,C18+1, IF(C18=expenses_max_row,expenses_total_row, IF(C18=expenses_total_row, "/2", IF(C18="/2", savings_header_row, IF(C18<savings_max_row, C18+1, IF(C18=savings_max_row, savings_total_row, -1)))))))))))} | D19: =IF(is_header, row_id, IF(NOT(is_empty), D18, -1)) | E19: {=OR(row_id=income_header_row, row_id=expenses_header_row, row_id=savings_header_row) * 1} | F19: =1 * NOT(OR(is_header, is_total, is_empty)) | G19: {=OR(row_id=income_total_row, row_id=expenses_total_row, row_id=savings_total_row) * 1} | H19: =OR(row_id="/1", row_id="/2", row_id=-1)*1 | I19: {=IFERROR(INDEX('Budget Planning'!$C:$C, header_row_id), "")} | J19: {=IFERROR(INDEX('Budget Planning'!$C:$C, row_id), "")} | K19: {=IF(OR(is_header, is_empty), "", IF(is_total, IF(selected_period="Total Year", SUM(tracking[Amount] * (tracking[Type]=type) * (YEAR(tracking[Effective Date])=selected_year)), SUM(tracking[Amount] * (tracking[Type]=type) * (YEAR(tracking[Effective Date])=selected_year) * (MONTH(tracking[Effective Date])=selected_period))), IF(selected_period="Total Year", SUM(tracking[Amount] * (tracking[Type]=type) * (tracking[Category]=item) * (YEAR(tracking[Effective Date])=selected_year)), SUM(tracking[Amount] * (tracking[Type]=type) * (tracking[Category]=item) * (YEAR(tracking[Effective Date])=selected_year) * (MONTH(tracking[Effective Date])=selected_period)))))} | L19: {=IF(OR(is_header, is_empty), "", INDEX('Budget Planning'!$E:$EM, row_id, MATCH(IF(selected_period="Total Year", selected_year, DATE(selected_year, selected_period, 1)), 'Budget Planning'!$E$9:$EM$9, 0)))} | M19: {=IF(is_cat, IF(header_row_id=income_header_row, MATCH(income_min_row, $C:$C, 0), IF(header_row_id=expenses_header_row, MATCH(expenses_min_row, $C:$C, 0), IF(header_row_id=savings_header_row, MATCH(savings_min_row, $C:$C, 0), ""))), "")} | N19: {=IF(is_cat, IF(header_row_id=income_header_row, MATCH(income_max_row, $C:$C, 0), IF(header_row_id=expenses_header_row, MATCH(expenses_max_row, $C:$C, 0), IF(header_row_id=savings_header_row, MATCH(savings_max_row, $C:$C, 0), ""))), "")} | O19: =IF(is_cat, ADDRESS(sort_min_row, COLUMN(tracked)) & ":" & ADDRESS(sort_max_row, COLUMN(tracked)), "") | P19: =IF(is_cat, RANK(tracked, INDIRECT(tracked_range), 0), "") | Q19: =IF(is_cat, ADDRESS(sort_min_row, COLUMN(budget)) & ":" & ADDRESS(sort_max_row, COLUMN(budget)), "") | R19: =IF(is_cat, RANK(budget, INDIRECT(budget_range), 0), "") | S19: =IF(is_cat, _xlfn.NUMBERVALUE(tracked_rank & budget_rank), "") | T19: =IF(is_cat, ADDRESS(sort_min_row, COLUMN(comb_rank)) & ":" & ADDRESS(sort_max_row, COLUMN(comb_rank)), "") | U19: =IF(is_cat, RANK(comb_rank, INDIRECT(comb_rank_range), 1), "") | V19: =IF(is_cat, ADDRESS(sort_min_row, COLUMN(comb_rank_norm)) & ":" & ADDRESS(ROW(), COLUMN(comb_rank_norm)), "") | W19: =IF(is_cat, comb_rank_norm + COUNTIF(INDIRECT(comb_rank_norm_run_range), comb_rank_norm)-1, "") | X19: =IF(is_cat, header_row_id + comb_rank_unique, row_id) | Y19: =IF(is_empty, "", INDEX($J:$J, MATCH(row_id, $X:$X, 0))) | Z19: =IF(is_empty, "", IF(is_header, "Tracked", INDEX($K:$K, MATCH(row_id, $X:$X, 0)))) | AA19: =IF(is_empty, "", IF(is_header, "Budget", INDEX($L:$L, MATCH(row_id, $X:$X, 0)))) | AB19: =IF(is_empty, "", IF(is_header, "% Compl.", IFERROR(out_tracked / out_budget, "-"))) | AC19: =IF(is_empty, "", IF(is_header, "Remaining", IF(out_budget - out_tracked > 0, out_budget - out_tracked, 0))) | AD19: =IF(is_empty, "", IF(is_header, "Excess", IF(out_budget - out_tracked < 0, out_tracked - out_budget, 0))) | AI19: =Calculation!E38 | AJ19: =Calculation!F38
C20: {=IF(C19=-1,-1, IF(C19<income_max_row,C19+1, IF(C19=income_max_row,income_total_row, IF(C19=income_total_row,"/1", IF(C19="/1",expenses_header_row, IF(C19<expenses_max_row,C19+1, IF(C19=expenses_max_row,expenses_total_row, IF(C19=expenses_total_row, "/2", IF(C19="/2", savings_header_row, IF(C19<savings_max_row, C19+1, IF(C19=savings_max_row, savings_total_row, -1)))))))))))} | D20: =IF(is_header, row_id, IF(NOT(is_empty), D19, -1)) | E20: {=OR(row_id=income_header_row, row_id=expenses_header_row, row_id=savings_header_row) * 1} | F20: =1 * NOT(OR(is_header, is_total, is_empty)) | G20: {=OR(row_id=income_total_row, row_id=expenses_total_row, row_id=savings_total_row) * 1} | H20: =OR(row_id="/1", row_id="/2", row_id=-1)*1 | I20: {=IFERROR(INDEX('Budget Planning'!$C:$C, header_row_id), "")} | J20: {=IFERROR(INDEX('Budget Planning'!$C:$C, row_id), "")} | K20: {=IF(OR(is_header, is_empty), "", IF(is_total, IF(selected_period="Total Year", SUM(tracking[Amount] * (tracking[Type]=type) * (YEAR(tracking[Effective Date])=selected_year)), SUM(tracking[Amount] * (tracking[Type]=type) * (YEAR(tracking[Effective Date])=selected_year) * (MONTH(tracking[Effective Date])=selected_period))), IF(selected_period="Total Year", SUM(tracking[Amount] * (tracking[Type]=type) * (tracking[Category]=item) * (YEAR(tracking[Effective Date])=selected_year)), SUM(tracking[Amount] * (tracking[Type]=type) * (tracking[Category]=item) * (YEAR(tracking[Effective Date])=selected_year) * (MONTH(tracking[Effective Date])=selected_period)))))} | L20: {=IF(OR(is_header, is_empty), "", INDEX('Budget Planning'!$E:$EM, row_id, MATCH(IF(selected_period="Total Year", selected_year, DATE(selected_year, selected_period, 1)), 'Budget Planning'!$E$9:$EM$9, 0)))} | M20: {=IF(is_cat, IF(header_row_id=income_header_row, MATCH(income_min_row, $C:$C, 0), IF(header_row_id=expenses_header_row, MATCH(expenses_min_row, $C:$C, 0), IF(header_row_id=savings_header_row, MATCH(savings_min_row, $C:$C, 0), ""))), "")} | N20: {=IF(is_cat, IF(header_row_id=income_header_row, MATCH(income_max_row, $C:$C, 0), IF(header_row_id=expenses_header_row, MATCH(expenses_max_row, $C:$C, 0), IF(header_row_id=savings_header_row, MATCH(savings_max_row, $C:$C, 0), ""))), "")} | O20: =IF(is_cat, ADDRESS(sort_min_row, COLUMN(tracked)) & ":" & ADDRESS(sort_max_row, COLUMN(tracked)), "") | P20: =IF(is_cat, RANK(tracked, INDIRECT(tracked_range), 0), "") | Q20: =IF(is_cat, ADDRESS(sort_min_row, COLUMN(budget)) & ":" & ADDRESS(sort_max_row, COLUMN(budget)), "") | R20: =IF(is_cat, RANK(budget, INDIRECT(budget_range), 0), "") | S20: =IF(is_cat, _xlfn.NUMBERVALUE(tracked_rank & budget_rank), "") | T20: =IF(is_cat, ADDRESS(sort_min_row, COLUMN(comb_rank)) & ":" & ADDRESS(sort_max_row, COLUMN(comb_rank)), "") | U20: =IF(is_cat, RANK(comb_rank, INDIRECT(comb_rank_range), 1), "") | V20: =IF(is_cat, ADDRESS(sort_min_row, COLUMN(comb_rank_norm)) & ":" & ADDRESS(ROW(), COLUMN(comb_rank_norm)), "") | W20: =IF(is_cat, comb_rank_norm + COUNTIF(INDIRECT(comb_rank_norm_run_range), comb_rank_norm)-1, "") | X20: =IF(is_cat, header_row_id + comb_rank_unique, row_id) | Y20: =IF(is_empty, "", INDEX($J:$J, MATCH(row_id, $X:$X, 0))) | Z20: =IF(is_empty, "", IF(is_header, "Tracked", INDEX($K:$K, MATCH(row_id, $X:$X, 0)))) | AA20: =IF(is_empty, "", IF(is_header, "Budget", INDEX($L:$L, MATCH(row_id, $X:$X, 0)))) | AB20: =IF(is_empty, "", IF(is_header, "% Compl.", IFERROR(out_tracked / out_budget, "-"))) | AC20: =IF(is_empty, "", IF(is_header, "Remaining", IF(out_budget - out_tracked > 0, out_budget - out_tracked, 0))) | AD20: =IF(is_empty, "", IF(is_header, "Excess", IF(out_budget - out_tracked < 0, out_tracked - out_budget, 0))) | AI20: =Calculation!E39 | AJ20: =Calculation!F39
C21: {=IF(C20=-1,-1, IF(C20<income_max_row,C20+1, IF(C20=income_max_row,income_total_row, IF(C20=income_total_row,"/1", IF(C20="/1",expenses_header_row, IF(C20<expenses_max_row,C20+1, IF(C20=expenses_max_row,expenses_total_row, IF(C20=expenses_total_row, "/2", IF(C20="/2", savings_header_row, IF(C20<savings_max_row, C20+1, IF(C20=savings_max_row, savings_total_row, -1)))))))))))} | D21: =IF(is_header, row_id, IF(NOT(is_empty), D20, -1)) | E21: {=OR(row_id=income_header_row, row_id=expenses_header_row, row_id=savings_header_row) * 1} | F21: =1 * NOT(OR(is_header, is_total, is_empty)) | G21: {=OR(row_id=income_total_row, row_id=expenses_total_row, row_id=savings_total_row) * 1} | H21: =OR(row_id="/1", row_id="/2", row_id=-1)*1 | I21: {=IFERROR(INDEX('Budget Planning'!$C:$C, header_row_id), "")} | J21: {=IFERROR(INDEX('Budget Planning'!$C:$C, row_id), "")} | K21: {=IF(OR(is_header, is_empty), "", IF(is_total, IF(selected_period="Total Year", SUM(tracking[Amount] * (tracking[Type]=type) * (YEAR(tracking[Effective Date])=selected_year)), SUM(tracking[Amount] * (tracking[Type]=type) * (YEAR(tracking[Effective Date])=selected_year) * (MONTH(tracking[Effective Date])=selected_period))), IF(selected_period="Total Year", SUM(tracking[Amount] * (tracking[Type]=type) * (tracking[Category]=item) * (YEAR(tracking[Effective Date])=selected_year)), SUM(tracking[Amount] * (tracking[Type]=type) * (tracking[Category]=item) * (YEAR(tracking[Effective Date])=selected_year) * (MONTH(tracking[Effective Date])=selected_period)))))} | L21: {=IF(OR(is_header, is_empty), "", INDEX('Budget Planning'!$E:$EM, row_id, MATCH(IF(selected_period="Total Year", selected_year, DATE(selected_year, selected_period, 1)), 'Budget Planning'!$E$9:$EM$9, 0)))} | M21: {=IF(is_cat, IF(header_row_id=income_header_row, MATCH(income_min_row, $C:$C, 0), IF(header_row_id=expenses_header_row, MATCH(expenses_min_row, $C:$C, 0), IF(header_row_id=savings_header_row, MATCH(savings_min_row, $C:$C, 0), ""))), "")} | N21: {=IF(is_cat, IF(header_row_id=income_header_row, MATCH(income_max_row, $C:$C, 0), IF(header_row_id=expenses_header_row, MATCH(expenses_max_row, $C:$C, 0), IF(header_row_id=savings_header_row, MATCH(savings_max_row, $C:$C, 0), ""))), "")} | O21: =IF(is_cat, ADDRESS(sort_min_row, COLUMN(tracked)) & ":" & ADDRESS(sort_max_row, COLUMN(tracked)), "") | P21: =IF(is_cat, RANK(tracked, INDIRECT(tracked_range), 0), "") | Q21: =IF(is_cat, ADDRESS(sort_min_row, COLUMN(budget)) & ":" & ADDRESS(sort_max_row, COLUMN(budget)), "") | R21: =IF(is_cat, RANK(budget, INDIRECT(budget_range), 0), "") | S21: =IF(is_cat, _xlfn.NUMBERVALUE(tracked_rank & budget_rank), "") | T21: =IF(is_cat, ADDRESS(sort_min_row, COLUMN(comb_rank)) & ":" & ADDRESS(sort_max_row, COLUMN(comb_rank)), "") | U21: =IF(is_cat, RANK(comb_rank, INDIRECT(comb_rank_range), 1), "") | V21: =IF(is_cat, ADDRESS(sort_min_row, COLUMN(comb_rank_norm)) & ":" & ADDRESS(ROW(), COLUMN(comb_rank_norm)), "") | W21: =IF(is_cat, comb_rank_norm + COUNTIF(INDIRECT(comb_rank_norm_run_range), comb_rank_norm)-1, "") | X21: =IF(is_cat, header_row_id + comb_rank_unique, row_id) | Y21: =IF(is_empty, "", INDEX($J:$J, MATCH(row_id, $X:$X, 0))) | Z21: =IF(is_empty, "", IF(is_header, "Tracked", INDEX($K:$K, MATCH(row_id, $X:$X, 0)))) | AA21: =IF(is_empty, "", IF(is_header, "Budget", INDEX($L:$L, MATCH(row_id, $X:$X, 0)))) | AB21: =IF(is_empty, "", IF(is_header, "% Compl.", IFERROR(out_tracked / out_budget, "-"))) | AC21: =IF(is_empty, "", IF(is_header, "Remaining", IF(out_budget - out_tracked > 0, out_budget - out_tracked, 0))) | AD21: =IF(is_empty, "", IF(is_header, "Excess", IF(out_budget - out_tracked < 0, out_tracked - out_budget, 0))) | AI21: =Calculation!E40 | AJ21: =Calculation!F40
C22: {=IF(C21=-1,-1, IF(C21<income_max_row,C21+1, IF(C21=income_max_row,income_total_row, IF(C21=income_total_row,"/1", IF(C21="/1",expenses_header_row, IF(C21<expenses_max_row,C21+1, IF(C21=expenses_max_row,expenses_total_row, IF(C21=expenses_total_row, "/2", IF(C21="/2", savings_header_row, IF(C21<savings_max_row, C21+1, IF(C21=savings_max_row, savings_total_row, -1)))))))))))} | D22: =IF(is_header, row_id, IF(NOT(is_empty), D21, -1)) | E22: {=OR(row_id=income_header_row, row_id=expenses_header_row, row_id=savings_header_row) * 1} | F22: =1 * NOT(OR(is_header, is_total, is_empty)) | G22: {=OR(row_id=income_total_row, row_id=expenses_total_row, row_id=savings_total_row) * 1} | H22: =OR(row_id="/1", row_id="/2", row_id=-1)*1 | I22: {=IFERROR(INDEX('Budget Planning'!$C:$C, header_row_id), "")} | J22: {=IFERROR(INDEX('Budget Planning'!$C:$C, row_id), "")} | K22: {=IF(OR(is_header, is_empty), "", IF(is_total, IF(selected_period="Total Year", SUM(tracking[Amount] * (tracking[Type]=type) * (YEAR(tracking[Effective Date])=selected_year)), SUM(tracking[Amount] * (tracking[Type]=type) * (YEAR(tracking[Effective Date])=selected_year) * (MONTH(tracking[Effective Date])=selected_period))), IF(selected_period="Total Year", SUM(tracking[Amount] * (tracking[Type]=type) * (tracking[Category]=item) * (YEAR(tracking[Effective Date])=selected_year)), SUM(tracking[Amount] * (tracking[Type]=type) * (tracking[Category]=item) * (YEAR(tracking[Effective Date])=selected_year) * (MONTH(tracking[Effective Date])=selected_period)))))} | L22: {=IF(OR(is_header, is_empty), "", INDEX('Budget Planning'!$E:$EM, row_id, MATCH(IF(selected_period="Total Year", selected_year, DATE(selected_year, selected_period, 1)), 'Budget Planning'!$E$9:$EM$9, 0)))} | M22: {=IF(is_cat, IF(header_row_id=income_header_row, MATCH(income_min_row, $C:$C, 0), IF(header_row_id=expenses_header_row, MATCH(expenses_min_row, $C:$C, 0), IF(header_row_id=savings_header_row, MATCH(savings_min_row, $C:$C, 0), ""))), "")} | N22: {=IF(is_cat, IF(header_row_id=income_header_row, MATCH(income_max_row, $C:$C, 0), IF(header_row_id=expenses_header_row, MATCH(expenses_max_row, $C:$C, 0), IF(header_row_id=savings_header_row, MATCH(savings_max_row, $C:$C, 0), ""))), "")} | O22: =IF(is_cat, ADDRESS(sort_min_row, COLUMN(tracked)) & ":" & ADDRESS(sort_max_row, COLUMN(tracked)), "") | P22: =IF(is_cat, RANK(tracked, INDIRECT(tracked_range), 0), "") | Q22: =IF(is_cat, ADDRESS(sort_min_row, COLUMN(budget)) & ":" & ADDRESS(sort_max_row, COLUMN(budget)), "") | R22: =IF(is_cat, RANK(budget, INDIRECT(budget_range), 0), "") | S22: =IF(is_cat, _xlfn.NUMBERVALUE(tracked_rank & budget_rank), "") | T22: =IF(is_cat, ADDRESS(sort_min_row, COLUMN(comb_rank)) & ":" & ADDRESS(sort_max_row, COLUMN(comb_rank)), "") | U22: =IF(is_cat, RANK(comb_rank, INDIRECT(comb_rank_range), 1), "") | V22: =IF(is_cat, ADDRESS(sort_min_row, COLUMN(comb_rank_norm)) & ":" & ADDRESS(ROW(), COLUMN(comb_rank_norm)), "") | W22: =IF(is_cat, comb_rank_norm + COUNTIF(INDIRECT(comb_rank_norm_run_range), comb_rank_norm)-1, "") | X22: =IF(is_cat, header_row_id + comb_rank_unique, row_id) | Y22: =IF(is_empty, "", INDEX($J:$J, MATCH(row_id, $X:$X, 0))) | Z22: =IF(is_empty, "", IF(is_header, "Tracked", INDEX($K:$K, MATCH(row_id, $X:$X, 0)))) | AA22: =IF(is_empty, "", IF(is_header, "Budget", INDEX($L:$L, MATCH(row_id, $X:$X, 0)))) | AB22: =IF(is_empty, "", IF(is_header, "% Compl.", IFERROR(out_tracked / out_budget, "-"))) | AC22: =IF(is_empty, "", IF(is_header, "Remaining", IF(out_budget - out_tracked > 0, out_budget - out_tracked, 0))) | AD22: =IF(is_empty, "", IF(is_header, "Excess", IF(out_budget - out_tracked < 0, out_tracked - out_budget, 0))) | AI22: =Calculation!E41 | AJ22: =Calculation!F41
C23: {=IF(C22=-1,-1, IF(C22<income_max_row,C22+1, IF(C22=income_max_row,income_total_row, IF(C22=income_total_row,"/1", IF(C22="/1",expenses_header_row, IF(C22<expenses_max_row,C22+1, IF(C22=expenses_max_row,expenses_total_row, IF(C22=expenses_total_row, "/2", IF(C22="/2", savings_header_row, IF(C22<savings_max_row, C22+1, IF(C22=savings_max_row, savings_total_row, -1)))))))))))} | D23: =IF(is_header, row_id, IF(NOT(is_empty), D22, -1)) | E23: {=OR(row_id=income_header_row, row_id=expenses_header_row, row_id=savings_header_row) * 1} | F23: =1 * NOT(OR(is_header, is_total, is_empty)) | G23: {=OR(row_id=income_total_row, row_id=expenses_total_row, row_id=savings_total_row) * 1} | H23: =OR(row_id="/1", row_id="/2", row_id=-1)*1 | I23: {=IFERROR(INDEX('Budget Planning'!$C:$C, header_row_id), "")} | J23: {=IFERROR(INDEX('Budget Planning'!$C:$C, row_id), "")} | K23: {=IF(OR(is_header, is_empty), "", IF(is_total, IF(selected_period="Total Year", SUM(tracking[Amount] * (tracking[Type]=type) * (YEAR(tracking[Effective Date])=selected_year)), SUM(tracking[Amount] * (tracking[Type]=type) * (YEAR(tracking[Effective Date])=selected_year) * (MONTH(tracking[Effective Date])=selected_period))), IF(selected_period="Total Year", SUM(tracking[Amount] * (tracking[Type]=type) * (tracking[Category]=item) * (YEAR(tracking[Effective Date])=selected_year)), SUM(tracking[Amount] * (tracking[Type]=type) * (tracking[Category]=item) * (YEAR(tracking[Effective Date])=selected_year) * (MONTH(tracking[Effective Date])=selected_period)))))} | L23: {=IF(OR(is_header, is_empty), "", INDEX('Budget Planning'!$E:$EM, row_id, MATCH(IF(selected_period="Total Year", selected_year, DATE(selected_year, selected_period, 1)), 'Budget Planning'!$E$9:$EM$9, 0)))} | M23: {=IF(is_cat, IF(header_row_id=income_header_row, MATCH(income_min_row, $C:$C, 0), IF(header_row_id=expenses_header_row, MATCH(expenses_min_row, $C:$C, 0), IF(header_row_id=savings_header_row, MATCH(savings_min_row, $C:$C, 0), ""))), "")} | N23: {=IF(is_cat, IF(header_row_id=income_header_row, MATCH(income_max_row, $C:$C, 0), IF(header_row_id=expenses_header_row, MATCH(expenses_max_row, $C:$C, 0), IF(header_row_id=savings_header_row, MATCH(savings_max_row, $C:$C, 0), ""))), "")} | O23: =IF(is_cat, ADDRESS(sort_min_row, COLUMN(tracked)) & ":" & ADDRESS(sort_max_row, COLUMN(tracked)), "") | P23: =IF(is_cat, RANK(tracked, INDIRECT(tracked_range), 0), "") | Q23: =IF(is_cat, ADDRESS(sort_min_row, COLUMN(budget)) & ":" & ADDRESS(sort_max_row, COLUMN(budget)), "") | R23: =IF(is_cat, RANK(budget, INDIRECT(budget_range), 0), "") | S23: =IF(is_cat, _xlfn.NUMBERVALUE(tracked_rank & budget_rank), "") | T23: =IF(is_cat, ADDRESS(sort_min_row, COLUMN(comb_rank)) & ":" & ADDRESS(sort_max_row, COLUMN(comb_rank)), "") | U23: =IF(is_cat, RANK(comb_rank, INDIRECT(comb_rank_range), 1), "") | V23: =IF(is_cat, ADDRESS(sort_min_row, COLUMN(comb_rank_norm)) & ":" & ADDRESS(ROW(), COLUMN(comb_rank_norm)), "") | W23: =IF(is_cat, comb_rank_norm + COUNTIF(INDIRECT(comb_rank_norm_run_range), comb_rank_norm)-1, "") | X23: =IF(is_cat, header_row_id + comb_rank_unique, row_id) | Y23: =IF(is_empty, "", INDEX($J:$J, MATCH(row_id, $X:$X, 0))) | Z23: =IF(is_empty, "", IF(is_header, "Tracked", INDEX($K:$K, MATCH(row_id, $X:$X, 0)))) | AA23: =IF(is_empty, "", IF(is_header, "Budget", INDEX($L:$L, MATCH(row_id, $X:$X, 0)))) | AB23: =IF(is_empty, "", IF(is_header, "% Compl.", IFERROR(out_tracked / out_budget, "-"))) | AC23: =IF(is_empty, "", IF(is_header, "Remaining", IF(out_budget - out_tracked > 0, out_budget - out_tracked, 0))) | AD23: =IF(is_empty, "", IF(is_header, "Excess", IF(out_budget - out_tracked < 0, out_tracked - out_budget, 0)))
C24: {=IF(C23=-1,-1, IF(C23<income_max_row,C23+1, IF(C23=income_max_row,income_total_row, IF(C23=income_total_row,"/1", IF(C23="/1",expenses_header_row, IF(C23<expenses_max_row,C23+1, IF(C23=expenses_max_row,expenses_total_row, IF(C23=expenses_total_row, "/2", IF(C23="/2", savings_header_row, IF(C23<savings_max_row, C23+1, IF(C23=savings_max_row, savings_total_row, -1)))))))))))} | D24: =IF(is_header, row_id, IF(NOT(is_empty), D23, -1)) | E24: {=OR(row_id=income_header_row, row_id=expenses_header_row, row_id=savings_header_row) * 1} | F24: =1 * NOT(OR(is_header, is_total, is_empty)) | G24: {=OR(row_id=income_total_row, row_id=expenses_total_row, row_id=savings_total_row) * 1} | H24: =OR(row_id="/1", row_id="/2", row_id=-1)*1 | I24: {=IFERROR(INDEX('Budget Planning'!$C:$C, header_row_id), "")} | J24: {=IFERROR(INDEX('Budget Planning'!$C:$C, row_id), "")} | K24: {=IF(OR(is_header, is_empty), "", IF(is_total, IF(selected_period="Total Year", SUM(tracking[Amount] * (tracking[Type]=type) * (YEAR(tracking[Effective Date])=selected_year)), SUM(tracking[Amount] * (tracking[Type]=type) * (YEAR(tracking[Effective Date])=selected_year) * (MONTH(tracking[Effective Date])=selected_period))), IF(selected_period="Total Year", SUM(tracking[Amount] * (tracking[Type]=type) * (tracking[Category]=item) * (YEAR(tracking[Effective Date])=selected_year)), SUM(tracking[Amount] * (tracking[Type]=type) * (tracking[Category]=item) * (YEAR(tracking[Effective Date])=selected_year) * (MONTH(tracking[Effective Date])=selected_period)))))} | L24: {=IF(OR(is_header, is_empty), "", INDEX('Budget Planning'!$E:$EM, row_id, MATCH(IF(selected_period="Total Year", selected_year, DATE(selected_year, selected_period, 1)), 'Budget Planning'!$E$9:$EM$9, 0)))} | M24: {=IF(is_cat, IF(header_row_id=income_header_row, MATCH(income_min_row, $C:$C, 0), IF(header_row_id=expenses_header_row, MATCH(expenses_min_row, $C:$C, 0), IF(header_row_id=savings_header_row, MATCH(savings_min_row, $C:$C, 0), ""))), "")} | N24: {=IF(is_cat, IF(header_row_id=income_header_row, MATCH(income_max_row, $C:$C, 0), IF(header_row_id=expenses_header_row, MATCH(expenses_max_row, $C:$C, 0), IF(header_row_id=savings_header_row, MATCH(savings_max_row, $C:$C, 0), ""))), "")} | O24: =IF(is_cat, ADDRESS(sort_min_row, COLUMN(tracked)) & ":" & ADDRESS(sort_max_row, COLUMN(tracked)), "") | P24: =IF(is_cat, RANK(tracked, INDIRECT(tracked_range), 0), "") | Q24: =IF(is_cat, ADDRESS(sort_min_row, COLUMN(budget)) & ":" & ADDRESS(sort_max_row, COLUMN(budget)), "") | R24: =IF(is_cat, RANK(budget, INDIRECT(budget_range), 0), "") | S24: =IF(is_cat, _xlfn.NUMBERVALUE(tracked_rank & budget_rank), "") | T24: =IF(is_cat, ADDRESS(sort_min_row, COLUMN(comb_rank)) & ":" & ADDRESS(sort_max_row, COLUMN(comb_rank)), "") | U24: =IF(is_cat, RANK(comb_rank, INDIRECT(comb_rank_range), 1), "") | V24: =IF(is_cat, ADDRESS(sort_min_row, COLUMN(comb_rank_norm)) & ":" & ADDRESS(ROW(), COLUMN(comb_rank_norm)), "") | W24: =IF(is_cat, comb_rank_norm + COUNTIF(INDIRECT(comb_rank_norm_run_range), comb_rank_norm)-1, "") | X24: =IF(is_cat, header_row_id + comb_rank_unique, row_id) | Y24: =IF(is_empty, "", INDEX($J:$J, MATCH(row_id, $X:$X, 0))) | Z24: =IF(is_empty, "", IF(is_header, "Tracked", INDEX($K:$K, MATCH(row_id, $X:$X, 0)))) | AA24: =IF(is_empty, "", IF(is_header, "Budget", INDEX($L:$L, MATCH(row_id, $X:$X, 0)))) | AB24: =IF(is_empty, "", IF(is_header, "% Compl.", IFERROR(out_tracked / out_budget, "-"))) | AC24: =IF(is_empty, "", IF(is_header, "Remaining", IF(out_budget - out_tracked > 0, out_budget - out_tracked, 0))) | AD24: =IF(is_empty, "", IF(is_header, "Excess", IF(out_budget - out_tracked < 0, out_tracked - out_budget, 0)))
C25: {=IF(C24=-1,-1, IF(C24<income_max_row,C24+1, IF(C24=income_max_row,income_total_row, IF(C24=income_total_row,"/1", IF(C24="/1",expenses_header_row, IF(C24<expenses_max_row,C24+1, IF(C24=expenses_max_row,expenses_total_row, IF(C24=expenses_total_row, "/2", IF(C24="/2", savings_header_row, IF(C24<savings_max_row, C24+1, IF(C24=savings_max_row, savings_total_row, -1)))))))))))} | D25: =IF(is_header, row_id, IF(NOT(is_empty), D24, -1)) | E25: {=OR(row_id=income_header_row, row_id=expenses_header_row, row_id=savings_header_row) * 1} | F25: =1 * NOT(OR(is_header, is_total, is_empty)) | G25: {=OR(row_id=income_total_row, row_id=expenses_total_row, row_id=savings_total_row) * 1} | H25: =OR(row_id="/1", row_id="/2", row_id=-1)*1 | I25: {=IFERROR(INDEX('Budget Planning'!$C:$C, header_row_id), "")} | J25: {=IFERROR(INDEX('Budget Planning'!$C:$C, row_id), "")} | K25: {=IF(OR(is_header, is_empty), "", IF(is_total, IF(selected_period="Total Year", SUM(tracking[Amount] * (tracking[Type]=type) * (YEAR(tracking[Effective Date])=selected_year)), SUM(tracking[Amount] * (tracking[Type]=type) * (YEAR(tracking[Effective Date])=selected_year) * (MONTH(tracking[Effective Date])=selected_period))), IF(selected_period="Total Year", SUM(tracking[Amount] * (tracking[Type]=type) * (tracking[Category]=item) * (YEAR(tracking[Effective Date])=selected_year)), SUM(tracking[Amount] * (tracking[Type]=type) * (tracking[Category]=item) * (YEAR(tracking[Effective Date])=selected_year) * (MONTH(tracking[Effective Date])=selected_period)))))} | L25: {=IF(OR(is_header, is_empty), "", INDEX('Budget Planning'!$E:$EM, row_id, MATCH(IF(selected_period="Total Year", selected_year, DATE(selected_year, selected_period, 1)), 'Budget Planning'!$E$9:$EM$9, 0)))} | M25: {=IF(is_cat, IF(header_row_id=income_header_row, MATCH(income_min_row, $C:$C, 0), IF(header_row_id=expenses_header_row, MATCH(expenses_min_row, $C:$C, 0), IF(header_row_id=savings_header_row, MATCH(savings_min_row, $C:$C, 0), ""))), "")} | N25: {=IF(is_cat, IF(header_row_id=income_header_row, MATCH(income_max_row, $C:$C, 0), IF(header_row_id=expenses_header_row, MATCH(expenses_max_row, $C:$C, 0), IF(header_row_id=savings_header_row, MATCH(savings_max_row, $C:$C, 0), ""))), "")} | O25: =IF(is_cat, ADDRESS(sort_min_row, COLUMN(tracked)) & ":" & ADDRESS(sort_max_row, COLUMN(tracked)), "") | P25: =IF(is_cat, RANK(tracked, INDIRECT(tracked_range), 0), "") | Q25: =IF(is_cat, ADDRESS(sort_min_row, COLUMN(budget)) & ":" & ADDRESS(sort_max_row, COLUMN(budget)), "") | R25: =IF(is_cat, RANK(budget, INDIRECT(budget_range), 0), "") | S25: =IF(is_cat, _xlfn.NUMBERVALUE(tracked_rank & budget_rank), "") | T25: =IF(is_cat, ADDRESS(sort_min_row, COLUMN(comb_rank)) & ":" & ADDRESS(sort_max_row, COLUMN(comb_rank)), "") | U25: =IF(is_cat, RANK(comb_rank, INDIRECT(comb_rank_range), 1), "") | V25: =IF(is_cat, ADDRESS(sort_min_row, COLUMN(comb_rank_norm)) & ":" & ADDRESS(ROW(), COLUMN(comb_rank_norm)), "") | W25: =IF(is_cat, comb_rank_norm + COUNTIF(INDIRECT(comb_rank_norm_run_range), comb_rank_norm)-1, "") | X25: =IF(is_cat, header_row_id + comb_rank_unique, row_id) | Y25: =IF(is_empty, "", INDEX($J:$J, MATCH(row_id, $X:$X, 0))) | Z25: =IF(is_empty, "", IF(is_header, "Tracked", INDEX($K:$K, MATCH(row_id, $X:$X, 0)))) | AA25: =IF(is_empty, "", IF(is_header, "Budget", INDEX($L:$L, MATCH(row_id, $X:$X, 0)))) | AB25: =IF(is_empty, "", IF(is_header, "% Compl.", IFERROR(out_tracked / out_budget, "-"))) | AC25: =IF(is_empty, "", IF(is_header, "Remaining", IF(out_budget - out_tracked > 0, out_budget - out_tracked, 0))) | AD25: =IF(is_empty, "", IF(is_header, "Excess", IF(out_budget - out_tracked < 0, out_tracked - out_budget, 0)))
C26: {=IF(C25=-1,-1, IF(C25<income_max_row,C25+1, IF(C25=income_max_row,income_total_row, IF(C25=income_total_row,"/1", IF(C25="/1",expenses_header_row, IF(C25<expenses_max_row,C25+1, IF(C25=expenses_max_row,expenses_total_row, IF(C25=expenses_total_row, "/2", IF(C25="/2", savings_header_row, IF(C25<savings_max_row, C25+1, IF(C25=savings_max_row, savings_total_row, -1)))))))))))} | D26: =IF(is_header, row_id, IF(NOT(is_empty), D25, -1)) | E26: {=OR(row_id=income_header_row, row_id=expenses_header_row, row_id=savings_header_row) * 1} | F26: =1 * NOT(OR(is_header, is_total, is_empty)) | G26: {=OR(row_id=income_total_row, row_id=expenses_total_row, row_id=savings_total_row) * 1} | H26: =OR(row_id="/1", row_id="/2", row_id=-1)*1 | I26: {=IFERROR(INDEX('Budget Planning'!$C:$C, header_row_id), "")} | J26: {=IFERROR(INDEX('Budget Planning'!$C:$C, row_id), "")} | K26: {=IF(OR(is_header, is_empty), "", IF(is_total, IF(selected_period="Total Year", SUM(tracking[Amount] * (tracking[Type]=type) * (YEAR(tracking[Effective Date])=selected_year)), SUM(tracking[Amount] * (tracking[Type]=type) * (YEAR(tracking[Effective Date])=selected_year) * (MONTH(tracking[Effective Date])=selected_period))), IF(selected_period="Total Year", SUM(tracking[Amount] * (tracking[Type]=type) * (tracking[Category]=item) * (YEAR(tracking[Effective Date])=selected_year)), SUM(tracking[Amount] * (tracking[Type]=type) * (tracking[Category]=item) * (YEAR(tracking[Effective Date])=selected_year) * (MONTH(tracking[Effective Date])=selected_period)))))} | L26: {=IF(OR(is_header, is_empty), "", INDEX('Budget Planning'!$E:$EM, row_id, MATCH(IF(selected_period="Total Year", selected_year, DATE(selected_year, selected_period, 1)), 'Budget Planning'!$E$9:$EM$9, 0)))} | M26: {=IF(is_cat, IF(header_row_id=income_header_row, MATCH(income_min_row, $C:$C, 0), IF(header_row_id=expenses_header_row, MATCH(expenses_min_row, $C:$C, 0), IF(header_row_id=savings_header_row, MATCH(savings_min_row, $C:$C, 0), ""))), "")} | N26: {=IF(is_cat, IF(header_row_id=income_header_row, MATCH(income_max_row, $C:$C, 0), IF(header_row_id=expenses_header_row, MATCH(expenses_max_row, $C:$C, 0), IF(header_row_id=savings_header_row, MATCH(savings_max_row, $C:$C, 0), ""))), "")} | O26: =IF(is_cat, ADDRESS(sort_min_row, COLUMN(tracked)) & ":" & ADDRESS(sort_max_row, COLUMN(tracked)), "") | P26: =IF(is_cat, RANK(tracked, INDIRECT(tracked_range), 0), "") | Q26: =IF(is_cat, ADDRESS(sort_min_row, COLUMN(budget)) & ":" & ADDRESS(sort_max_row, COLUMN(budget)), "") | R26: =IF(is_cat, RANK(budget, INDIRECT(budget_range), 0), "") | S26: =IF(is_cat, _xlfn.NUMBERVALUE(tracked_rank & budget_rank), "") | T26: =IF(is_cat, ADDRESS(sort_min_row, COLUMN(comb_rank)) & ":" & ADDRESS(sort_max_row, COLUMN(comb_rank)), "") | U26: =IF(is_cat, RANK(comb_rank, INDIRECT(comb_rank_range), 1), "") | V26: =IF(is_cat, ADDRESS(sort_min_row, COLUMN(comb_rank_norm)) & ":" & ADDRESS(ROW(), COLUMN(comb_rank_norm)), "") | W26: =IF(is_cat, comb_rank_norm + COUNTIF(INDIRECT(comb_rank_norm_run_range), comb_rank_norm)-1, "") | X26: =IF(is_cat, header_row_id + comb_rank_unique, row_id) | Y26: =IF(is_empty, "", INDEX($J:$J, MATCH(row_id, $X:$X, 0))) | Z26: =IF(is_empty, "", IF(is_header, "Tracked", INDEX($K:$K, MATCH(row_id, $X:$X, 0)))) | AA26: =IF(is_empty, "", IF(is_header, "Budget", INDEX($L:$L, MATCH(row_id, $X:$X, 0)))) | AB26: =IF(is_empty, "", IF(is_header, "% Compl.", IFERROR(out_tracked / out_budget, "-"))) | AC26: =IF(is_empty, "", IF(is_header, "Remaining", IF(out_budget - out_tracked > 0, out_budget - out_tracked, 0))) | AD26: =IF(is_empty, "", IF(is_header, "Excess", IF(out_budget - out_tracked < 0, out_tracked - out_budget, 0)))
C27: {=IF(C26=-1,-1, IF(C26<income_max_row,C26+1, IF(C26=income_max_row,income_total_row, IF(C26=income_total_row,"/1", IF(C26="/1",expenses_header_row, IF(C26<expenses_max_row,C26+1, IF(C26=expenses_max_row,expenses_total_row, IF(C26=expenses_total_row, "/2", IF(C26="/2", savings_header_row, IF(C26<savings_max_row, C26+1, IF(C26=savings_max_row, savings_total_row, -1)))))))))))} | D27: =IF(is_header, row_id, IF(NOT(is_empty), D26, -1)) | E27: {=OR(row_id=income_header_row, row_id=expenses_header_row, row_id=savings_header_row) * 1} | F27: =1 * NOT(OR(is_header, is_total, is_empty)) | G27: {=OR(row_id=income_total_row, row_id=expenses_total_row, row_id=savings_total_row) * 1} | H27: =OR(row_id="/1", row_id="/2", row_id=-1)*1 | I27: {=IFERROR(INDEX('Budget Planning'!$C:$C, header_row_id), "")} | J27: {=IFERROR(INDEX('Budget Planning'!$C:$C, row_id), "")} | K27: {=IF(OR(is_header, is_empty), "", IF(is_total, IF(selected_period="Total Year", SUM(tracking[Amount] * (tracking[Type]=type) * (YEAR(tracking[Effective Date])=selected_year)), SUM(tracking[Amount] * (tracking[Type]=type) * (YEAR(tracking[Effective Date])=selected_year) * (MONTH(tracking[Effective Date])=selected_period))), IF(selected_period="Total Year", SUM(tracking[Amount] * (tracking[Type]=type) * (tracking[Category]=item) * (YEAR(tracking[Effective Date])=selected_year)), SUM(tracking[Amount] * (tracking[Type]=type) * (tracking[Category]=item) * (YEAR(tracking[Effective Date])=selected_year) * (MONTH(tracking[Effective Date])=selected_period)))))} | L27: {=IF(OR(is_header, is_empty), "", INDEX('Budget Planning'!$E:$EM, row_id, MATCH(IF(selected_period="Total Year", selected_year, DATE(selected_year, selected_period, 1)), 'Budget Planning'!$E$9:$EM$9, 0)))} | M27: {=IF(is_cat, IF(header_row_id=income_header_row, MATCH(income_min_row, $C:$C, 0), IF(header_row_id=expenses_header_row, MATCH(expenses_min_row, $C:$C, 0), IF(header_row_id=savings_header_row, MATCH(savings_min_row, $C:$C, 0), ""))), "")} | N27: {=IF(is_cat, IF(header_row_id=income_header_row, MATCH(income_max_row, $C:$C, 0), IF(header_row_id=expenses_header_row, MATCH(expenses_max_row, $C:$C, 0), IF(header_row_id=savings_header_row, MATCH(savings_max_row, $C:$C, 0), ""))), "")} | O27: =IF(is_cat, ADDRESS(sort_min_row, COLUMN(tracked)) & ":" & ADDRESS(sort_max_row, COLUMN(tracked)), "") | P27: =IF(is_cat, RANK(tracked, INDIRECT(tracked_range), 0), "") | Q27: =IF(is_cat, ADDRESS(sort_min_row, COLUMN(budget)) & ":" & ADDRESS(sort_max_row, COLUMN(budget)), "") | R27: =IF(is_cat, RANK(budget, INDIRECT(budget_range), 0), "") | S27: =IF(is_cat, _xlfn.NUMBERVALUE(tracked_rank & budget_rank), "") | T27: =IF(is_cat, ADDRESS(sort_min_row, COLUMN(comb_rank)) & ":" & ADDRESS(sort_max_row, COLUMN(comb_rank)), "") | U27: =IF(is_cat, RANK(comb_rank, INDIRECT(comb_rank_range), 1), "") | V27: =IF(is_cat, ADDRESS(sort_min_row, COLUMN(comb_rank_norm)) & ":" & ADDRESS(ROW(), COLUMN(comb_rank_norm)), "") | W27: =IF(is_cat, comb_rank_norm + COUNTIF(INDIRECT(comb_rank_norm_run_range), comb_rank_norm)-1, "") | X27: =IF(is_cat, header_row_id + comb_rank_unique, row_id) | Y27: =IF(is_empty, "", INDEX($J:$J, MATCH(row_id, $X:$X, 0))) | Z27: =IF(is_empty, "", IF(is_header, "Tracked", INDEX($K:$K, MATCH(row_id, $X:$X, 0)))) | AA27: =IF(is_empty, "", IF(is_header, "Budget", INDEX($L:$L, MATCH(row_id, $X:$X, 0)))) | AB27: =IF(is_empty, "", IF(is_header, "% Compl.", IFERROR(out_tracked / out_budget, "-"))) | AC27: =IF(is_empty, "", IF(is_header, "Remaining", IF(out_budget - out_tracked > 0, out_budget - out_tracked, 0))) | AD27: =IF(is_empty, "", IF(is_header, "Excess", IF(out_budget - out_tracked < 0, out_tracked - out_budget, 0)))
C28: {=IF(C27=-1,-1, IF(C27<income_max_row,C27+1, IF(C27=income_max_row,income_total_row, IF(C27=income_total_row,"/1", IF(C27="/1",expenses_header_row, IF(C27<expenses_max_row,C27+1, IF(C27=expenses_max_row,expenses_total_row, IF(C27=expenses_total_row, "/2", IF(C27="/2", savings_header_row, IF(C27<savings_max_row, C27+1, IF(C27=savings_max_row, savings_total_row, -1)))))))))))} | D28: =IF(is_header, row_id, IF(NOT(is_empty), D27, -1)) | E28: {=OR(row_id=income_header_row, row_id=expenses_header_row, row_id=savings_header_row) * 1} | F28: =1 * NOT(OR(is_header, is_total, is_empty)) | G28: {=OR(row_id=income_total_row, row_id=expenses_total_row, row_id=savings_total_row) * 1} | H28: =OR(row_id="/1", row_id="/2", row_id=-1)*1 | I28: {=IFERROR(INDEX('Budget Planning'!$C:$C, header_row_id), "")} | J28: {=IFERROR(INDEX('Budget Planning'!$C:$C, row_id), "")} | K28: {=IF(OR(is_header, is_empty), "", IF(is_total, IF(selected_period="Total Year", SUM(tracking[Amount] * (tracking[Type]=type) * (YEAR(tracking[Effective Date])=selected_year)), SUM(tracking[Amount] * (tracking[Type]=type) * (YEAR(tracking[Effective Date])=selected_year) * (MONTH(tracking[Effective Date])=selected_period))), IF(selected_period="Total Year", SUM(tracking[Amount] * (tracking[Type]=type) * (tracking[Category]=item) * (YEAR(tracking[Effective Date])=selected_year)), SUM(tracking[Amount] * (tracking[Type]=type) * (tracking[Category]=item) * (YEAR(tracking[Effective Date])=selected_year) * (MONTH(tracking[Effective Date])=selected_period)))))} | L28: {=IF(OR(is_header, is_empty), "", INDEX('Budget Planning'!$E:$EM, row_id, MATCH(IF(selected_period="Total Year", selected_year, DATE(selected_year, selected_period, 1)), 'Budget Planning'!$E$9:$EM$9, 0)))} | M28: {=IF(is_cat, IF(header_row_id=income_header_row, MATCH(income_min_row, $C:$C, 0), IF(header_row_id=expenses_header_row, MATCH(expenses_min_row, $C:$C, 0), IF(header_row_id=savings_header_row, MATCH(savings_min_row, $C:$C, 0), ""))), "")} | N28: {=IF(is_cat, IF(header_row_id=income_header_row, MATCH(income_max_row, $C:$C, 0), IF(header_row_id=expenses_header_row, MATCH(expenses_max_row, $C:$C, 0), IF(header_row_id=savings_header_row, MATCH(savings_max_row, $C:$C, 0), ""))), "")} | O28: =IF(is_cat, ADDRESS(sort_min_row, COLUMN(tracked)) & ":" & ADDRESS(sort_max_row, COLUMN(tracked)), "") | P28: =IF(is_cat, RANK(tracked, INDIRECT(tracked_range), 0), "") | Q28: =IF(is_cat, ADDRESS(sort_min_row, COLUMN(budget)) & ":" & ADDRESS(sort_max_row, COLUMN(budget)), "") | R28: =IF(is_cat, RANK(budget, INDIRECT(budget_range), 0), "") | S28: =IF(is_cat, _xlfn.NUMBERVALUE(tracked_rank & budget_rank), "") | T28: =IF(is_cat, ADDRESS(sort_min_row, COLUMN(comb_rank)) & ":" & ADDRESS(sort_max_row, COLUMN(comb_rank)), "") | U28: =IF(is_cat, RANK(comb_rank, INDIRECT(comb_rank_range), 1), "") | V28: =IF(is_cat, ADDRESS(sort_min_row, COLUMN(comb_rank_norm)) & ":" & ADDRESS(ROW(), COLUMN(comb_rank_norm)), "") | W28: =IF(is_cat, comb_rank_norm + COUNTIF(INDIRECT(comb_rank_norm_run_range), comb_rank_norm)-1, "") | X28: =IF(is_cat, header_row_id + comb_rank_unique, row_id) | Y28: =IF(is_empty, "", INDEX($J:$J, MATCH(row_id, $X:$X, 0))) | Z28: =IF(is_empty, "", IF(is_header, "Tracked", INDEX($K:$K, MATCH(row_id, $X:$X, 0)))) | AA28: =IF(is_empty, "", IF(is_header, "Budget", INDEX($L:$L, MATCH(row_id, $X:$X, 0)))) | AB28: =IF(is_empty, "", IF(is_header, "% Compl.", IFERROR(out_tracked / out_budget, "-"))) | AC28: =IF(is_empty, "", IF(is_header, "Remaining", IF(out_budget - out_tracked > 0, out_budget - out_tracked, 0))) | AD28: =IF(is_empty, "", IF(is_header, "Excess", IF(out_budget - out_tracked < 0, out_tracked - out_budget, 0)))
C29: {=IF(C28=-1,-1, IF(C28<income_max_row,C28+1, IF(C28=income_max_row,income_total_row, IF(C28=income_total_row,"/1", IF(C28="/1",expenses_header_row, IF(C28<expenses_max_row,C28+1, IF(C28=expenses_max_row,expenses_total_row, IF(C28=expenses_total_row, "/2", IF(C28="/2", savings_header_row, IF(C28<savings_max_row, C28+1, IF(C28=savings_max_row, savings_total_row, -1)))))))))))} | D29: =IF(is_header, row_id, IF(NOT(is_empty), D28, -1)) | E29: {=OR(row_id=income_header_row, row_id=expenses_header_row, row_id=savings_header_row) * 1} | F29: =1 * NOT(OR(is_header, is_total, is_empty)) | G29: {=OR(row_id=income_total_row, row_id=expenses_total_row, row_id=savings_total_row) * 1} | H29: =OR(row_id="/1", row_id="/2", row_id=-1)*1 | I29: {=IFERROR(INDEX('Budget Planning'!$C:$C, header_row_id), "")} | J29: {=IFERROR(INDEX('Budget Planning'!$C:$C, row_id), "")} | K29: {=IF(OR(is_header, is_empty), "", IF(is_total, IF(selected_period="Total Year", SUM(tracking[Amount] * (tracking[Type]=type) * (YEAR(tracking[Effective Date])=selected_year)), SUM(tracking[Amount] * (tracking[Type]=type) * (YEAR(tracking[Effective Date])=selected_year) * (MONTH(tracking[Effective Date])=selected_period))), IF(selected_period="Total Year", SUM(tracking[Amount] * (tracking[Type]=type) * (tracking[Category]=item) * (YEAR(tracking[Effective Date])=selected_year)), SUM(tracking[Amount] * (tracking[Type]=type) * (tracking[Category]=item) * (YEAR(tracking[Effective Date])=selected_year) * (MONTH(tracking[Effective Date])=selected_period)))))} | L29: {=IF(OR(is_header, is_empty), "", INDEX('Budget Planning'!$E:$EM, row_id, MATCH(IF(selected_period="Total Year", selected_year, DATE(selected_year, selected_period, 1)), 'Budget Planning'!$E$9:$EM$9, 0)))} | M29: {=IF(is_cat, IF(header_row_id=income_header_row, MATCH(income_min_row, $C:$C, 0), IF(header_row_id=expenses_header_row, MATCH(expenses_min_row, $C:$C, 0), IF(header_row_id=savings_header_row, MATCH(savings_min_row, $C:$C, 0), ""))), "")} | N29: {=IF(is_cat, IF(header_row_id=income_header_row, MATCH(income_max_row, $C:$C, 0), IF(header_row_id=expenses_header_row, MATCH(expenses_max_row, $C:$C, 0), IF(header_row_id=savings_header_row, MATCH(savings_max_row, $C:$C, 0), ""))), "")} | O29: =IF(is_cat, ADDRESS(sort_min_row, COLUMN(tracked)) & ":" & ADDRESS(sort_max_row, COLUMN(tracked)), "") | P29: =IF(is_cat, RANK(tracked, INDIRECT(tracked_range), 0), "") | Q29: =IF(is_cat, ADDRESS(sort_min_row, COLUMN(budget)) & ":" & ADDRESS(sort_max_row, COLUMN(budget)), "") | R29: =IF(is_cat, RANK(budget, INDIRECT(budget_range), 0), "") | S29: =IF(is_cat, _xlfn.NUMBERVALUE(tracked_rank & budget_rank), "") | T29: =IF(is_cat, ADDRESS(sort_min_row, COLUMN(comb_rank)) & ":" & ADDRESS(sort_max_row, COLUMN(comb_rank)), "") | U29: =IF(is_cat, RANK(comb_rank, INDIRECT(comb_rank_range), 1), "") | V29: =IF(is_cat, ADDRESS(sort_min_row, COLUMN(comb_rank_norm)) & ":" & ADDRESS(ROW(), COLUMN(comb_rank_norm)), "") | W29: =IF(is_cat, comb_rank_norm + COUNTIF(INDIRECT(comb_rank_norm_run_range), comb_rank_norm)-1, "") | X29: =IF(is_cat, header_row_id + comb_rank_unique, row_id) | Y29: =IF(is_empty, "", INDEX($J:$J, MATCH(row_id, $X:$X, 0))) | Z29: =IF(is_empty, "", IF(is_header, "Tracked", INDEX($K:$K, MATCH(row_id, $X:$X, 0)))) | AA29: =IF(is_empty, "", IF(is_header, "Budget", INDEX($L:$L, MATCH(row_id, $X:$X, 0)))) | AB29: =IF(is_empty, "", IF(is_header, "% Compl.", IFERROR(out_tracked / out_budget, "-"))) | AC29: =IF(is_empty, "", IF(is_header, "Remaining", IF(out_budget - out_tracked > 0, out_budget - out_tracked, 0))) | AD29: =IF(is_empty, "", IF(is_header, "Excess", IF(out_budget - out_tracked < 0, out_tracked - out_budget, 0)))
C30: {=IF(C29=-1,-1, IF(C29<income_max_row,C29+1, IF(C29=income_max_row,income_total_row, IF(C29=income_total_row,"/1", IF(C29="/1",expenses_header_row, IF(C29<expenses_max_row,C29+1, IF(C29=expenses_max_row,expenses_total_row, IF(C29=expenses_total_row, "/2", IF(C29="/2", savings_header_row, IF(C29<savings_max_row, C29+1, IF(C29=savings_max_row, savings_total_row, -1)))))))))))} | D30: =IF(is_header, row_id, IF(NOT(is_empty), D29, -1)) | E30: {=OR(row_id=income_header_row, row_id=expenses_header_row, row_id=savings_header_row) * 1} | F30: =1 * NOT(OR(is_header, is_total, is_empty)) | G30: {=OR(row_id=income_total_row, row_id=expenses_total_row, row_id=savings_total_row) * 1} | H30: =OR(row_id="/1", row_id="/2", row_id=-1)*1 | I30: {=IFERROR(INDEX('Budget Planning'!$C:$C, header_row_id), "")} | J30: {=IFERROR(INDEX('Budget Planning'!$C:$C, row_id), "")} | K30: {=IF(OR(is_header, is_empty), "", IF(is_total, IF(selected_period="Total Year", SUM(tracking[Amount] * (tracking[Type]=type) * (YEAR(tracking[Effective Date])=selected_year)), SUM(tracking[Amount] * (tracking[Type]=type) * (YEAR(tracking[Effective Date])=selected_year) * (MONTH(tracking[Effective Date])=selected_period))), IF(selected_period="Total Year", SUM(tracking[Amount] * (tracking[Type]=type) * (tracking[Category]=item) * (YEAR(tracking[Effective Date])=selected_year)), SUM(tracking[Amount] * (tracking[Type]=type) * (tracking[Category]=item) * (YEAR(tracking[Effective Date])=selected_year) * (MONTH(tracking[Effective Date])=selected_period)))))} | L30: {=IF(OR(is_header, is_empty), "", INDEX('Budget Planning'!$E:$EM, row_id, MATCH(IF(selected_period="Total Year", selected_year, DATE(selected_year, selected_period, 1)), 'Budget Planning'!$E$9:$EM$9, 0)))} | M30: {=IF(is_cat, IF(header_row_id=income_header_row, MATCH(income_min_row, $C:$C, 0), IF(header_row_id=expenses_header_row, MATCH(expenses_min_row, $C:$C, 0), IF(header_row_id=savings_header_row, MATCH(savings_min_row, $C:$C, 0), ""))), "")} | N30: {=IF(is_cat, IF(header_row_id=income_header_row, MATCH(income_max_row, $C:$C, 0), IF(header_row_id=expenses_header_row, MATCH(expenses_max_row, $C:$C, 0), IF(header_row_id=savings_header_row, MATCH(savings_max_row, $C:$C, 0), ""))), "")} | O30: =IF(is_cat, ADDRESS(sort_min_row, COLUMN(tracked)) & ":" & ADDRESS(sort_max_row, COLUMN(tracked)), "") | P30: =IF(is_cat, RANK(tracked, INDIRECT(tracked_range), 0), "") | Q30: =IF(is_cat, ADDRESS(sort_min_row, COLUMN(budget)) & ":" & ADDRESS(sort_max_row, COLUMN(budget)), "") | R30: =IF(is_cat, RANK(budget, INDIRECT(budget_range), 0), "") | S30: =IF(is_cat, _xlfn.NUMBERVALUE(tracked_rank & budget_rank), "") | T30: =IF(is_cat, ADDRESS(sort_min_row, COLUMN(comb_rank)) & ":" & ADDRESS(sort_max_row, COLUMN(comb_rank)), "") | U30: =IF(is_cat, RANK(comb_rank, INDIRECT(comb_rank_range), 1), "") | V30: =IF(is_cat, ADDRESS(sort_min_row, COLUMN(comb_rank_norm)) & ":" & ADDRESS(ROW(), COLUMN(comb_rank_norm)), "") | W30: =IF(is_cat, comb_rank_norm + COUNTIF(INDIRECT(comb_rank_norm_run_range), comb_rank_norm)-1, "") | X30: =IF(is_cat, header_row_id + comb_rank_unique, row_id) | Y30: =IF(is_empty, "", INDEX($J:$J, MATCH(row_id, $X:$X, 0))) | Z30: =IF(is_empty, "", IF(is_header, "Tracked", INDEX($K:$K, MATCH(row_id, $X:$X, 0)))) | AA30: =IF(is_empty, "", IF(is_header, "Budget", INDEX($L:$L, MATCH(row_id, $X:$X, 0)))) | AB30: =IF(is_empty, "", IF(is_header, "% Compl.", IFERROR(out_tracked / out_budget, "-"))) | AC30: =IF(is_empty, "", IF(is_header, "Remaining", IF(out_budget - out_tracked > 0, out_budget - out_tracked, 0))) | AD30: =IF(is_empty, "", IF(is_header, "Excess", IF(out_budget - out_tracked < 0, out_tracked - out_budget, 0))) | AI30: =Calculation!I35 | AJ30: =Calculation!J35 | AP30: =Calculation!M35 | AQ30: =Calculation!N35
C31: {=IF(C30=-1,-1, IF(C30<income_max_row,C30+1, IF(C30=income_max_row,income_total_row, IF(C30=income_total_row,"/1", IF(C30="/1",expenses_header_row, IF(C30<expenses_max_row,C30+1, IF(C30=expenses_max_row,expenses_total_row, IF(C30=expenses_total_row, "/2", IF(C30="/2", savings_header_row, IF(C30<savings_max_row, C30+1, IF(C30=savings_max_row, savings_total_row, -1)))))))))))} | D31: =IF(is_header, row_id, IF(NOT(is_empty), D30, -1)) | E31: {=OR(row_id=income_header_row, row_id=expenses_header_row, row_id=savings_header_row) * 1} | F31: =1 * NOT(OR(is_header, is_total, is_empty)) | G31: {=OR(row_id=income_total_row, row_id=expenses_total_row, row_id=savings_total_row) * 1} | H31: =OR(row_id="/1", row_id="/2", row_id=-1)*1 | I31: {=IFERROR(INDEX('Budget Planning'!$C:$C, header_row_id), "")} | J31: {=IFERROR(INDEX('Budget Planning'!$C:$C, row_id), "")} | K31: {=IF(OR(is_header, is_empty), "", IF(is_total, IF(selected_period="Total Year", SUM(tracking[Amount] * (tracking[Type]=type) * (YEAR(tracking[Effective Date])=selected_year)), SUM(tracking[Amount] * (tracking[Type]=type) * (YEAR(tracking[Effective Date])=selected_year) * (MONTH(tracking[Effective Date])=selected_period))), IF(selected_period="Total Year", SUM(tracking[Amount] * (tracking[Type]=type) * (tracking[Category]=item) * (YEAR(tracking[Effective Date])=selected_year)), SUM(tracking[Amount] * (tracking[Type]=type) * (tracking[Category]=item) * (YEAR(tracking[Effective Date])=selected_year) * (MONTH(tracking[Effective Date])=selected_period)))))} | L31: {=IF(OR(is_header, is_empty), "", INDEX('Budget Planning'!$E:$EM, row_id, MATCH(IF(selected_period="Total Year", selected_year, DATE(selected_year, selected_period, 1)), 'Budget Planning'!$E$9:$EM$9, 0)))} | M31: {=IF(is_cat, IF(header_row_id=income_header_row, MATCH(income_min_row, $C:$C, 0), IF(header_row_id=expenses_header_row, MATCH(expenses_min_row, $C:$C, 0), IF(header_row_id=savings_header_row, MATCH(savings_min_row, $C:$C, 0), ""))), "")} | N31: {=IF(is_cat, IF(header_row_id=income_header_row, MATCH(income_max_row, $C:$C, 0), IF(header_row_id=expenses_header_row, MATCH(expenses_max_row, $C:$C, 0), IF(header_row_id=savings_header_row, MATCH(savings_max_row, $C:$C, 0), ""))), "")} | O31: =IF(is_cat, ADDRESS(sort_min_row, COLUMN(tracked)) & ":" & ADDRESS(sort_max_row, COLUMN(tracked)), "") | P31: =IF(is_cat, RANK(tracked, INDIRECT(tracked_range), 0), "") | Q31: =IF(is_cat, ADDRESS(sort_min_row, COLUMN(budget)) & ":" & ADDRESS(sort_max_row, COLUMN(budget)), "") | R31: =IF(is_cat, RANK(budget, INDIRECT(budget_range), 0), "") | S31: =IF(is_cat, _xlfn.NUMBERVALUE(tracked_rank & budget_rank), "") | T31: =IF(is_cat, ADDRESS(sort_min_row, COLUMN(comb_rank)) & ":" & ADDRESS(sort_max_row, COLUMN(comb_rank)), "") | U31: =IF(is_cat, RANK(comb_rank, INDIRECT(comb_rank_range), 1), "") | V31: =IF(is_cat, ADDRESS(sort_min_row, COLUMN(comb_rank_norm)) & ":" & ADDRESS(ROW(), COLUMN(comb_rank_norm)), "") | W31: =IF(is_cat, comb_rank_norm + COUNTIF(INDIRECT(comb_rank_norm_run_range), comb_rank_norm)-1, "") | X31: =IF(is_cat, header_row_id + comb_rank_unique, row_id) | Y31: =IF(is_empty, "", INDEX($J:$J, MATCH(row_id, $X:$X, 0))) | Z31: =IF(is_empty, "", IF(is_header, "Tracked", INDEX($K:$K, MATCH(row_id, $X:$X, 0)))) | AA31: =IF(is_empty, "", IF(is_header, "Budget", INDEX($L:$L, MATCH(row_id, $X:$X, 0)))) | AB31: =IF(is_empty, "", IF(is_header, "% Compl.", IFERROR(out_tracked / out_budget, "-"))) | AC31: =IF(is_empty, "", IF(is_header, "Remaining", IF(out_budget - out_tracked > 0, out_budget - out_tracked, 0))) | AD31: =IF(is_empty, "", IF(is_header, "Excess", IF(out_budget - out_tracked < 0, out_tracked - out_budget, 0))) | AI31: =Calculation!I36 | AJ31: =Calculation!J36 | AP31: =Calculation!M36 | AQ31: =Calculation!N36
C32: {=IF(C31=-1,-1, IF(C31<income_max_row,C31+1, IF(C31=income_max_row,income_total_row, IF(C31=income_total_row,"/1", IF(C31="/1",expenses_header_row, IF(C31<expenses_max_row,C31+1, IF(C31=expenses_max_row,expenses_total_row, IF(C31=expenses_total_row, "/2", IF(C31="/2", savings_header_row, IF(C31<savings_max_row, C31+1, IF(C31=savings_max_row, savings_total_row, -1)))))))))))} | D32: =IF(is_header, row_id, IF(NOT(is_empty), D31, -1)) | E32: {=OR(row_id=income_header_row, row_id=expenses_header_row, row_id=savings_header_row) * 1} | F32: =1 * NOT(OR(is_header, is_total, is_empty)) | G32: {=OR(row_id=income_total_row, row_id=expenses_total_row, row_id=savings_total_row) * 1} | H32: =OR(row_id="/1", row_id="/2", row_id=-1)*1 | I32: {=IFERROR(INDEX('Budget Planning'!$C:$C, header_row_id), "")} | J32: {=IFERROR(INDEX('Budget Planning'!$C:$C, row_id), "")} | K32: {=IF(OR(is_header, is_empty), "", IF(is_total, IF(selected_period="Total Year", SUM(tracking[Amount] * (tracking[Type]=type) * (YEAR(tracking[Effective Date])=selected_year)), SUM(tracking[Amount] * (tracking[Type]=type) * (YEAR(tracking[Effective Date])=selected_year) * (MONTH(tracking[Effective Date])=selected_period))), IF(selected_period="Total Year", SUM(tracking[Amount] * (tracking[Type]=type) * (tracking[Category]=item) * (YEAR(tracking[Effective Date])=selected_year)), SUM(tracking[Amount] * (tracking[Type]=type) * (tracking[Category]=item) * (YEAR(tracking[Effective Date])=selected_year) * (MONTH(tracking[Effective Date])=selected_period)))))} | L32: {=IF(OR(is_header, is_empty), "", INDEX('Budget Planning'!$E:$EM, row_id, MATCH(IF(selected_period="Total Year", selected_year, DATE(selected_year, selected_period, 1)), 'Budget Planning'!$E$9:$EM$9, 0)))} | M32: {=IF(is_cat, IF(header_row_id=income_header_row, MATCH(income_min_row, $C:$C, 0), IF(header_row_id=expenses_header_row, MATCH(expenses_min_row, $C:$C, 0), IF(header_row_id=savings_header_row, MATCH(savings_min_row, $C:$C, 0), ""))), "")} | N32: {=IF(is_cat, IF(header_row_id=income_header_row, MATCH(income_max_row, $C:$C, 0), IF(header_row_id=expenses_header_row, MATCH(expenses_max_row, $C:$C, 0), IF(header_row_id=savings_header_row, MATCH(savings_max_row, $C:$C, 0), ""))), "")} | O32: =IF(is_cat, ADDRESS(sort_min_row, COLUMN(tracked)) & ":" & ADDRESS(sort_max_row, COLUMN(tracked)), "") | P32: =IF(is_cat, RANK(tracked, INDIRECT(tracked_range), 0), "") | Q32: =IF(is_cat, ADDRESS(sort_min_row, COLUMN(budget)) & ":" & ADDRESS(sort_max_row, COLUMN(budget)), "") | R32: =IF(is_cat, RANK(budget, INDIRECT(budget_range), 0), "") | S32: =IF(is_cat, _xlfn.NUMBERVALUE(tracked_rank & budget_rank), "") | T32: =IF(is_cat, ADDRESS(sort_min_row, COLUMN(comb_rank)) & ":" & ADDRESS(sort_max_row, COLUMN(comb_rank)), "") | U32: =IF(is_cat, RANK(comb_rank, INDIRECT(comb_rank_range), 1), "") | V32: =IF(is_cat, ADDRESS(sort_min_row, COLUMN(comb_rank_norm)) & ":" & ADDRESS(ROW(), COLUMN(comb_rank_norm)), "") | W32: =IF(is_cat, comb_rank_norm + COUNTIF(INDIRECT(comb_rank_norm_run_range), comb_rank_norm)-1, "") | X32: =IF(is_cat, header_row_id + comb_rank_unique, row_id) | Y32: =IF(is_empty, "", INDEX($J:$J, MATCH(row_id, $X:$X, 0))) | Z32: =IF(is_empty, "", IF(is_header, "Tracked", INDEX($K:$K, MATCH(row_id, $X:$X, 0)))) | AA32: =IF(is_empty, "", IF(is_header, "Budget", INDEX($L:$L, MATCH(row_id, $X:$X, 0)))) | AB32: =IF(is_empty, "", IF(is_header, "% Compl.", IFERROR(out_tracked / out_budget, "-"))) | AC32: =IF(is_empty, "", IF(is_header, "Remaining", IF(out_budget - out_tracked > 0, out_budget - out_tracked, 0))) | AD32: =IF(is_empty, "", IF(is_header, "Excess", IF(out_budget - out_tracked < 0, out_tracked - out_budget, 0))) | AI32: =Calculation!I37 | AJ32: =Calculation!J37 | AP32: =Calculation!M37 | AQ32: =Calculation!N37
C33: {=IF(C32=-1,-1, IF(C32<income_max_row,C32+1, IF(C32=income_max_row,income_total_row, IF(C32=income_total_row,"/1", IF(C32="/1",expenses_header_row, IF(C32<expenses_max_row,C32+1, IF(C32=expenses_max_row,expenses_total_row, IF(C32=expenses_total_row, "/2", IF(C32="/2", savings_header_row, IF(C32<savings_max_row, C32+1, IF(C32=savings_max_row, savings_total_row, -1)))))))))))} | D33: =IF(is_header, row_id, IF(NOT(is_empty), D32, -1)) | E33: {=OR(row_id=income_header_row, row_id=expenses_header_row, row_id=savings_header_row) * 1} | F33: =1 * NOT(OR(is_header, is_total, is_empty)) | G33: {=OR(row_id=income_total_row, row_id=expenses_total_row, row_id=savings_total_row) * 1} | H33: =OR(row_id="/1", row_id="/2", row_id=-1)*1 | I33: {=IFERROR(INDEX('Budget Planning'!$C:$C, header_row_id), "")} | J33: {=IFERROR(INDEX('Budget Planning'!$C:$C, row_id), "")} | K33: {=IF(OR(is_header, is_empty), "", IF(is_total, IF(selected_period="Total Year", SUM(tracking[Amount] * (tracking[Type]=type) * (YEAR(tracking[Effective Date])=selected_year)), SUM(tracking[Amount] * (tracking[Type]=type) * (YEAR(tracking[Effective Date])=selected_year) * (MONTH(tracking[Effective Date])=selected_period))), IF(selected_period="Total Year", SUM(tracking[Amount] * (tracking[Type]=type) * (tracking[Category]=item) * (YEAR(tracking[Effective Date])=selected_year)), SUM(tracking[Amount] * (tracking[Type]=type) * (tracking[Category]=item) * (YEAR(tracking[Effective Date])=selected_year) * (MONTH(tracking[Effective Date])=selected_period)))))} | L33: {=IF(OR(is_header, is_empty), "", INDEX('Budget Planning'!$E:$EM, row_id, MATCH(IF(selected_period="Total Year", selected_year, DATE(selected_year, selected_period, 1)), 'Budget Planning'!$E$9:$EM$9, 0)))} | M33: {=IF(is_cat, IF(header_row_id=income_header_row, MATCH(income_min_row, $C:$C, 0), IF(header_row_id=expenses_header_row, MATCH(expenses_min_row, $C:$C, 0), IF(header_row_id=savings_header_row, MATCH(savings_min_row, $C:$C, 0), ""))), "")} | N33: {=IF(is_cat, IF(header_row_id=income_header_row, MATCH(income_max_row, $C:$C, 0), IF(header_row_id=expenses_header_row, MATCH(expenses_max_row, $C:$C, 0), IF(header_row_id=savings_header_row, MATCH(savings_max_row, $C:$C, 0), ""))), "")} | O33: =IF(is_cat, ADDRESS(sort_min_row, COLUMN(tracked)) & ":" & ADDRESS(sort_max_row, COLUMN(tracked)), "") | P33: =IF(is_cat, RANK(tracked, INDIRECT(tracked_range), 0), "") | Q33: =IF(is_cat, ADDRESS(sort_min_row, COLUMN(budget)) & ":" & ADDRESS(sort_max_row, COLUMN(budget)), "") | R33: =IF(is_cat, RANK(budget, INDIRECT(budget_range), 0), "") | S33: =IF(is_cat, _xlfn.NUMBERVALUE(tracked_rank & budget_rank), "") | T33: =IF(is_cat, ADDRESS(sort_min_row, COLUMN(comb_rank)) & ":" & ADDRESS(sort_max_row, COLUMN(comb_rank)), "") | U33: =IF(is_cat, RANK(comb_rank, INDIRECT(comb_rank_range), 1), "") | V33: =IF(is_cat, ADDRESS(sort_min_row, COLUMN(comb_rank_norm)) & ":" & ADDRESS(ROW(), COLUMN(comb_rank_norm)), "") | W33: =IF(is_cat, comb_rank_norm + COUNTIF(INDIRECT(comb_rank_norm_run_range), comb_rank_norm)-1, "") | X33: =IF(is_cat, header_row_id + comb_rank_unique, row_id) | Y33: =IF(is_empty, "", INDEX($J:$J, MATCH(row_id, $X:$X, 0))) | Z33: =IF(is_empty, "", IF(is_header, "Tracked", INDEX($K:$K, MATCH(row_id, $X:$X, 0)))) | AA33: =IF(is_empty, "", IF(is_header, "Budget", INDEX($L:$L, MATCH(row_id, $X:$X, 0)))) | AB33: =IF(is_empty, "", IF(is_header, "% Compl.", IFERROR(out_tracked / out_budget, "-"))) | AC33: =IF(is_empty, "", IF(is_header, "Remaining", IF(out_budget - out_tracked > 0, out_budget - out_tracked, 0))) | AD33: =IF(is_empty, "", IF(is_header, "Excess", IF(out_budget - out_tracked < 0, out_tracked - out_budget, 0))) | AI33: =Calculation!I38 | AJ33: =Calculation!J38 | AP33: =Calculation!M38 | AQ33: =Calculation!N38
C34: {=IF(C33=-1,-1, IF(C33<income_max_row,C33+1, IF(C33=income_max_row,income_total_row, IF(C33=income_total_row,"/1", IF(C33="/1",expenses_header_row, IF(C33<expenses_max_row,C33+1, IF(C33=expenses_max_row,expenses_total_row, IF(C33=expenses_total_row, "/2", IF(C33="/2", savings_header_row, IF(C33<savings_max_row, C33+1, IF(C33=savings_max_row, savings_total_row, -1)))))))))))} | D34: =IF(is_header, row_id, IF(NOT(is_empty), D33, -1)) | E34: {=OR(row_id=income_header_row, row_id=expenses_header_row, row_id=savings_header_row) * 1} | F34: =1 * NOT(OR(is_header, is_total, is_empty)) | G34: {=OR(row_id=income_total_row, row_id=expenses_total_row, row_id=savings_total_row) * 1} | H34: =OR(row_id="/1", row_id="/2", row_id=-1)*1 | I34: {=IFERROR(INDEX('Budget Planning'!$C:$C, header_row_id), "")} | J34: {=IFERROR(INDEX('Budget Planning'!$C:$C, row_id), "")} | K34: {=IF(OR(is_header, is_empty), "", IF(is_total, IF(selected_period="Total Year", SUM(tracking[Amount] * (tracking[Type]=type) * (YEAR(tracking[Effective Date])=selected_year)), SUM(tracking[Amount] * (tracking[Type]=type) * (YEAR(tracking[Effective Date])=selected_year) * (MONTH(tracking[Effective Date])=selected_period))), IF(selected_period="Total Year", SUM(tracking[Amount] * (tracking[Type]=type) * (tracking[Category]=item) * (YEAR(tracking[Effective Date])=selected_year)), SUM(tracking[Amount] * (tracking[Type]=type) * (tracking[Category]=item) * (YEAR(tracking[Effective Date])=selected_year) * (MONTH(tracking[Effective Date])=selected_period)))))} | L34: {=IF(OR(is_header, is_empty), "", INDEX('Budget Planning'!$E:$EM, row_id, MATCH(IF(selected_period="Total Year", selected_year, DATE(selected_year, selected_period, 1)), 'Budget Planning'!$E$9:$EM$9, 0)))} | M34: {=IF(is_cat, IF(header_row_id=income_header_row, MATCH(income_min_row, $C:$C, 0), IF(header_row_id=expenses_header_row, MATCH(expenses_min_row, $C:$C, 0), IF(header_row_id=savings_header_row, MATCH(savings_min_row, $C:$C, 0), ""))), "")} | N34: {=IF(is_cat, IF(header_row_id=income_header_row, MATCH(income_max_row, $C:$C, 0), IF(header_row_id=expenses_header_row, MATCH(expenses_max_row, $C:$C, 0), IF(header_row_id=savings_header_row, MATCH(savings_max_row, $C:$C, 0), ""))), "")} | O34: =IF(is_cat, ADDRESS(sort_min_row, COLUMN(tracked)) & ":" & ADDRESS(sort_max_row, COLUMN(tracked)), "") | P34: =IF(is_cat, RANK(tracked, INDIRECT(tracked_range), 0), "") | Q34: =IF(is_cat, ADDRESS(sort_min_row, COLUMN(budget)) & ":" & ADDRESS(sort_max_row, COLUMN(budget)), "") | R34: =IF(is_cat, RANK(budget, INDIRECT(budget_range), 0), "") | S34: =IF(is_cat, _xlfn.NUMBERVALUE(tracked_rank & budget_rank), "") | T34: =IF(is_cat, ADDRESS(sort_min_row, COLUMN(comb_rank)) & ":" & ADDRESS(sort_max_row, COLUMN(comb_rank)), "") | U34: =IF(is_cat, RANK(comb_rank, INDIRECT(comb_rank_range), 1), "") | V34: =IF(is_cat, ADDRESS(sort_min_row, COLUMN(comb_rank_norm)) & ":" & ADDRESS(ROW(), COLUMN(comb_rank_norm)), "") | W34: =IF(is_cat, comb_rank_norm + COUNTIF(INDIRECT(comb_rank_norm_run_range), comb_rank_norm)-1, "") | X34: =IF(is_cat, header_row_id + comb_rank_unique, row_id) | Y34: =IF(is_empty, "", INDEX($J:$J, MATCH(row_id, $X:$X, 0))) | Z34: =IF(is_empty, "", IF(is_header, "Tracked", INDEX($K:$K, MATCH(row_id, $X:$X, 0)))) | AA34: =IF(is_empty, "", IF(is_header, "Budget", INDEX($L:$L, MATCH(row_id, $X:$X, 0)))) | AB34: =IF(is_empty, "", IF(is_header, "% Compl.", IFERROR(out_tracked / out_budget, "-"))) | AC34: =IF(is_empty, "", IF(is_header, "Remaining", IF(out_budget - out_tracked > 0, out_budget - out_tracked, 0))) | AD34: =IF(is_empty, "", IF(is_header, "Excess", IF(out_budget - out_tracked < 0, out_tracked - out_budget, 0))) | AI34: =Calculation!I39 | AJ34: =Calculation!J39 | AP34: =Calculation!M39 | AQ34: =Calculation!N39
C35: {=IF(C34=-1,-1, IF(C34<income_max_row,C34+1, IF(C34=income_max_row,income_total_row, IF(C34=income_total_row,"/1", IF(C34="/1",expenses_header_row, IF(C34<expenses_max_row,C34+1, IF(C34=expenses_max_row,expenses_total_row, IF(C34=expenses_total_row, "/2", IF(C34="/2", savings_header_row, IF(C34<savings_max_row, C34+1, IF(C34=savings_max_row, savings_total_row, -1)))))))))))} | D35: =IF(is_header, row_id, IF(NOT(is_empty), D34, -1)) | E35: {=OR(row_id=income_header_row, row_id=expenses_header_row, row_id=savings_header_row) * 1} | F35: =1 * NOT(OR(is_header, is_total, is_empty)) | G35: {=OR(row_id=income_total_row, row_id=expenses_total_row, row_id=savings_total_row) * 1} | H35: =OR(row_id="/1", row_id="/2", row_id=-1)*1 | I35: {=IFERROR(INDEX('Budget Planning'!$C:$C, header_row_id), "")} | J35: {=IFERROR(INDEX('Budget Planning'!$C:$C, row_id), "")} | K35: {=IF(OR(is_header, is_empty), "", IF(is_total, IF(selected_period="Total Year", SUM(tracking[Amount] * (tracking[Type]=type) * (YEAR(tracking[Effective Date])=selected_year)), SUM(tracking[Amount] * (tracking[Type]=type) * (YEAR(tracking[Effective Date])=selected_year) * (MONTH(tracking[Effective Date])=selected_period))), IF(selected_period="Total Year", SUM(tracking[Amount] * (tracking[Type]=type) * (tracking[Category]=item) * (YEAR(tracking[Effective Date])=selected_year)), SUM(tracking[Amount] * (tracking[Type]=type) * (tracking[Category]=item) * (YEAR(tracking[Effective Date])=selected_year) * (MONTH(tracking[Effective Date])=selected_period)))))} | L35: {=IF(OR(is_header, is_empty), "", INDEX('Budget Planning'!$E:$EM, row_id, MATCH(IF(selected_period="Total Year", selected_year, DATE(selected_year, selected_period, 1)), 'Budget Planning'!$E$9:$EM$9, 0)))} | M35: {=IF(is_cat, IF(header_row_id=income_header_row, MATCH(income_min_row, $C:$C, 0), IF(header_row_id=expenses_header_row, MATCH(expenses_min_row, $C:$C, 0), IF(header_row_id=savings_header_row, MATCH(savings_min_row, $C:$C, 0), ""))), "")} | N35: {=IF(is_cat, IF(header_row_id=income_header_row, MATCH(income_max_row, $C:$C, 0), IF(header_row_id=expenses_header_row, MATCH(expenses_max_row, $C:$C, 0), IF(header_row_id=savings_header_row, MATCH(savings_max_row, $C:$C, 0), ""))), "")} | O35: =IF(is_cat, ADDRESS(sort_min_row, COLUMN(tracked)) & ":" & ADDRESS(sort_max_row, COLUMN(tracked)), "") | P35: =IF(is_cat, RANK(tracked, INDIRECT(tracked_range), 0), "") | Q35: =IF(is_cat, ADDRESS(sort_min_row, COLUMN(budget)) & ":" & ADDRESS(sort_max_row, COLUMN(budget)), "") | R35: =IF(is_cat, RANK(budget, INDIRECT(budget_range), 0), "") | S35: =IF(is_cat, _xlfn.NUMBERVALUE(tracked_rank & budget_rank), "") | T35: =IF(is_cat, ADDRESS(sort_min_row, COLUMN(comb_rank)) & ":" & ADDRESS(sort_max_row, COLUMN(comb_rank)), "") | U35: =IF(is_cat, RANK(comb_rank, INDIRECT(comb_rank_range), 1), "") | V35: =IF(is_cat, ADDRESS(sort_min_row, COLUMN(comb_rank_norm)) & ":" & ADDRESS(ROW(), COLUMN(comb_rank_norm)), "") | W35: =IF(is_cat, comb_rank_norm + COUNTIF(INDIRECT(comb_rank_norm_run_range), comb_rank_norm)-1, "") | X35: =IF(is_cat, header_row_id + comb_rank_unique, row_id) | Y35: =IF(is_empty, "", INDEX($J:$J, MATCH(row_id, $X:$X, 0))) | Z35: =IF(is_empty, "", IF(is_header, "Tracked", INDEX($K:$K, MATCH(row_id, $X:$X, 0)))) | AA35: =IF(is_empty, "", IF(is_header, "Budget", INDEX($L:$L, MATCH(row_id, $X:$X, 0)))) | AB35: =IF(is_empty, "", IF(is_header, "% Compl.", IFERROR(out_tracked / out_budget, "-"))) | AC35: =IF(is_empty, "", IF(is_header, "Remaining", IF(out_budget - out_tracked > 0, out_budget - out_tracked, 0))) | AD35: =IF(is_empty, "", IF(is_header, "Excess", IF(out_budget - out_tracked < 0, out_tracked - out_budget, 0))) | AI35: =Calculation!I40 | AJ35: =Calculation!J40 | AP35: =Calculation!M40 | AQ35: =Calculation!N40
C36: {=IF(C35=-1,-1, IF(C35<income_max_row,C35+1, IF(C35=income_max_row,income_total_row, IF(C35=income_total_row,"/1", IF(C35="/1",expenses_header_row, IF(C35<expenses_max_row,C35+1, IF(C35=expenses_max_row,expenses_total_row, IF(C35=expenses_total_row, "/2", IF(C35="/2", savings_header_row, IF(C35<savings_max_row, C35+1, IF(C35=savings_max_row, savings_total_row, -1)))))))))))} | D36: =IF(is_header, row_id, IF(NOT(is_empty), D35, -1)) | E36: {=OR(row_id=income_header_row, row_id=expenses_header_row, row_id=savings_header_row) * 1} | F36: =1 * NOT(OR(is_header, is_total, is_empty)) | G36: {=OR(row_id=income_total_row, row_id=expenses_total_row, row_id=savings_total_row) * 1} | H36: =OR(row_id="/1", row_id="/2", row_id=-1)*1 | I36: {=IFERROR(INDEX('Budget Planning'!$C:$C, header_row_id), "")} | J36: {=IFERROR(INDEX('Budget Planning'!$C:$C, row_id), "")} | K36: {=IF(OR(is_header, is_empty), "", IF(is_total, IF(selected_period="Total Year", SUM(tracking[Amount] * (tracking[Type]=type) * (YEAR(tracking[Effective Date])=selected_year)), SUM(tracking[Amount] * (tracking[Type]=type) * (YEAR(tracking[Effective Date])=selected_year) * (MONTH(tracking[Effective Date])=selected_period))), IF(selected_period="Total Year", SUM(tracking[Amount] * (tracking[Type]=type) * (tracking[Category]=item) * (YEAR(tracking[Effective Date])=selected_year)), SUM(tracking[Amount] * (tracking[Type]=type) * (tracking[Category]=item) * (YEAR(tracking[Effective Date])=selected_year) * (MONTH(tracking[Effective Date])=selected_period)))))} | L36: {=IF(OR(is_header, is_empty), "", INDEX('Budget Planning'!$E:$EM, row_id, MATCH(IF(selected_period="Total Year", selected_year, DATE(selected_year, selected_period, 1)), 'Budget Planning'!$E$9:$EM$9, 0)))} | M36: {=IF(is_cat, IF(header_row_id=income_header_row, MATCH(income_min_row, $C:$C, 0), IF(header_row_id=expenses_header_row, MATCH(expenses_min_row, $C:$C, 0), IF(header_row_id=savings_header_row, MATCH(savings_min_row, $C:$C, 0), ""))), "")} | N36: {=IF(is_cat, IF(header_row_id=income_header_row, MATCH(income_max_row, $C:$C, 0), IF(header_row_id=expenses_header_row, MATCH(expenses_max_row, $C:$C, 0), IF(header_row_id=savings_header_row, MATCH(savings_max_row, $C:$C, 0), ""))), "")} | O36: =IF(is_cat, ADDRESS(sort_min_row, COLUMN(tracked)) & ":" & ADDRESS(sort_max_row, COLUMN(tracked)), "") | P36: =IF(is_cat, RANK(tracked, INDIRECT(tracked_range), 0), "") | Q36: =IF(is_cat, ADDRESS(sort_min_row, COLUMN(budget)) & ":" & ADDRESS(sort_max_row, COLUMN(budget)), "") | R36: =IF(is_cat, RANK(budget, INDIRECT(budget_range), 0), "") | S36: =IF(is_cat, _xlfn.NUMBERVALUE(tracked_rank & budget_rank), "") | T36: =IF(is_cat, ADDRESS(sort_min_row, COLUMN(comb_rank)) & ":" & ADDRESS(sort_max_row, COLUMN(comb_rank)), "") | U36: =IF(is_cat, RANK(comb_rank, INDIRECT(comb_rank_range), 1), "") | V36: =IF(is_cat, ADDRESS(sort_min_row, COLUMN(comb_rank_norm)) & ":" & ADDRESS(ROW(), COLUMN(comb_rank_norm)), "") | W36: =IF(is_cat, comb_rank_norm + COUNTIF(INDIRECT(comb_rank_norm_run_range), comb_rank_norm)-1, "") | X36: =IF(is_cat, header_row_id + comb_rank_unique, row_id) | Y36: =IF(is_empty, "", INDEX($J:$J, MATCH(row_id, $X:$X, 0))) | Z36: =IF(is_empty, "", IF(is_header, "Tracked", INDEX($K:$K, MATCH(row_id, $X:$X, 0)))) | AA36: =IF(is_empty, "", IF(is_header, "Budget", INDEX($L:$L, MATCH(row_id, $X:$X, 0)))) | AB36: =IF(is_empty, "", IF(is_header, "% Compl.", IFERROR(out_tracked / out_budget, "-"))) | AC36: =IF(is_empty, "", IF(is_header, "Remaining", IF(out_budget - out_tracked > 0, out_budget - out_tracked, 0))) | AD36: =IF(is_empty, "", IF(is_header, "Excess", IF(out_budget - out_tracked < 0, out_tracked - out_budget, 0))) | AI36: =Calculation!I41 | AJ36: =Calculation!J41 | AP36: =Calculation!M41 | AQ36: =Calculation!N41
C37: {=IF(C36=-1,-1, IF(C36<income_max_row,C36+1, IF(C36=income_max_row,income_total_row, IF(C36=income_total_row,"/1", IF(C36="/1",expenses_header_row, IF(C36<expenses_max_row,C36+1, IF(C36=expenses_max_row,expenses_total_row, IF(C36=expenses_total_row, "/2", IF(C36="/2", savings_header_row, IF(C36<savings_max_row, C36+1, IF(C36=savings_max_row, savings_total_row, -1)))))))))))} | D37: =IF(is_header, row_id, IF(NOT(is_empty), D36, -1)) | E37: {=OR(row_id=income_header_row, row_id=expenses_header_row, row_id=savings_header_row) * 1} | F37: =1 * NOT(OR(is_header, is_total, is_empty)) | G37: {=OR(row_id=income_total_row, row_id=expenses_total_row, row_id=savings_total_row) * 1} | H37: =OR(row_id="/1", row_id="/2", row_id=-1)*1 | I37: {=IFERROR(INDEX('Budget Planning'!$C:$C, header_row_id), "")} | J37: {=IFERROR(INDEX('Budget Planning'!$C:$C, row_id), "")} | K37: {=IF(OR(is_header, is_empty), "", IF(is_total, IF(selected_period="Total Year", SUM(tracking[Amount] * (tracking[Type]=type) * (YEAR(tracking[Effective Date])=selected_year)), SUM(tracking[Amount] * (tracking[Type]=type) * (YEAR(tracking[Effective Date])=selected_year) * (MONTH(tracking[Effective Date])=selected_period))), IF(selected_period="Total Year", SUM(tracking[Amount] * (tracking[Type]=type) * (tracking[Category]=item) * (YEAR(tracking[Effective Date])=selected_year)), SUM(tracking[Amount] * (tracking[Type]=type) * (tracking[Category]=item) * (YEAR(tracking[Effective Date])=selected_year) * (MONTH(tracking[Effective Date])=selected_period)))))} | L37: {=IF(OR(is_header, is_empty), "", INDEX('Budget Planning'!$E:$EM, row_id, MATCH(IF(selected_period="Total Year", selected_year, DATE(selected_year, selected_period, 1)), 'Budget Planning'!$E$9:$EM$9, 0)))} | M37: {=IF(is_cat, IF(header_row_id=income_header_row, MATCH(income_min_row, $C:$C, 0), IF(header_row_id=expenses_header_row, MATCH(expenses_min_row, $C:$C, 0), IF(header_row_id=savings_header_row, MATCH(savings_min_row, $C:$C, 0), ""))), "")} | N37: {=IF(is_cat, IF(header_row_id=income_header_row, MATCH(income_max_row, $C:$C, 0), IF(header_row_id=expenses_header_row, MATCH(expenses_max_row, $C:$C, 0), IF(header_row_id=savings_header_row, MATCH(savings_max_row, $C:$C, 0), ""))), "")} | O37: =IF(is_cat, ADDRESS(sort_min_row, COLUMN(tracked)) & ":" & ADDRESS(sort_max_row, COLUMN(tracked)), "") | P37: =IF(is_cat, RANK(tracked, INDIRECT(tracked_range), 0), "") | Q37: =IF(is_cat, ADDRESS(sort_min_row, COLUMN(budget)) & ":" & ADDRESS(sort_max_row, COLUMN(budget)), "") | R37: =IF(is_cat, RANK(budget, INDIRECT(budget_range), 0), "") | S37: =IF(is_cat, _xlfn.NUMBERVALUE(tracked_rank & budget_rank), "") | T37: =IF(is_cat, ADDRESS(sort_min_row, COLUMN(comb_rank)) & ":" & ADDRESS(sort_max_row, COLUMN(comb_rank)), "") | U37: =IF(is_cat, RANK(comb_rank, INDIRECT(comb_rank_range), 1), "") | V37: =IF(is_cat, ADDRESS(sort_min_row, COLUMN(comb_rank_norm)) & ":" & ADDRESS(ROW(), COLUMN(comb_rank_norm)), "") | W37: =IF(is_cat, comb_rank_norm + COUNTIF(INDIRECT(comb_rank_norm_run_range), comb_rank_norm)-1, "") | X37: =IF(is_cat, header_row_id + comb_rank_unique, row_id) | Y37: =IF(is_empty, "", INDEX($J:$J, MATCH(row_id, $X:$X, 0))) | Z37: =IF(is_empty, "", IF(is_header, "Tracked", INDEX($K:$K, MATCH(row_id, $X:$X, 0)))) | AA37: =IF(is_empty, "", IF(is_header, "Budget", INDEX($L:$L, MATCH(row_id, $X:$X, 0)))) | AB37: =IF(is_empty, "", IF(is_header, "% Compl.", IFERROR(out_tracked / out_budget, "-"))) | AC37: =IF(is_empty, "", IF(is_header, "Remaining", IF(out_budget - out_tracked > 0, out_budget - out_tracked, 0))) | AD37: =IF(is_empty, "", IF(is_header, "Excess", IF(out_budget - out_tracked < 0, out_tracked - out_budget, 0)))
C38: {=IF(C37=-1,-1, IF(C37<income_max_row,C37+1, IF(C37=income_max_row,income_total_row, IF(C37=income_total_row,"/1", IF(C37="/1",expenses_header_row, IF(C37<expenses_max_row,C37+1, IF(C37=expenses_max_row,expenses_total_row, IF(C37=expenses_total_row, "/2", IF(C37="/2", savings_header_row, IF(C37<savings_max_row, C37+1, IF(C37=savings_max_row, savings_total_row, -1)))))))))))} | D38: =IF(is_header, row_id, IF(NOT(is_empty), D37, -1)) | E38: {=OR(row_id=income_header_row, row_id=expenses_header_row, row_id=savings_header_row) * 1} | F38: =1 * NOT(OR(is_header, is_total, is_empty)) | G38: {=OR(row_id=income_total_row, row_id=expenses_total_row, row_id=savings_total_row) * 1} | H38: =OR(row_id="/1", row_id="/2", row_id=-1)*1 | I38: {=IFERROR(INDEX('Budget Planning'!$C:$C, header_row_id), "")} | J38: {=IFERROR(INDEX('Budget Planning'!$C:$C, row_id), "")} | K38: {=IF(OR(is_header, is_empty), "", IF(is_total, IF(selected_period="Total Year", SUM(tracking[Amount] * (tracking[Type]=type) * (YEAR(tracking[Effective Date])=selected_year)), SUM(tracking[Amount] * (tracking[Type]=type) * (YEAR(tracking[Effective Date])=selected_year) * (MONTH(tracking[Effective Date])=selected_period))), IF(selected_period="Total Year", SUM(tracking[Amount] * (tracking[Type]=type) * (tracking[Category]=item) * (YEAR(tracking[Effective Date])=selected_year)), SUM(tracking[Amount] * (tracking[Type]=type) * (tracking[Category]=item) * (YEAR(tracking[Effective Date])=selected_year) * (MONTH(tracking[Effective Date])=selected_period)))))} | L38: {=IF(OR(is_header, is_empty), "", INDEX('Budget Planning'!$E:$EM, row_id, MATCH(IF(selected_period="Total Year", selected_year, DATE(selected_year, selected_period, 1)), 'Budget Planning'!$E$9:$EM$9, 0)))} | M38: {=IF(is_cat, IF(header_row_id=income_header_row, MATCH(income_min_row, $C:$C, 0), IF(header_row_id=expenses_header_row, MATCH(expenses_min_row, $C:$C, 0), IF(header_row_id=savings_header_row, MATCH(savings_min_row, $C:$C, 0), ""))), "")} | N38: {=IF(is_cat, IF(header_row_id=income_header_row, MATCH(income_max_row, $C:$C, 0), IF(header_row_id=expenses_header_row, MATCH(expenses_max_row, $C:$C, 0), IF(header_row_id=savings_header_row, MATCH(savings_max_row, $C:$C, 0), ""))), "")} | O38: =IF(is_cat, ADDRESS(sort_min_row, COLUMN(tracked)) & ":" & ADDRESS(sort_max_row, COLUMN(tracked)), "") | P38: =IF(is_cat, RANK(tracked, INDIRECT(tracked_range), 0), "") | Q38: =IF(is_cat, ADDRESS(sort_min_row, COLUMN(budget)) & ":" & ADDRESS(sort_max_row, COLUMN(budget)), "") | R38: =IF(is_cat, RANK(budget, INDIRECT(budget_range), 0), "") | S38: =IF(is_cat, _xlfn.NUMBERVALUE(tracked_rank & budget_rank), "") | T38: =IF(is_cat, ADDRESS(sort_min_row, COLUMN(comb_rank)) & ":" & ADDRESS(sort_max_row, COLUMN(comb_rank)), "") | U38: =IF(is_cat, RANK(comb_rank, INDIRECT(comb_rank_range), 1), "") | V38: =IF(is_cat, ADDRESS(sort_min_row, COLUMN(comb_rank_norm)) & ":" & ADDRESS(ROW(), COLUMN(comb_rank_norm)), "") | W38: =IF(is_cat, comb_rank_norm + COUNTIF(INDIRECT(comb_rank_norm_run_range), comb_rank_norm)-1, "") | X38: =IF(is_cat, header_row_id + comb_rank_unique, row_id) | Y38: =IF(is_empty, "", INDEX($J:$J, MATCH(row_id, $X:$X, 0))) | Z38: =IF(is_empty, "", IF(is_header, "Tracked", INDEX($K:$K, MATCH(row_id, $X:$X, 0)))) | AA38: =IF(is_empty, "", IF(is_header, "Budget", INDEX($L:$L, MATCH(row_id, $X:$X, 0)))) | AB38: =IF(is_empty, "", IF(is_header, "% Compl.", IFERROR(out_tracked / out_budget, "-"))) | AC38: =IF(is_empty, "", IF(is_header, "Remaining", IF(out_budget - out_tracked > 0, out_budget - out_tracked, 0))) | AD38: =IF(is_empty, "", IF(is_header, "Excess", IF(out_budget - out_tracked < 0, out_tracked - out_budget, 0)))
C39: {=IF(C38=-1,-1, IF(C38<income_max_row,C38+1, IF(C38=income_max_row,income_total_row, IF(C38=income_total_row,"/1", IF(C38="/1",expenses_header_row, IF(C38<expenses_max_row,C38+1, IF(C38=expenses_max_row,expenses_total_row, IF(C38=expenses_total_row, "/2", IF(C38="/2", savings_header_row, IF(C38<savings_max_row, C38+1, IF(C38=savings_max_row, savings_total_row, -1)))))))))))} | D39: =IF(is_header, row_id, IF(NOT(is_empty), D38, -1)) | E39: {=OR(row_id=income_header_row, row_id=expenses_header_row, row_id=savings_header_row) * 1} | F39: =1 * NOT(OR(is_header, is_total, is_empty)) | G39: {=OR(row_id=income_total_row, row_id=expenses_total_row, row_id=savings_total_row) * 1} | H39: =OR(row_id="/1", row_id="/2", row_id=-1)*1 | I39: {=IFERROR(INDEX('Budget Planning'!$C:$C, header_row_id), "")} | J39: {=IFERROR(INDEX('Budget Planning'!$C:$C, row_id), "")} | K39: {=IF(OR(is_header, is_empty), "", IF(is_total, IF(selected_period="Total Year", SUM(tracking[Amount] * (tracking[Type]=type) * (YEAR(tracking[Effective Date])=selected_year)), SUM(tracking[Amount] * (tracking[Type]=type) * (YEAR(tracking[Effective Date])=selected_year) * (MONTH(tracking[Effective Date])=selected_period))), IF(selected_period="Total Year", SUM(tracking[Amount] * (tracking[Type]=type) * (tracking[Category]=item) * (YEAR(tracking[Effective Date])=selected_year)), SUM(tracking[Amount] * (tracking[Type]=type) * (tracking[Category]=item) * (YEAR(tracking[Effective Date])=selected_year) * (MONTH(tracking[Effective Date])=selected_period)))))} | L39: {=IF(OR(is_header, is_empty), "", INDEX('Budget Planning'!$E:$EM, row_id, MATCH(IF(selected_period="Total Year", selected_year, DATE(selected_year, selected_period, 1)), 'Budget Planning'!$E$9:$EM$9, 0)))} | M39: {=IF(is_cat, IF(header_row_id=income_header_row, MATCH(income_min_row, $C:$C, 0), IF(header_row_id=expenses_header_row, MATCH(expenses_min_row, $C:$C, 0), IF(header_row_id=savings_header_row, MATCH(savings_min_row, $C:$C, 0), ""))), "")} | N39: {=IF(is_cat, IF(header_row_id=income_header_row, MATCH(income_max_row, $C:$C, 0), IF(header_row_id=expenses_header_row, MATCH(expenses_max_row, $C:$C, 0), IF(header_row_id=savings_header_row, MATCH(savings_max_row, $C:$C, 0), ""))), "")} | O39: =IF(is_cat, ADDRESS(sort_min_row, COLUMN(tracked)) & ":" & ADDRESS(sort_max_row, COLUMN(tracked)), "") | P39: =IF(is_cat, RANK(tracked, INDIRECT(tracked_range), 0), "") | Q39: =IF(is_cat, ADDRESS(sort_min_row, COLUMN(budget)) & ":" & ADDRESS(sort_max_row, COLUMN(budget)), "") | R39: =IF(is_cat, RANK(budget, INDIRECT(budget_range), 0), "") | S39: =IF(is_cat, _xlfn.NUMBERVALUE(tracked_rank & budget_rank), "") | T39: =IF(is_cat, ADDRESS(sort_min_row, COLUMN(comb_rank)) & ":" & ADDRESS(sort_max_row, COLUMN(comb_rank)), "") | U39: =IF(is_cat, RANK(comb_rank, INDIRECT(comb_rank_range), 1), "") | V39: =IF(is_cat, ADDRESS(sort_min_row, COLUMN(comb_rank_norm)) & ":" & ADDRESS(ROW(), COLUMN(comb_rank_norm)), "") | W39: =IF(is_cat, comb_rank_norm + COUNTIF(INDIRECT(comb_rank_norm_run_range), comb_rank_norm)-1, "") | X39: =IF(is_cat, header_row_id + comb_rank_unique, row_id) | Y39: =IF(is_empty, "", INDEX($J:$J, MATCH(row_id, $X:$X, 0))) | Z39: =IF(is_empty, "", IF(is_header, "Tracked", INDEX($K:$K, MATCH(row_id, $X:$X, 0)))) | AA39: =IF(is_empty, "", IF(is_header, "Budget", INDEX($L:$L, MATCH(row_id, $X:$X, 0)))) | AB39: =IF(is_empty, "", IF(is_header, "% Compl.", IFERROR(out_tracked / out_budget, "-"))) | AC39: =IF(is_empty, "", IF(is_header, "Remaining", IF(out_budget - out_tracked > 0, out_budget - out_tracked, 0))) | AD39: =IF(is_empty, "", IF(is_header, "Excess", IF(out_budget - out_tracked < 0, out_tracked - out_budget, 0)))
C40: {=IF(C39=-1,-1, IF(C39<income_max_row,C39+1, IF(C39=income_max_row,income_total_row, IF(C39=income_total_row,"/1", IF(C39="/1",expenses_header_row, IF(C39<expenses_max_row,C39+1, IF(C39=expenses_max_row,expenses_total_row, IF(C39=expenses_total_row, "/2", IF(C39="/2", savings_header_row, IF(C39<savings_max_row, C39+1, IF(C39=savings_max_row, savings_total_row, -1)))))))))))} | D40: =IF(is_header, row_id, IF(NOT(is_empty), D39, -1)) | E40: {=OR(row_id=income_header_row, row_id=expenses_header_row, row_id=savings_header_row) * 1} | F40: =1 * NOT(OR(is_header, is_total, is_empty)) | G40: {=OR(row_id=income_total_row, row_id=expenses_total_row, row_id=savings_total_row) * 1} | H40: =OR(row_id="/1", row_id="/2", row_id=-1)*1 | I40: {=IFERROR(INDEX('Budget Planning'!$C:$C, header_row_id), "")} | J40: {=IFERROR(INDEX('Budget Planning'!$C:$C, row_id), "")} | K40: {=IF(OR(is_header, is_empty), "", IF(is_total, IF(selected_period="Total Year", SUM(tracking[Amount] * (tracking[Type]=type) * (YEAR(tracking[Effective Date])=selected_year)), SUM(tracking[Amount] * (tracking[Type]=type) * (YEAR(tracking[Effective Date])=selected_year) * (MONTH(tracking[Effective Date])=selected_period))), IF(selected_period="Total Year", SUM(tracking[Amount] * (tracking[Type]=type) * (tracking[Category]=item) * (YEAR(tracking[Effective Date])=selected_year)), SUM(tracking[Amount] * (tracking[Type]=type) * (tracking[Category]=item) * (YEAR(tracking[Effective Date])=selected_year) * (MONTH(tracking[Effective Date])=selected_period)))))} | L40: {=IF(OR(is_header, is_empty), "", INDEX('Budget Planning'!$E:$EM, row_id, MATCH(IF(selected_period="Total Year", selected_year, DATE(selected_year, selected_period, 1)), 'Budget Planning'!$E$9:$EM$9, 0)))} | M40: {=IF(is_cat, IF(header_row_id=income_header_row, MATCH(income_min_row, $C:$C, 0), IF(header_row_id=expenses_header_row, MATCH(expenses_min_row, $C:$C, 0), IF(header_row_id=savings_header_row, MATCH(savings_min_row, $C:$C, 0), ""))), "")} | N40: {=IF(is_cat, IF(header_row_id=income_header_row, MATCH(income_max_row, $C:$C, 0), IF(header_row_id=expenses_header_row, MATCH(expenses_max_row, $C:$C, 0), IF(header_row_id=savings_header_row, MATCH(savings_max_row, $C:$C, 0), ""))), "")} | O40: =IF(is_cat, ADDRESS(sort_min_row, COLUMN(tracked)) & ":" & ADDRESS(sort_max_row, COLUMN(tracked)), "") | P40: =IF(is_cat, RANK(tracked, INDIRECT(tracked_range), 0), "") | Q40: =IF(is_cat, ADDRESS(sort_min_row, COLUMN(budget)) & ":" & ADDRESS(sort_max_row, COLUMN(budget)), "") | R40: =IF(is_cat, RANK(budget, INDIRECT(budget_range), 0), "") | S40: =IF(is_cat, _xlfn.NUMBERVALUE(tracked_rank & budget_rank), "") | T40: =IF(is_cat, ADDRESS(sort_min_row, COLUMN(comb_rank)) & ":" & ADDRESS(sort_max_row, COLUMN(comb_rank)), "") | U40: =IF(is_cat, RANK(comb_rank, INDIRECT(comb_rank_range), 1), "") | V40: =IF(is_cat, ADDRESS(sort_min_row, COLUMN(comb_rank_norm)) & ":" & ADDRESS(ROW(), COLUMN(comb_rank_norm)), "") | W40: =IF(is_cat, comb_rank_norm + COUNTIF(INDIRECT(comb_rank_norm_run_range), comb_rank_norm)-1, "") | X40: =IF(is_cat, header_row_id + comb_rank_unique, row_id) | Y40: =IF(is_empty, "", INDEX($J:$J, MATCH(row_id, $X:$X, 0))) | Z40: =IF(is_empty, "", IF(is_header, "Tracked", INDEX($K:$K, MATCH(row_id, $X:$X, 0)))) | AA40: =IF(is_empty, "", IF(is_header, "Budget", INDEX($L:$L, MATCH(row_id, $X:$X, 0)))) | AB40: =IF(is_empty, "", IF(is_header, "% Compl.", IFERROR(out_tracked / out_budget, "-"))) | AC40: =IF(is_empty, "", IF(is_header, "Remaining", IF(out_budget - out_tracked > 0, out_budget - out_tracked, 0))) | AD40: =IF(is_empty, "", IF(is_header, "Excess", IF(out_budget - out_tracked < 0, out_tracked - out_budget, 0)))
C41: {=IF(C40=-1,-1, IF(C40<income_max_row,C40+1, IF(C40=income_max_row,income_total_row, IF(C40=income_total_row,"/1", IF(C40="/1",expenses_header_row, IF(C40<expenses_max_row,C40+1, IF(C40=expenses_max_row,expenses_total_row, IF(C40=expenses_total_row, "/2", IF(C40="/2", savings_header_row, IF(C40<savings_max_row, C40+1, IF(C40=savings_max_row, savings_total_row, -1)))))))))))} | D41: =IF(is_header, row_id, IF(NOT(is_empty), D40, -1)) | E41: {=OR(row_id=income_header_row, row_id=expenses_header_row, row_id=savings_header_row) * 1} | F41: =1 * NOT(OR(is_header, is_total, is_empty)) | G41: {=OR(row_id=income_total_row, row_id=expenses_total_row, row_id=savings_total_row) * 1} | H41: =OR(row_id="/1", row_id="/2", row_id=-1)*1 | I41: {=IFERROR(INDEX('Budget Planning'!$C:$C, header_row_id), "")} | J41: {=IFERROR(INDEX('Budget Planning'!$C:$C, row_id), "")} | K41: {=IF(OR(is_header, is_empty), "", IF(is_total, IF(selected_period="Total Year", SUM(tracking[Amount] * (tracking[Type]=type) * (YEAR(tracking[Effective Date])=selected_year)), SUM(tracking[Amount] * (tracking[Type]=type) * (YEAR(tracking[Effective Date])=selected_year) * (MONTH(tracking[Effective Date])=selected_period))), IF(selected_period="Total Year", SUM(tracking[Amount] * (tracking[Type]=type) * (tracking[Category]=item) * (YEAR(tracking[Effective Date])=selected_year)), SUM(tracking[Amount] * (tracking[Type]=type) * (tracking[Category]=item) * (YEAR(tracking[Effective Date])=selected_year) * (MONTH(tracking[Effective Date])=selected_period)))))} | L41: {=IF(OR(is_header, is_empty), "", INDEX('Budget Planning'!$E:$EM, row_id, MATCH(IF(selected_period="Total Year", selected_year, DATE(selected_year, selected_period, 1)), 'Budget Planning'!$E$9:$EM$9, 0)))} | M41: {=IF(is_cat, IF(header_row_id=income_header_row, MATCH(income_min_row, $C:$C, 0), IF(header_row_id=expenses_header_row, MATCH(expenses_min_row, $C:$C, 0), IF(header_row_id=savings_header_row, MATCH(savings_min_row, $C:$C, 0), ""))), "")} | N41: {=IF(is_cat, IF(header_row_id=income_header_row, MATCH(income_max_row, $C:$C, 0), IF(header_row_id=expenses_header_row, MATCH(expenses_max_row, $C:$C, 0), IF(header_row_id=savings_header_row, MATCH(savings_max_row, $C:$C, 0), ""))), "")} | O41: =IF(is_cat, ADDRESS(sort_min_row, COLUMN(tracked)) & ":" & ADDRESS(sort_max_row, COLUMN(tracked)), "") | P41: =IF(is_cat, RANK(tracked, INDIRECT(tracked_range), 0), "") | Q41: =IF(is_cat, ADDRESS(sort_min_row, COLUMN(budget)) & ":" & ADDRESS(sort_max_row, COLUMN(budget)), "") | R41: =IF(is_cat, RANK(budget, INDIRECT(budget_range), 0), "") | S41: =IF(is_cat, _xlfn.NUMBERVALUE(tracked_rank & budget_rank), "") | T41: =IF(is_cat, ADDRESS(sort_min_row, COLUMN(comb_rank)) & ":" & ADDRESS(sort_max_row, COLUMN(comb_rank)), "") | U41: =IF(is_cat, RANK(comb_rank, INDIRECT(comb_rank_range), 1), "") | V41: =IF(is_cat, ADDRESS(sort_min_row, COLUMN(comb_rank_norm)) & ":" & ADDRESS(ROW(), COLUMN(comb_rank_norm)), "") | W41: =IF(is_cat, comb_rank_norm + COUNTIF(INDIRECT(comb_rank_norm_run_range), comb_rank_norm)-1, "") | X41: =IF(is_cat, header_row_id + comb_rank_unique, row_id) | Y41: =IF(is_empty, "", INDEX($J:$J, MATCH(row_id, $X:$X, 0))) | Z41: =IF(is_empty, "", IF(is_header, "Tracked", INDEX($K:$K, MATCH(row_id, $X:$X, 0)))) | AA41: =IF(is_empty, "", IF(is_header, "Budget", INDEX($L:$L, MATCH(row_id, $X:$X, 0)))) | AB41: =IF(is_empty, "", IF(is_header, "% Compl.", IFERROR(out_tracked / out_budget, "-"))) | AC41: =IF(is_empty, "", IF(is_header, "Remaining", IF(out_budget - out_tracked > 0, out_budget - out_tracked, 0))) | AD41: =IF(is_empty, "", IF(is_header, "Excess", IF(out_budget - out_tracked < 0, out_tracked - out_budget, 0)))
C42: {=IF(C41=-1,-1, IF(C41<income_max_row,C41+1, IF(C41=income_max_row,income_total_row, IF(C41=income_total_row,"/1", IF(C41="/1",expenses_header_row, IF(C41<expenses_max_row,C41+1, IF(C41=expenses_max_row,expenses_total_row, IF(C41=expenses_total_row, "/2", IF(C41="/2", savings_header_row, IF(C41<savings_max_row, C41+1, IF(C41=savings_max_row, savings_total_row, -1)))))))))))} | D42: =IF(is_header, row_id, IF(NOT(is_empty), D41, -1)) | E42: {=OR(row_id=income_header_row, row_id=expenses_header_row, row_id=savings_header_row) * 1} | F42: =1 * NOT(OR(is_header, is_total, is_empty)) | G42: {=OR(row_id=income_total_row, row_id=expenses_total_row, row_id=savings_total_row) * 1} | H42: =OR(row_id="/1", row_id="/2", row_id=-1)*1 | I42: {=IFERROR(INDEX('Budget Planning'!$C:$C, header_row_id), "")} | J42: {=IFERROR(INDEX('Budget Planning'!$C:$C, row_id), "")} | K42: {=IF(OR(is_header, is_empty), "", IF(is_total, IF(selected_period="Total Year", SUM(tracking[Amount] * (tracking[Type]=type) * (YEAR(tracking[Effective Date])=selected_year)), SUM(tracking[Amount] * (tracking[Type]=type) * (YEAR(tracking[Effective Date])=selected_year) * (MONTH(tracking[Effective Date])=selected_period))), IF(selected_period="Total Year", SUM(tracking[Amount] * (tracking[Type]=type) * (tracking[Category]=item) * (YEAR(tracking[Effective Date])=selected_year)), SUM(tracking[Amount] * (tracking[Type]=type) * (tracking[Category]=item) * (YEAR(tracking[Effective Date])=selected_year) * (MONTH(tracking[Effective Date])=selected_period)))))} | L42: {=IF(OR(is_header, is_empty), "", INDEX('Budget Planning'!$E:$EM, row_id, MATCH(IF(selected_period="Total Year", selected_year, DATE(selected_year, selected_period, 1)), 'Budget Planning'!$E$9:$EM$9, 0)))} | M42: {=IF(is_cat, IF(header_row_id=income_header_row, MATCH(income_min_row, $C:$C, 0), IF(header_row_id=expenses_header_row, MATCH(expenses_min_row, $C:$C, 0), IF(header_row_id=savings_header_row, MATCH(savings_min_row, $C:$C, 0), ""))), "")} | N42: {=IF(is_cat, IF(header_row_id=income_header_row, MATCH(income_max_row, $C:$C, 0), IF(header_row_id=expenses_header_row, MATCH(expenses_max_row, $C:$C, 0), IF(header_row_id=savings_header_row, MATCH(savings_max_row, $C:$C, 0), ""))), "")} | O42: =IF(is_cat, ADDRESS(sort_min_row, COLUMN(tracked)) & ":" & ADDRESS(sort_max_row, COLUMN(tracked)), "") | P42: =IF(is_cat, RANK(tracked, INDIRECT(tracked_range), 0), "") | Q42: =IF(is_cat, ADDRESS(sort_min_row, COLUMN(budget)) & ":" & ADDRESS(sort_max_row, COLUMN(budget)), "") | R42: =IF(is_cat, RANK(budget, INDIRECT(budget_range), 0), "") | S42: =IF(is_cat, _xlfn.NUMBERVALUE(tracked_rank & budget_rank), "") | T42: =IF(is_cat, ADDRESS(sort_min_row, COLUMN(comb_rank)) & ":" & ADDRESS(sort_max_row, COLUMN(comb_rank)), "") | U42: =IF(is_cat, RANK(comb_rank, INDIRECT(comb_rank_range), 1), "") | V42: =IF(is_cat, ADDRESS(sort_min_row, COLUMN(comb_rank_norm)) & ":" & ADDRESS(ROW(), COLUMN(comb_rank_norm)), "") | W42: =IF(is_cat, comb_rank_norm + COUNTIF(INDIRECT(comb_rank_norm_run_range), comb_rank_norm)-1, "") | X42: =IF(is_cat, header_row_id + comb_rank_unique, row_id) | Y42: =IF(is_empty, "", INDEX($J:$J, MATCH(row_id, $X:$X, 0))) | Z42: =IF(is_empty, "", IF(is_header, "Tracked", INDEX($K:$K, MATCH(row_id, $X:$X, 0)))) | AA42: =IF(is_empty, "", IF(is_header, "Budget", INDEX($L:$L, MATCH(row_id, $X:$X, 0)))) | AB42: =IF(is_empty, "", IF(is_header, "% Compl.", IFERROR(out_tracked / out_budget, "-"))) | AC42: =IF(is_empty, "", IF(is_header, "Remaining", IF(out_budget - out_tracked > 0, out_budget - out_tracked, 0))) | AD42: =IF(is_empty, "", IF(is_header, "Excess", IF(out_budget - out_tracked < 0, out_tracked - out_budget, 0)))
C43: {=IF(C42=-1,-1, IF(C42<income_max_row,C42+1, IF(C42=income_max_row,income_total_row, IF(C42=income_total_row,"/1", IF(C42="/1",expenses_header_row, IF(C42<expenses_max_row,C42+1, IF(C42=expenses_max_row,expenses_total_row, IF(C42=expenses_total_row, "/2", IF(C42="/2", savings_header_row, IF(C42<savings_max_row, C42+1, IF(C42=savings_max_row, savings_total_row, -1)))))))))))} | D43: =IF(is_header, row_id, IF(NOT(is_empty), D42, -1)) | E43: {=OR(row_id=income_header_row, row_id=expenses_header_row, row_id=savings_header_row) * 1} | F43: =1 * NOT(OR(is_header, is_total, is_empty)) | G43: {=OR(row_id=income_total_row, row_id=expenses_total_row, row_id=savings_total_row) * 1} | H43: =OR(row_id="/1", row_id="/2", row_id=-1)*1 | I43: {=IFERROR(INDEX('Budget Planning'!$C:$C, header_row_id), "")} | J43: {=IFERROR(INDEX('Budget Planning'!$C:$C, row_id), "")} | K43: {=IF(OR(is_header, is_empty), "", IF(is_total, IF(selected_period="Total Year", SUM(tracking[Amount] * (tracking[Type]=type) * (YEAR(tracking[Effective Date])=selected_year)), SUM(tracking[Amount] * (tracking[Type]=type) * (YEAR(tracking[Effective Date])=selected_year) * (MONTH(tracking[Effective Date])=selected_period))), IF(selected_period="Total Year", SUM(tracking[Amount] * (tracking[Type]=type) * (tracking[Category]=item) * (YEAR(tracking[Effective Date])=selected_year)), SUM(tracking[Amount] * (tracking[Type]=type) * (tracking[Category]=item) * (YEAR(tracking[Effective Date])=selected_year) * (MONTH(tracking[Effective Date])=selected_period)))))} | L43: {=IF(OR(is_header, is_empty), "", INDEX('Budget Planning'!$E:$EM, row_id, MATCH(IF(selected_period="Total Year", selected_year, DATE(selected_year, selected_period, 1)), 'Budget Planning'!$E$9:$EM$9, 0)))} | M43: {=IF(is_cat, IF(header_row_id=income_header_row, MATCH(income_min_row, $C:$C, 0), IF(header_row_id=expenses_header_row, MATCH(expenses_min_row, $C:$C, 0), IF(header_row_id=savings_header_row, MATCH(savings_min_row, $C:$C, 0), ""))), "")} | N43: {=IF(is_cat, IF(header_row_id=income_header_row, MATCH(income_max_row, $C:$C, 0), IF(header_row_id=expenses_header_row, MATCH(expenses_max_row, $C:$C, 0), IF(header_row_id=savings_header_row, MATCH(savings_max_row, $C:$C, 0), ""))), "")} | O43: =IF(is_cat, ADDRESS(sort_min_row, COLUMN(tracked)) & ":" & ADDRESS(sort_max_row, COLUMN(tracked)), "") | P43: =IF(is_cat, RANK(tracked, INDIRECT(tracked_range), 0), "") | Q43: =IF(is_cat, ADDRESS(sort_min_row, COLUMN(budget)) & ":" & ADDRESS(sort_max_row, COLUMN(budget)), "") | R43: =IF(is_cat, RANK(budget, INDIRECT(budget_range), 0), "") | S43: =IF(is_cat, _xlfn.NUMBERVALUE(tracked_rank & budget_rank), "") | T43: =IF(is_cat, ADDRESS(sort_min_row, COLUMN(comb_rank)) & ":" & ADDRESS(sort_max_row, COLUMN(comb_rank)), "") | U43: =IF(is_cat, RANK(comb_rank, INDIRECT(comb_rank_range), 1), "") | V43: =IF(is_cat, ADDRESS(sort_min_row, COLUMN(comb_rank_norm)) & ":" & ADDRESS(ROW(), COLUMN(comb_rank_norm)), "") | W43: =IF(is_cat, comb_rank_norm + COUNTIF(INDIRECT(comb_rank_norm_run_range), comb_rank_norm)-1, "") | X43: =IF(is_cat, header_row_id + comb_rank_unique, row_id) | Y43: =IF(is_empty, "", INDEX($J:$J, MATCH(row_id, $X:$X, 0))) | Z43: =IF(is_empty, "", IF(is_header, "Tracked", INDEX($K:$K, MATCH(row_id, $X:$X, 0)))) | AA43: =IF(is_empty, "", IF(is_header, "Budget", INDEX($L:$L, MATCH(row_id, $X:$X, 0)))) | AB43: =IF(is_empty, "", IF(is_header, "% Compl.", IFERROR(out_tracked / out_budget, "-"))) | AC43: =IF(is_empty, "", IF(is_header, "Remaining", IF(out_budget - out_tracked > 0, out_budget - out_tracked, 0))) | AD43: =IF(is_empty, "", IF(is_header, "Excess", IF(out_budget - out_tracked < 0, out_tracked - out_budget, 0)))
C44: {=IF(C43=-1,-1, IF(C43<income_max_row,C43+1, IF(C43=income_max_row,income_total_row, IF(C43=income_total_row,"/1", IF(C43="/1",expenses_header_row, IF(C43<expenses_max_row,C43+1, IF(C43=expenses_max_row,expenses_total_row, IF(C43=expenses_total_row, "/2", IF(C43="/2", savings_header_row, IF(C43<savings_max_row, C43+1, IF(C43=savings_max_row, savings_total_row, -1)))))))))))} | D44: =IF(is_header, row_id, IF(NOT(is_empty), D43, -1)) | E44: {=OR(row_id=income_header_row, row_id=expenses_header_row, row_id=savings_header_row) * 1} | F44: =1 * NOT(OR(is_header, is_total, is_empty)) | G44: {=OR(row_id=income_total_row, row_id=expenses_total_row, row_id=savings_total_row) * 1} | H44: =OR(row_id="/1", row_id="/2", row_id=-1)*1 | I44: {=IFERROR(INDEX('Budget Planning'!$C:$C, header_row_id), "")} | J44: {=IFERROR(INDEX('Budget Planning'!$C:$C, row_id), "")} | K44: {=IF(OR(is_header, is_empty), "", IF(is_total, IF(selected_period="Total Year", SUM(tracking[Amount] * (tracking[Type]=type) * (YEAR(tracking[Effective Date])=selected_year)), SUM(tracking[Amount] * (tracking[Type]=type) * (YEAR(tracking[Effective Date])=selected_year) * (MONTH(tracking[Effective Date])=selected_period))), IF(selected_period="Total Year", SUM(tracking[Amount] * (tracking[Type]=type) * (tracking[Category]=item) * (YEAR(tracking[Effective Date])=selected_year)), SUM(tracking[Amount] * (tracking[Type]=type) * (tracking[Category]=item) * (YEAR(tracking[Effective Date])=selected_year) * (MONTH(tracking[Effective Date])=selected_period)))))} | L44: {=IF(OR(is_header, is_empty), "", INDEX('Budget Planning'!$E:$EM, row_id, MATCH(IF(selected_period="Total Year", selected_year, DATE(selected_year, selected_period, 1)), 'Budget Planning'!$E$9:$EM$9, 0)))} | M44: {=IF(is_cat, IF(header_row_id=income_header_row, MATCH(income_min_row, $C:$C, 0), IF(header_row_id=expenses_header_row, MATCH(expenses_min_row, $C:$C, 0), IF(header_row_id=savings_header_row, MATCH(savings_min_row, $C:$C, 0), ""))), "")} | N44: {=IF(is_cat, IF(header_row_id=income_header_row, MATCH(income_max_row, $C:$C, 0), IF(header_row_id=expenses_header_row, MATCH(expenses_max_row, $C:$C, 0), IF(header_row_id=savings_header_row, MATCH(savings_max_row, $C:$C, 0), ""))), "")} | O44: =IF(is_cat, ADDRESS(sort_min_row, COLUMN(tracked)) & ":" & ADDRESS(sort_max_row, COLUMN(tracked)), "") | P44: =IF(is_cat, RANK(tracked, INDIRECT(tracked_range), 0), "") | Q44: =IF(is_cat, ADDRESS(sort_min_row, COLUMN(budget)) & ":" & ADDRESS(sort_max_row, COLUMN(budget)), "") | R44: =IF(is_cat, RANK(budget, INDIRECT(budget_range), 0), "") | S44: =IF(is_cat, _xlfn.NUMBERVALUE(tracked_rank & budget_rank), "") | T44: =IF(is_cat, ADDRESS(sort_min_row, COLUMN(comb_rank)) & ":" & ADDRESS(sort_max_row, COLUMN(comb_rank)), "") | U44: =IF(is_cat, RANK(comb_rank, INDIRECT(comb_rank_range), 1), "") | V44: =IF(is_cat, ADDRESS(sort_min_row, COLUMN(comb_rank_norm)) & ":" & ADDRESS(ROW(), COLUMN(comb_rank_norm)), "") | W44: =IF(is_cat, comb_rank_norm + COUNTIF(INDIRECT(comb_rank_norm_run_range), comb_rank_norm)-1, "") | X44: =IF(is_cat, header_row_id + comb_rank_unique, row_id) | Y44: =IF(is_empty, "", INDEX($J:$J, MATCH(row_id, $X:$X, 0))) | Z44: =IF(is_empty, "", IF(is_header, "Tracked", INDEX($K:$K, MATCH(row_id, $X:$X, 0)))) | AA44: =IF(is_empty, "", IF(is_header, "Budget", INDEX($L:$L, MATCH(row_id, $X:$X, 0)))) | AB44: =IF(is_empty, "", IF(is_header, "% Compl.", IFERROR(out_tracked / out_budget, "-"))) | AC44: =IF(is_empty, "", IF(is_header, "Remaining", IF(out_budget - out_tracked > 0, out_budget - out_tracked, 0))) | AD44: =IF(is_empty, "", IF(is_header, "Excess", IF(out_budget - out_tracked < 0, out_tracked - out_budget, 0)))
C45: {=IF(C44=-1,-1, IF(C44<income_max_row,C44+1, IF(C44=income_max_row,income_total_row, IF(C44=income_total_row,"/1", IF(C44="/1",expenses_header_row, IF(C44<expenses_max_row,C44+1, IF(C44=expenses_max_row,expenses_total_row, IF(C44=expenses_total_row, "/2", IF(C44="/2", savings_header_row, IF(C44<savings_max_row, C44+1, IF(C44=savings_max_row, savings_total_row, -1)))))))))))} | D45: =IF(is_header, row_id, IF(NOT(is_empty), D44, -1)) | E45: {=OR(row_id=income_header_row, row_id=expenses_header_row, row_id=savings_header_row) * 1} | F45: =1 * NOT(OR(is_header, is_total, is_empty)) | G45: {=OR(row_id=income_total_row, row_id=expenses_total_row, row_id=savings_total_row) * 1} | H45: =OR(row_id="/1", row_id="/2", row_id=-1)*1 | I45: {=IFERROR(INDEX('Budget Planning'!$C:$C, header_row_id), "")} | J45: {=IFERROR(INDEX('Budget Planning'!$C:$C, row_id), "")} | K45: {=IF(OR(is_header, is_empty), "", IF(is_total, IF(selected_period="Total Year", SUM(tracking[Amount] * (tracking[Type]=type) * (YEAR(tracking[Effective Date])=selected_year)), SUM(tracking[Amount] * (tracking[Type]=type) * (YEAR(tracking[Effective Date])=selected_year) * (MONTH(tracking[Effective Date])=selected_period))), IF(selected_period="Total Year", SUM(tracking[Amount] * (tracking[Type]=type) * (tracking[Category]=item) * (YEAR(tracking[Effective Date])=selected_year)), SUM(tracking[Amount] * (tracking[Type]=type) * (tracking[Category]=item) * (YEAR(tracking[Effective Date])=selected_year) * (MONTH(tracking[Effective Date])=selected_period)))))} | L45: {=IF(OR(is_header, is_empty), "", INDEX('Budget Planning'!$E:$EM, row_id, MATCH(IF(selected_period="Total Year", selected_year, DATE(selected_year, selected_period, 1)), 'Budget Planning'!$E$9:$EM$9, 0)))} | M45: {=IF(is_cat, IF(header_row_id=income_header_row, MATCH(income_min_row, $C:$C, 0), IF(header_row_id=expenses_header_row, MATCH(expenses_min_row, $C:$C, 0), IF(header_row_id=savings_header_row, MATCH(savings_min_row, $C:$C, 0), ""))), "")} | N45: {=IF(is_cat, IF(header_row_id=income_header_row, MATCH(income_max_row, $C:$C, 0), IF(header_row_id=expenses_header_row, MATCH(expenses_max_row, $C:$C, 0), IF(header_row_id=savings_header_row, MATCH(savings_max_row, $C:$C, 0), ""))), "")} | O45: =IF(is_cat, ADDRESS(sort_min_row, COLUMN(tracked)) & ":" & ADDRESS(sort_max_row, COLUMN(tracked)), "") | P45: =IF(is_cat, RANK(tracked, INDIRECT(tracked_range), 0), "") | Q45: =IF(is_cat, ADDRESS(sort_min_row, COLUMN(budget)) & ":" & ADDRESS(sort_max_row, COLUMN(budget)), "") | R45: =IF(is_cat, RANK(budget, INDIRECT(budget_range), 0), "") | S45: =IF(is_cat, _xlfn.NUMBERVALUE(tracked_rank & budget_rank), "") | T45: =IF(is_cat, ADDRESS(sort_min_row, COLUMN(comb_rank)) & ":" & ADDRESS(sort_max_row, COLUMN(comb_rank)), "") | U45: =IF(is_cat, RANK(comb_rank, INDIRECT(comb_rank_range), 1), "") | V45: =IF(is_cat, ADDRESS(sort_min_row, COLUMN(comb_rank_norm)) & ":" & ADDRESS(ROW(), COLUMN(comb_rank_norm)), "") | W45: =IF(is_cat, comb_rank_norm + COUNTIF(INDIRECT(comb_rank_norm_run_range), comb_rank_norm)-1, "") | X45: =IF(is_cat, header_row_id + comb_rank_unique, row_id) | Y45: =IF(is_empty, "", INDEX($J:$J, MATCH(row_id, $X:$X, 0))) | Z45: =IF(is_empty, "", IF(is_header, "Tracked", INDEX($K:$K, MATCH(row_id, $X:$X, 0)))) | AA45: =IF(is_empty, "", IF(is_header, "Budget", INDEX($L:$L, MATCH(row_id, $X:$X, 0)))) | AB45: =IF(is_empty, "", IF(is_header, "% Compl.", IFERROR(out_tracked / out_budget, "-"))) | AC45: =IF(is_empty, "", IF(is_header, "Remaining", IF(out_budget - out_tracked > 0, out_budget - out_tracked, 0))) | AD45: =IF(is_empty, "", IF(is_header, "Excess", IF(out_budget - out_tracked < 0, out_tracked - out_budget, 0)))
C46: {=IF(C45=-1,-1, IF(C45<income_max_row,C45+1, IF(C45=income_max_row,income_total_row, IF(C45=income_total_row,"/1", IF(C45="/1",expenses_header_row, IF(C45<expenses_max_row,C45+1, IF(C45=expenses_max_row,expenses_total_row, IF(C45=expenses_total_row, "/2", IF(C45="/2", savings_header_row, IF(C45<savings_max_row, C45+1, IF(C45=savings_max_row, savings_total_row, -1)))))))))))} | D46: =IF(is_header, row_id, IF(NOT(is_empty), D45, -1)) | E46: {=OR(row_id=income_header_row, row_id=expenses_header_row, row_id=savings_header_row) * 1} | F46: =1 * NOT(OR(is_header, is_total, is_empty)) | G46: {=OR(row_id=income_total_row, row_id=expenses_total_row, row_id=savings_total_row) * 1} | H46: =OR(row_id="/1", row_id="/2", row_id=-1)*1 | I46: {=IFERROR(INDEX('Budget Planning'!$C:$C, header_row_id), "")} | J46: {=IFERROR(INDEX('Budget Planning'!$C:$C, row_id), "")} | K46: {=IF(OR(is_header, is_empty), "", IF(is_total, IF(selected_period="Total Year", SUM(tracking[Amount] * (tracking[Type]=type) * (YEAR(tracking[Effective Date])=selected_year)), SUM(tracking[Amount] * (tracking[Type]=type) * (YEAR(tracking[Effective Date])=selected_year) * (MONTH(tracking[Effective Date])=selected_period))), IF(selected_period="Total Year", SUM(tracking[Amount] * (tracking[Type]=type) * (tracking[Category]=item) * (YEAR(tracking[Effective Date])=selected_year)), SUM(tracking[Amount] * (tracking[Type]=type) * (tracking[Category]=item) * (YEAR(tracking[Effective Date])=selected_year) * (MONTH(tracking[Effective Date])=selected_period)))))} | L46: {=IF(OR(is_header, is_empty), "", INDEX('Budget Planning'!$E:$EM, row_id, MATCH(IF(selected_period="Total Year", selected_year, DATE(selected_year, selected_period, 1)), 'Budget Planning'!$E$9:$EM$9, 0)))} | M46: {=IF(is_cat, IF(header_row_id=income_header_row, MATCH(income_min_row, $C:$C, 0), IF(header_row_id=expenses_header_row, MATCH(expenses_min_row, $C:$C, 0), IF(header_row_id=savings_header_row, MATCH(savings_min_row, $C:$C, 0), ""))), "")} | N46: {=IF(is_cat, IF(header_row_id=income_header_row, MATCH(income_max_row, $C:$C, 0), IF(header_row_id=expenses_header_row, MATCH(expenses_max_row, $C:$C, 0), IF(header_row_id=savings_header_row, MATCH(savings_max_row, $C:$C, 0), ""))), "")} | O46: =IF(is_cat, ADDRESS(sort_min_row, COLUMN(tracked)) & ":" & ADDRESS(sort_max_row, COLUMN(tracked)), "") | P46: =IF(is_cat, RANK(tracked, INDIRECT(tracked_range), 0), "") | Q46: =IF(is_cat, ADDRESS(sort_min_row, COLUMN(budget)) & ":" & ADDRESS(sort_max_row, COLUMN(budget)), "") | R46: =IF(is_cat, RANK(budget, INDIRECT(budget_range), 0), "") | S46: =IF(is_cat, _xlfn.NUMBERVALUE(tracked_rank & budget_rank), "") | T46: =IF(is_cat, ADDRESS(sort_min_row, COLUMN(comb_rank)) & ":" & ADDRESS(sort_max_row, COLUMN(comb_rank)), "") | U46: =IF(is_cat, RANK(comb_rank, INDIRECT(comb_rank_range), 1), "") | V46: =IF(is_cat, ADDRESS(sort_min_row, COLUMN(comb_rank_norm)) & ":" & ADDRESS(ROW(), COLUMN(comb_rank_norm)), "") | W46: =IF(is_cat, comb_rank_norm + COUNTIF(INDIRECT(comb_rank_norm_run_range), comb_rank_norm)-1, "") | X46: =IF(is_cat, header_row_id + comb_rank_unique, row_id) | Y46: =IF(is_empty, "", INDEX($J:$J, MATCH(row_id, $X:$X, 0))) | Z46: =IF(is_empty, "", IF(is_header, "Tracked", INDEX($K:$K, MATCH(row_id, $X:$X, 0)))) | AA46: =IF(is_empty, "", IF(is_header, "Budget", INDEX($L:$L, MATCH(row_id, $X:$X, 0)))) | AB46: =IF(is_empty, "", IF(is_header, "% Compl.", IFERROR(out_tracked / out_budget, "-"))) | AC46: =IF(is_empty, "", IF(is_header, "Remaining", IF(out_budget - out_tracked > 0, out_budget - out_tracked, 0))) | AD46: =IF(is_empty, "", IF(is_header, "Excess", IF(out_budget - out_tracked < 0, out_tracked - out_budget, 0)))
C47: {=IF(C46=-1,-1, IF(C46<income_max_row,C46+1, IF(C46=income_max_row,income_total_row, IF(C46=income_total_row,"/1", IF(C46="/1",expenses_header_row, IF(C46<expenses_max_row,C46+1, IF(C46=expenses_max_row,expenses_total_row, IF(C46=expenses_total_row, "/2", IF(C46="/2", savings_header_row, IF(C46<savings_max_row, C46+1, IF(C46=savings_max_row, savings_total_row, -1)))))))))))} | D47: =IF(is_header, row_id, IF(NOT(is_empty), D46, -1)) | E47: {=OR(row_id=income_header_row, row_id=expenses_header_row, row_id=savings_header_row) * 1} | F47: =1 * NOT(OR(is_header, is_total, is_empty)) | G47: {=OR(row_id=income_total_row, row_id=expenses_total_row, row_id=savings_total_row) * 1} | H47: =OR(row_id="/1", row_id="/2", row_id=-1)*1 | I47: {=IFERROR(INDEX('Budget Planning'!$C:$C, header_row_id), "")} | J47: {=IFERROR(INDEX('Budget Planning'!$C:$C, row_id), "")} | K47: {=IF(OR(is_header, is_empty), "", IF(is_total, IF(selected_period="Total Year", SUM(tracking[Amount] * (tracking[Type]=type) * (YEAR(tracking[Effective Date])=selected_year)), SUM(tracking[Amount] * (tracking[Type]=type) * (YEAR(tracking[Effective Date])=selected_year) * (MONTH(tracking[Effective Date])=selected_period))), IF(selected_period="Total Year", SUM(tracking[Amount] * (tracking[Type]=type) * (tracking[Category]=item) * (YEAR(tracking[Effective Date])=selected_year)), SUM(tracking[Amount] * (tracking[Type]=type) * (tracking[Category]=item) * (YEAR(tracking[Effective Date])=selected_year) * (MONTH(tracking[Effective Date])=selected_period)))))} | L47: {=IF(OR(is_header, is_empty), "", INDEX('Budget Planning'!$E:$EM, row_id, MATCH(IF(selected_period="Total Year", selected_year, DATE(selected_year, selected_period, 1)), 'Budget Planning'!$E$9:$EM$9, 0)))} | M47: {=IF(is_cat, IF(header_row_id=income_header_row, MATCH(income_min_row, $C:$C, 0), IF(header_row_id=expenses_header_row, MATCH(expenses_min_row, $C:$C, 0), IF(header_row_id=savings_header_row, MATCH(savings_min_row, $C:$C, 0), ""))), "")} | N47: {=IF(is_cat, IF(header_row_id=income_header_row, MATCH(income_max_row, $C:$C, 0), IF(header_row_id=expenses_header_row, MATCH(expenses_max_row, $C:$C, 0), IF(header_row_id=savings_header_row, MATCH(savings_max_row, $C:$C, 0), ""))), "")} | O47: =IF(is_cat, ADDRESS(sort_min_row, COLUMN(tracked)) & ":" & ADDRESS(sort_max_row, COLUMN(tracked)), "") | P47: =IF(is_cat, RANK(tracked, INDIRECT(tracked_range), 0), "") | Q47: =IF(is_cat, ADDRESS(sort_min_row, COLUMN(budget)) & ":" & ADDRESS(sort_max_row, COLUMN(budget)), "") | R47: =IF(is_cat, RANK(budget, INDIRECT(budget_range), 0), "") | S47: =IF(is_cat, _xlfn.NUMBERVALUE(tracked_rank & budget_rank), "") | T47: =IF(is_cat, ADDRESS(sort_min_row, COLUMN(comb_rank)) & ":" & ADDRESS(sort_max_row, COLUMN(comb_rank)), "") | U47: =IF(is_cat, RANK(comb_rank, INDIRECT(comb_rank_range), 1), "") | V47: =IF(is_cat, ADDRESS(sort_min_row, COLUMN(comb_rank_norm)) & ":" & ADDRESS(ROW(), COLUMN(comb_rank_norm)), "") | W47: =IF(is_cat, comb_rank_norm + COUNTIF(INDIRECT(comb_rank_norm_run_range), comb_rank_norm)-1, "") | X47: =IF(is_cat, header_row_id + comb_rank_unique, row_id) | Y47: =IF(is_empty, "", INDEX($J:$J, MATCH(row_id, $X:$X, 0))) | Z47: =IF(is_empty, "", IF(is_header, "Tracked", INDEX($K:$K, MATCH(row_id, $X:$X, 0)))) | AA47: =IF(is_empty, "", IF(is_header, "Budget", INDEX($L:$L, MATCH(row_id, $X:$X, 0)))) | AB47: =IF(is_empty, "", IF(is_header, "% Compl.", IFERROR(out_tracked / out_budget, "-"))) | AC47: =IF(is_empty, "", IF(is_header, "Remaining", IF(out_budget - out_tracked > 0, out_budget - out_tracked, 0))) | AD47: =IF(is_empty, "", IF(is_header, "Excess", IF(out_budget - out_tracked < 0, out_tracked - out_budget, 0)))
C48: {=IF(C47=-1,-1, IF(C47<income_max_row,C47+1, IF(C47=income_max_row,income_total_row, IF(C47=income_total_row,"/1", IF(C47="/1",expenses_header_row, IF(C47<expenses_max_row,C47+1, IF(C47=expenses_max_row,expenses_total_row, IF(C47=expenses_total_row, "/2", IF(C47="/2", savings_header_row, IF(C47<savings_max_row, C47+1, IF(C47=savings_max_row, savings_total_row, -1)))))))))))} | D48: =IF(is_header, row_id, IF(NOT(is_empty), D47, -1)) | E48: {=OR(row_id=income_header_row, row_id=expenses_header_row, row_id=savings_header_row) * 1} | F48: =1 * NOT(OR(is_header, is_total, is_empty)) | G48: {=OR(row_id=income_total_row, row_id=expenses_total_row, row_id=savings_total_row) * 1} | H48: =OR(row_id="/1", row_id="/2", row_id=-1)*1 | I48: {=IFERROR(INDEX('Budget Planning'!$C:$C, header_row_id), "")} | J48: {=IFERROR(INDEX('Budget Planning'!$C:$C, row_id), "")} | K48: {=IF(OR(is_header, is_empty), "", IF(is_total, IF(selected_period="Total Year", SUM(tracking[Amount] * (tracking[Type]=type) * (YEAR(tracking[Effective Date])=selected_year)), SUM(tracking[Amount] * (tracking[Type]=type) * (YEAR(tracking[Effective Date])=selected_year) * (MONTH(tracking[Effective Date])=selected_period))), IF(selected_period="Total Year", SUM(tracking[Amount] * (tracking[Type]=type) * (tracking[Category]=item) * (YEAR(tracking[Effective Date])=selected_year)), SUM(tracking[Amount] * (tracking[Type]=type) * (tracking[Category]=item) * (YEAR(tracking[Effective Date])=selected_year) * (MONTH(tracking[Effective Date])=selected_period)))))} | L48: {=IF(OR(is_header, is_empty), "", INDEX('Budget Planning'!$E:$EM, row_id, MATCH(IF(selected_period="Total Year", selected_year, DATE(selected_year, selected_period, 1)), 'Budget Planning'!$E$9:$EM$9, 0)))} | M48: {=IF(is_cat, IF(header_row_id=income_header_row, MATCH(income_min_row, $C:$C, 0), IF(header_row_id=expenses_header_row, MATCH(expenses_min_row, $C:$C, 0), IF(header_row_id=savings_header_row, MATCH(savings_min_row, $C:$C, 0), ""))), "")} | N48: {=IF(is_cat, IF(header_row_id=income_header_row, MATCH(income_max_row, $C:$C, 0), IF(header_row_id=expenses_header_row, MATCH(expenses_max_row, $C:$C, 0), IF(header_row_id=savings_header_row, MATCH(savings_max_row, $C:$C, 0), ""))), "")} | O48: =IF(is_cat, ADDRESS(sort_min_row, COLUMN(tracked)) & ":" & ADDRESS(sort_max_row, COLUMN(tracked)), "") | P48: =IF(is_cat, RANK(tracked, INDIRECT(tracked_range), 0), "") | Q48: =IF(is_cat, ADDRESS(sort_min_row, COLUMN(budget)) & ":" & ADDRESS(sort_max_row, COLUMN(budget)), "") | R48: =IF(is_cat, RANK(budget, INDIRECT(budget_range), 0), "") | S48: =IF(is_cat, _xlfn.NUMBERVALUE(tracked_rank & budget_rank), "") | T48: =IF(is_cat, ADDRESS(sort_min_row, COLUMN(comb_rank)) & ":" & ADDRESS(sort_max_row, COLUMN(comb_rank)), "") | U48: =IF(is_cat, RANK(comb_rank, INDIRECT(comb_rank_range), 1), "") | V48: =IF(is_cat, ADDRESS(sort_min_row, COLUMN(comb_rank_norm)) & ":" & ADDRESS(ROW(), COLUMN(comb_rank_norm)), "") | W48: =IF(is_cat, comb_rank_norm + COUNTIF(INDIRECT(comb_rank_norm_run_range), comb_rank_norm)-1, "") | X48: =IF(is_cat, header_row_id + comb_rank_unique, row_id) | Y48: =IF(is_empty, "", INDEX($J:$J, MATCH(row_id, $X:$X, 0))) | Z48: =IF(is_empty, "", IF(is_header, "Tracked", INDEX($K:$K, MATCH(row_id, $X:$X, 0)))) | AA48: =IF(is_empty, "", IF(is_header, "Budget", INDEX($L:$L, MATCH(row_id, $X:$X, 0)))) | AB48: =IF(is_empty, "", IF(is_header, "% Compl.", IFERROR(out_tracked / out_budget, "-"))) | AC48: =IF(is_empty, "", IF(is_header, "Remaining", IF(out_budget - out_tracked > 0, out_budget - out_tracked, 0))) | AD48: =IF(is_empty, "", IF(is_header, "Excess", IF(out_budget - out_tracked < 0, out_tracked - out_budget, 0)))
... C53: {=IF(C52=-1,-1, IF(C52<income_max_row,C52+1, IF(C52=income_max_row,income_total_row, IF(C52=income_total_row,"/1", IF(C52="/1",expenses_header_row, IF(C52<expenses_max_row,C52+1, IF(C52=expenses_max_row,expenses_total_row, IF(C52=expenses_total_row, "/2", IF(C52="/2", savings_header_row, IF(C52<savings_max_row, C52+1, IF(C52=savings_max_row, savings_total_row, -1)))))))))))} | D53: =IF(is_header, row_id, IF(NOT(is_empty), D52, -1)) | E53: {=OR(row_id=income_header_row, row_id=expenses_header_row, row_id=savings_header_row) * 1} | F53: =1 * NOT(OR(is_header, is_total, is_empty)) | G53: {=OR(row_id=income_total_row, row_id=expenses_total_row, row_id=savings_total_row) * 1} | H53: =OR(row_id="/1", row_id="/2", row_id=-1)*1 | I53: {=IFERROR(INDEX('Budget Planning'!$C:$C, header_row_id), "")} | J53: {=IFERROR(INDEX('Budget Planning'!$C:$C, row_id), "")} | K53: {=IF(OR(is_header, is_empty), "", IF(is_total, IF(selected_period="Total Year", SUM(tracking[Amount] * (tracking[Type]=type) * (YEAR(tracking[Effective Date])=selected_year)), SUM(tracking[Amount] * (tracking[Type]=type) * (YEAR(tracking[Effective Date])=selected_year) * (MONTH(tracking[Effective Date])=selected_period))), IF(selected_period="Total Year", SUM(tracking[Amount] * (tracking[Type]=type) * (tracking[Category]=item) * (YEAR(tracking[Effective Date])=selected_year)), SUM(tracking[Amount] * (tracking[Type]=type) * (tracking[Category]=item) * (YEAR(tracking[Effective Date])=selected_year) * (MONTH(tracking[Effective Date])=selected_period)))))} | L53: {=IF(OR(is_header, is_empty), "", INDEX('Budget Planning'!$E:$EM, row_id, MATCH(IF(selected_period="Total Year", selected_year, DATE(selected_year, selected_period, 1)), 'Budget Planning'!$E$9:$EM$9, 0)))} | M53: {=IF(is_cat, IF(header_row_id=income_header_row, MATCH(income_min_row, $C:$C, 0), IF(header_row_id=expenses_header_row, MATCH(expenses_min_row, $C:$C, 0), IF(header_row_id=savings_header_row, MATCH(savings_min_row, $C:$C, 0), ""))), "")} | N53: {=IF(is_cat, IF(header_row_id=income_header_row, MATCH(income_max_row, $C:$C, 0), IF(header_row_id=expenses_header_row, MATCH(expenses_max_row, $C:$C, 0), IF(header_row_id=savings_header_row, MATCH(savings_max_row, $C:$C, 0), ""))), "")} | O53: =IF(is_cat, ADDRESS(sort_min_row, COLUMN(tracked)) & ":" & ADDRESS(sort_max_row, COLUMN(tracked)), "") | P53: =IF(is_cat, RANK(tracked, INDIRECT(tracked_range), 0), "") | Q53: =IF(is_cat, ADDRESS(sort_min_row, COLUMN(budget)) & ":" & ADDRESS(sort_max_row, COLUMN(budget)), "") | R53: =IF(is_cat, RANK(budget, INDIRECT(budget_range), 0), "") | S53: =IF(is_cat, _xlfn.NUMBERVALUE(tracked_rank & budget_rank), "") | T53: =IF(is_cat, ADDRESS(sort_min_row, COLUMN(comb_rank)) & ":" & ADDRESS(sort_max_row, COLUMN(comb_rank)), "") | U53: =IF(is_cat, RANK(comb_rank, INDIRECT(comb_rank_range), 1), "") | V53: =IF(is_cat, ADDRESS(sort_min_row, COLUMN(comb_rank_norm)) & ":" & ADDRESS(ROW(), COLUMN(comb_rank_norm)), "") | W53: =IF(is_cat, comb_rank_norm + COUNTIF(INDIRECT(comb_rank_norm_run_range), comb_rank_norm)-1, "") | X53: =IF(is_cat, header_row_id + comb_rank_unique, row_id) | Y53: =IF(is_empty, "", INDEX($J:$J, MATCH(row_id, $X:$X, 0))) | Z53: =IF(is_empty, "", IF(is_header, "Tracked", INDEX($K:$K, MATCH(row_id, $X:$X, 0)))) | AA53: =IF(is_empty, "", IF(is_header, "Budget", INDEX($L:$L, MATCH(row_id, $X:$X, 0)))) | AB53: =IF(is_empty, "", IF(is_header, "% Compl.", IFERROR(out_tracked / out_budget, "-"))) | AC53: =IF(is_empty, "", IF(is_header, "Remaining", IF(out_budget - out_tracked > 0, out_budget - out_tracked, 0))) | AD53: =IF(is_empty, "", IF(is_header, "Excess", IF(out_budget - out_tracked < 0, out_tracked - out_budget, 0)))

Sheet Calculation
B1: Calculations
C6: Worksheet:Budget Tracking
D8: Today: | E8: {=current_date}
D9: Last Record: | E9: =MAX(tracking[Date])
D10: Delta Last Record: | E10: =IF(E9=0, "", "(" & _xlfn.DAYS(E8,E9) & " days ago)")
D11: # Records | E11: =COUNT(tracking[Date])
D12: # Records in the current year | E12: {="(" & SUMPRODUCT(--(YEAR(tracking[Date])=YEAR(current_date))) & " this year)"}
D13: Tracking Balance: | E13: =_xlfn.IFNA(INDEX(tracking[Balance], MATCH(E9, tracking[Date],0)), "-")
D14: Balance Analysis Text: | E14: =IF(E13>=0, "of tracked income left to be allocated", "allocated not covered by income")
C17: Worksheet: Budget Dashboard
D19: Selected Year: | E19: {=IF('Budget Dashboard'!$AQ$6="Current Year", YEAR(current_date), 'Budget Dashboard'!$AQ$6)}
D20: Selected Period: | E20: {=IF('Budget Dashboard'!$AQ$9="Total Year", "Total Year", IF('Budget Dashboard'!$AQ$9="Current Month", MONTH(current_date), MONTH('Budget Dashboard'!$AQ$9)))}
D21: Selected Period (Display): | E21: =IF(selected_period="Total Year", "Total Year", TEXT(DATE(selected_year, selected_period,1), "mmmm"))
D22: Days in Period: | E22: =IF(selected_period="Total Year", DATE(selected_year, 12, 31) - DATE(selected_year-1, 12, 31), DAY(EOMONTH(DATE(selected_year, selected_period, 1), 0)))
D23: Days passed in Period: | E23: {=IF(selected_year=YEAR(current_date), IF(selected_period="Total Year", current_date=DATE(selected_year-1, 12, 31), IF(selected_period=MONTH(current_date), DAY(current_date), IF(selected_period<MONTH(current_date), E22, 0))), IF(selected_year<YEAR(current_date), E22, 0))}
D24: Days passed in Period %: | E24: =E23/E22
D25: Period Tracking Balance: | E25: =F41 - (J41 + N41)
D26: Balance Analysis Text: | E26: =IF(E25>=0, "of tracked income left to be allocated", "allocated not covered by income")
D27: Period Savings Rate: | E27: =IFERROR(IF(savings_rate_calculation_type="% allocated to Savings", N41/F41, (F41-J41)/F41), "-")
D32: Chart Calculations: Category Distribution Charts
D34: Income | E34: Category | F34: Amount | H34: Expenses | I34: Category | J34: Amount | L34: Savings | M34: Category | N34: Amount
D35: 1 | E35: {=IF(F35="", "", INDEX('Budget Dashboard'!$J:$J, MATCH(income_header_row + D35, 'Budget Dashboard'!$X:$X, 0)))} | F35: {=IF(D35>COUNTA(income[]), "", IF(INDEX('Budget Dashboard'!$K:$K, MATCH(income_header_row + D35, 'Budget Dashboard'!$X:$X, 0))=0, "", INDEX('Budget Dashboard'!$K:$K, MATCH(income_header_row + D35, 'Budget Dashboard'!$X:$X, 0))))} | H35: 1 | I35: {=IF(J35="", "", INDEX('Budget Dashboard'!$J:$J, MATCH(expenses_header_row + H35, 'Budget Dashboard'!$X:$X, 0)))} | J35: {=IF(H35>COUNTA(expenses[]), "", IF(INDEX('Budget Dashboard'!$K:$K, MATCH(expenses_header_row + H35, 'Budget Dashboard'!$X:$X, 0))=0, "", INDEX('Budget Dashboard'!$K:$K, MATCH(expenses_header_row + H35, 'Budget Dashboard'!$X:$X, 0))))} | L35: 1 | M35: {=IF(N35="", "", INDEX('Budget Dashboard'!$J:$J, MATCH(savings_header_row + L35, 'Budget Dashboard'!$X:$X, 0)))} | N35: {=IF(L35>COUNTA(savings[]), "", IF(INDEX('Budget Dashboard'!$K:$K, MATCH(savings_header_row + L35, 'Budget Dashboard'!$X:$X, 0))=0, "", INDEX('Budget Dashboard'!$K:$K, MATCH(savings_header_row + L35, 'Budget Dashboard'!$X:$X, 0))))}
D36: 2 | E36: {=IF(F36="", "", INDEX('Budget Dashboard'!$J:$J, MATCH(income_header_row + D36, 'Budget Dashboard'!$X:$X, 0)))} | F36: {=IF(D36>COUNTA(income[]), "", IF(INDEX('Budget Dashboard'!$K:$K, MATCH(income_header_row + D36, 'Budget Dashboard'!$X:$X, 0))=0, "", INDEX('Budget Dashboard'!$K:$K, MATCH(income_header_row + D36, 'Budget Dashboard'!$X:$X, 0))))} | H36: 2 | I36: {=IF(J36="", "", INDEX('Budget Dashboard'!$J:$J, MATCH(expenses_header_row + H36, 'Budget Dashboard'!$X:$X, 0)))} | J36: {=IF(H36>COUNTA(expenses[]), "", IF(INDEX('Budget Dashboard'!$K:$K, MATCH(expenses_header_row + H36, 'Budget Dashboard'!$X:$X, 0))=0, "", INDEX('Budget Dashboard'!$K:$K, MATCH(expenses_header_row + H36, 'Budget Dashboard'!$X:$X, 0))))} | L36: 2 | M36: {=IF(N36="", "", INDEX('Budget Dashboard'!$J:$J, MATCH(savings_header_row + L36, 'Budget Dashboard'!$X:$X, 0)))} | N36: {=IF(L36>COUNTA(savings[]), "", IF(INDEX('Budget Dashboard'!$K:$K, MATCH(savings_header_row + L36, 'Budget Dashboard'!$X:$X, 0))=0, "", INDEX('Budget Dashboard'!$K:$K, MATCH(savings_header_row + L36, 'Budget Dashboard'!$X:$X, 0))))}
D37: 3 | E37: {=IF(F37="", "", INDEX('Budget Dashboard'!$J:$J, MATCH(income_header_row + D37, 'Budget Dashboard'!$X:$X, 0)))} | F37: {=IF(D37>COUNTA(income[]), "", IF(INDEX('Budget Dashboard'!$K:$K, MATCH(income_header_row + D37, 'Budget Dashboard'!$X:$X, 0))=0, "", INDEX('Budget Dashboard'!$K:$K, MATCH(income_header_row + D37, 'Budget Dashboard'!$X:$X, 0))))} | H37: 3 | I37: {=IF(J37="", "", INDEX('Budget Dashboard'!$J:$J, MATCH(expenses_header_row + H37, 'Budget Dashboard'!$X:$X, 0)))} | J37: {=IF(H37>COUNTA(expenses[]), "", IF(INDEX('Budget Dashboard'!$K:$K, MATCH(expenses_header_row + H37, 'Budget Dashboard'!$X:$X, 0))=0, "", INDEX('Budget Dashboard'!$K:$K, MATCH(expenses_header_row + H37, 'Budget Dashboard'!$X:$X, 0))))} | L37: 3 | M37: {=IF(N37="", "", INDEX('Budget Dashboard'!$J:$J, MATCH(savings_header_row + L37, 'Budget Dashboard'!$X:$X, 0)))} | N37: {=IF(L37>COUNTA(savings[]), "", IF(INDEX('Budget Dashboard'!$K:$K, MATCH(savings_header_row + L37, 'Budget Dashboard'!$X:$X, 0))=0, "", INDEX('Budget Dashboard'!$K:$K, MATCH(savings_header_row + L37, 'Budget Dashboard'!$X:$X, 0))))}
